Workbook
Name aaa: #REF!
Name ACRound: #REF!
Name BBIE: #REF!
Name BBIE: #REF!
Name bbie2: #REF!
Name bbie2: #REF!
Name BuiltIn_AutoFilter___1: #REF!
Name BuiltIn_AutoFilter___1: #REF!
Name LineRounding: #REF!
Name RoundTotal: #REF!
Name Tax: #REF!
Name TaxableAmRound: #REF!
Name TaxAmuRound: #REF!
Name TaxRate1: #REF!
Name TaxRate2: #REF!
Name TotalRounding: #REF!
Name ｘｘｘ: #REF!
Name ｘｘｘ: #REF!
Name あ: #REF!
Name あ: #REF!
Name ああ: #REF!
Name ああ: #REF!
Name あああ: #REF!
Name あああ: #REF!
Name 改訂履歴: #REF!
Name 改訂履歴: #REF!
Name 支払通知: #REF!
Name 支払通知: #REF!
Name 支払通知３: #REF!
Name 支払通知３: #REF!
Name 請求１: #REF!
Name 請求１: #REF!
Name 単一請求: #REF!
Name 単一請求: #REF!
Name 表紙１: #REF!
Name 表紙１: #REF!

Sheet JP-PINT
A1: ID | B1: business_term | C1: business_term_ja | D1: syn_card | E1: sem_card | F1: Xpath
A2: IBG-00 | B2: Invoice | C2: デジタルインボイス | E2: 1..1 | F2: /Invoice
A3: IBT-001 | B3: Invoice number | C3: 請求書番号 | D3: 1..1 | E3: 1..1 | F3: /Invoice/cbc:ID
A4: IBT-002 | B4: Invoice issue date | C4: 請求書発行日 | D4: 1..1 | E4: 1..1 | F4: /Invoice/cbc:IssueDate
A5: IBT-168 | B5: Invoice issue time | C5: 請求書発行時刻 | D5: 0..1 | E5: 0..1 | F5: /Invoice/cbc:IssueTime
A6: IBT-003 | B6: Invoice type code | C6: 請求書タイプコード | D6: 1..1 | E6: 1..1 | F6: /Invoice/cbc:InvoiceTypeCode
A7: IBT-005 | B7: Invoice currency code | C7: 請求書通貨コード | D7: 1..1 | E7: 1..1 | F7: /Invoice/cbc:DocumentCurrencyCode
A8: IBT-006 | B8: Tax accounting currency | C8: 税会計報告用通貨コード | D8: 0..1 | E8: 0..1 | F8: /Invoice/cbc:TaxCurrencyCode
A9: IBT-007 | B9: TAX point date | C9: 課税基準日 | D9: 0..1 | E9: 0..1 | F9: /Invoice/cbc:TaxPointDate
A10: IBT-008 | B10: TAX point date code | C10: 課税基準日コード | D10: 0..1 | E10: 0..1 | F10: /Invoice/cac:InvoicePeriod/cbc:DescriptionCode
A11: IBT-009 | B11: Payment due date | C11: 支払期日 | D11: 0..1 | E11: 0..1 | F11: /Invoice/cbc:DueDate
A12: IBT-010 | B12: Buyer reference | C12: 買い手参照 | D12: 0..1 | E12: 0..1 | F12: /Invoice/cbc:BuyerReference
A13: IBT-011 | B13: Project reference | C13: プロジェクト参照 | D13: 0..1 | E13: 1..1 | F13: /Invoice/cac:ProjectReference/cbc:ID
A14: IBT-012 | B14: Contract reference | C14: 契約書参照 | D14: 0..1 | E14: 1..1 | F14: /Invoice/cac:ContractDocumentReference/cbc:ID
... A22: IBT-019 | B22: Buyer accounting reference | C22: 買い手会計参照 | D22: 0..1 | E22: 0..1 | F22: /Invoice/cbc:AccountingCost
A23: IBG-02 | B23: PROCESS CONTROL | C23: プロセスコントロール | D23: 0..1 | E23: 1..1
A24: IBT-023 | B24: Business process type | C24: ビジネスプロセスタイプ | D24: 0..1 | E24: 1..1 | F24: /Invoice/cbc:ProfileID
A25: IBT-024 | B25: Specification identifier | C25: 仕様ID | D25: 0..1 | E25: 1..1 | F25: /Invoice/cbc:CustomizationID
A26: IBG-33 | B26: INVOICE TERMS | C26: 支払条件 | D26: 0..n | E26: 0..n | F26: /Invoice/cac:PaymentTerms
A27: IBT-187 | B27: > Terms payment instructions ID | C27: 支払条件指示ID | D27: 0..1 | E27: 0..1 | F27: /Invoice/cac:PaymentTerms/cbc:PaymentMeansID
A28: IBT-020 | B28: > Payment terms | C28: 支払条件 | D28: 0..1 | E28: 0..1 | F28: /Invoice/cac:PaymentTerms/cbc:Note
A29: IBT-176 | B29: > Terms amount | C29: 支払条件金額 | D29: 0..1 | E29: 0..1 | F29: /Invoice/cac:PaymentTerms/cbc:Amount
A30: IBT-177 | B30: > Terms installment due date | C30: 分割支払支払期日 | D30: 0..1 | E30: 0..1 | F30: /Invoice/cac:PaymentTerms/cbc:InstallmentDueDate
A31: IBT-022 | B31: Invoice note | C31: 請求書注釈内容 | D31: 0..1 | E31: 0..1 | F31: /Invoice/cbc:Note
A32: IBG-03 | B32: PRECEDING INVOICE REFERENCE | C32: 先行請求書への参照 | D32: 0..n | E32: 0..n | F32: /Invoice/cac:BillingReference
A33: IBT-025 | B33: > Preceding Invoice reference | C33: 先行請求書への参照 | D33: 1..1 | E33: 1..1 | F33: /Invoice/cac:BillingReference/cac:InvoiceDocumentReference/cbc:ID
A34: IBT-026 | B34: > Preceding Invoice issue date | C34: 先行請求書発行日 | D34: 0..1 | E34: 0..1 | F34: /Invoice/cac:BillingReference/cac:InvoiceDocumentReference/cbc:IssueDate
A35: IBG-04 | B35: SELLER | C35: 売り手 | D35: 1..1 | E35: 1..1 | F35: /Invoice/cac:AccountingSupplierParty
... A39: IBT-030 | B39: > Seller legal registration identifier | C39: 売り手法人ID | D39: 0..1 | E39: 0..1 | F39: /Invoice/cac:AccountingSupplierParty/cac:Party/cac:PartyLegalEntity/cbc:CompanyID
A40: IBT-031 | B40: > Seller TAX identifier | C40: 売り手税ID | D40: 0..1 | E40: 0 | F40: /Invoice/cac:AccountingSupplierParty/cac:Party/cac:PartyTaxScheme[cac:TaxScheme/cbc:ID='VAT']/cbc:CompanyID
A41: IBT-032 | B41: > Seller TAX registration identifier | C41: 売り手税登録ID | D41: 0..1 | E41: 1..1 | F41: /Invoice/cac:AccountingSupplierParty/cac:Party/cac:PartyTaxScheme[cac:TaxScheme/cbc:ID!='VAT']/cbc:CompanyID
A42: IBT-033 | B42: > Seller additional legal information | C42: 売り手追加法的情報 | D42: 0..1 | E42: 0..1 | F42: /Invoice/cac:AccountingSupplierParty/cac:Party/cac:PartyLegalEntity/cbc:CompanyLegalForm
A43: IBT-034 | B43: > Seller electronic address | C43: 売り手電子アドレス | D43: 1..1 | E43: 1..1 | F43: /Invoice/cac:AccountingSupplierParty/cac:Party/cbc:EndpointID
A44: IBT-034-1 | B44: >>Scheme identifier | C44: スキーマID | D44: 0..1 | E44: 1..1 | F44: /Invoice/cac:AccountingSupplierParty/cac:Party/cbc:EndpointID/@scemeID
A45: IBG-05 | B45: > SELLER POSTAL ADDRESS | C45: 売り手住所 | D45: 1..1 | E45: 1..1 | F45: /Invoice/cac:AccountingSupplierParty/cac:Party/cac:PostalAddress
A46: IBT-035 | B46: >> Seller address line 1 | C46: 売り手住所欄1 | D46: 0..1 | E46: 0..1 | F46: /Invoice/cac:AccountingSupplierParty/cac:Party/cac:PostalAddress/cbc:StreetName
A47: IBT-036 | B47: >> Seller address line 2 | C47: 売り手住所欄2 | D47: 0..1 | E47: 0..1 | F47: /Invoice/cac:AccountingSupplierParty/cac:Party/cac:PostalAddress/cbc:AdditionalStreetName
A48: IBT-162 | B48: >> Seller address line 3 | C48: 売り手住所欄3 | D48: 0..1 | E48: 1..1 | F48: /Invoice/cac:AccountingSupplierParty/cac:Party/cac:PostalAddress/cac:AddressLine/cbc:Line
A49: IBT-037 | B49: >> Seller city | C49: 売り手住所 市区町村 | D49: 0..1 | E49: 0..1 | F49: /Invoice/cac:AccountingSupplierParty/cac:Party/cac:PostalAddress/cbc:CityName
A50: IBT-038 | B50: >> Seller post code | C50: 売り手郵便番号 | D50: 0..1 | E50: 0..1 | F50: /Invoice/cac:AccountingSupplierParty/cac:Party/cac:PostalAddress/cbc:PostalZone
A51: IBT-039 | B51: >> Seller country subdivision | C51: 売り手住所 都道府県 | D51: 0..1 | E51: 0..1 | F51: /Invoice/cac:AccountingSupplierParty/cac:Party/cac:PostalAddress/cbc:CountrySubentity
A52: IBT-040 | B52: >> Seller country code | C52: 売り手国コード | D52: 1..1 | E52: 1..1 | F52: /Invoice/cac:AccountingSupplierParty/cac:Party/cac:PostalAddress/cac:Country/cbc:IdentificationCode
... A232: IBT-161 | B232: >>> Item attribute value | C232: 品目属性値 | D232: 1..1 | E232: 1..1 | F232: /Invoice/cac:InvoiceLine/cac:Item/cac:AdditionalItemProperty/cbc:Value

Sheet 仕入明細
C1: 行番号 | D1: 鑑ヘッダ/ 明細文書ヘッダ/明細行 | E1: GR/ID | F1: 項目名 | G1: 項目定義 | H1: 繰返し | I1: 制定/ 改定 | J1: 区分３ 統合 仕入明細 | K1: 区分２ 単一 仕入明細 | L1: 区分１ コア 仕入明細 | M1: 会計連携 | N1: v1.0 （参考） | P1: ヘッダ部/明細部 | Q1: 国連CEFACT 共通辞書ID | R1: 項目種 | S1: コード表ID | T1: コード表 管理者名 | U1: コード値 入力方法 | V1: 入力値 (コード定義値を入力) | Y1: Id | Z1: BusinesTerm | AA1: Card.
A2: =IF(ISTEXT(E2),_xlfn.XLOOKUP(E2,'[1]SME09-01_LHM'!$D:$D,'[1]SME09-01_LHM'!$B:$B)) -> 1 | B2: 1 | C2: =ROW()-25 -> -23 | D2: 鑑ヘッダ | E2: IV | F2: 仕入明細書 | H2: － | I2: v4/v4.3 | P2: ヘッダ部 | R2: MA | Y2: =_xlfn.LET(_xlpm.v,_xlfn.XLOOKUP(E2,'[1]SME09-01_LHM'!$D:$D,'[1]SME09-01_LHM'!$AL:$AL),IF(_xlpm.v=0,"",_xlpm.v)) | Z2: =_xlfn.LET(_xlpm.v,IF(ISTEXT(Y2),_xlfn.XLOOKUP(Y2,'JP-PINT'!A:A,'JP-PINT'!B:B),""),IF(ISERROR(_xlpm.v),"",_xlpm.v))
A3: =IF(ISTEXT(E3),_xlfn.XLOOKUP(E3,'[1]SME09-01_LHM'!$D:$D,'[1]SME09-01_LHM'!$B:$B)) -> 2 | B3: =_xlfn.XLOOKUP(F3,'[1]SME09-01_LHM'!$I:$I,'[1]SME09-01_LHM'!$B:$B) -> 2 | C3: =ROW()-25 -> -22 | D3: 鑑ヘッダ | E3: GR1 | F3: 取引設定グループ | G3: メッセージの設定内容に関する情報からなるグループ | H3: 0..1 | I3: v1 | J3: △ | K3: △ | L3: △ | P3: ヘッダ部 | Q3: UN01005479 | R3: ASMA | Y3: =_xlfn.LET(_xlpm.v,_xlfn.XLOOKUP(E3,'[1]SME09-01_LHM'!$D:$D,'[1]SME09-01_LHM'!$AL:$AL),IF(_xlpm.v=0,"",_xlpm.v)) | Z3: =_xlfn.LET(_xlpm.v,IF(ISTEXT(Y3),_xlfn.XLOOKUP(Y3,'JP-PINT'!A:A,'JP-PINT'!B:B),""),IF(ISERROR(_xlpm.v),"",_xlpm.v))
A4: =IF(ISTEXT(E4),_xlfn.XLOOKUP(E4,'[1]SME09-01_LHM'!$D:$D,'[1]SME09-01_LHM'!$B:$B)) -> 3 | B4: =_xlfn.XLOOKUP(F4,'[1]SME09-01_LHM'!$I:$I,'[1]SME09-01_LHM'!$B:$B) -> 3 | C4: =ROW()-25 -> -21 | D4: 鑑ヘッダ | E4: ID1 | F4: 取引ID | G4: メッセージがやり取りされる取引識別番号 | H4: 0..1 | I4: v1 | J4: △ | K4: △ | L4: △ | P4: ヘッダ部 | Q4: UN01005480 | R4: BBIE | Y4: =_xlfn.LET(_xlpm.v,_xlfn.XLOOKUP(E4,'[1]SME09-01_LHM'!$D:$D,'[1]SME09-01_LHM'!$AL:$AL),IF(_xlpm.v=0,"",_xlpm.v)) | Z4: =_xlfn.LET(_xlpm.v,IF(ISTEXT(Y4),_xlfn.XLOOKUP(Y4,'JP-PINT'!A:A,'JP-PINT'!B:B),""),IF(ISERROR(_xlpm.v),"",_xlpm.v))
A5: =IF(ISTEXT(E5),_xlfn.XLOOKUP(E5,'[1]SME09-01_LHM'!$D:$D,'[1]SME09-01_LHM'!$B:$B)) -> 4 | B5: =_xlfn.XLOOKUP(F5,'[1]SME09-01_LHM'!$I:$I,'[1]SME09-01_LHM'!$B:$B) -> 4 | C5: =ROW()-25 -> -20 | D5: 鑑ヘッダ | E5: ID2 | F5: 処理日時 | G5: メッセージがやり取りされる日時 | H5: 0..1 | I5: v1/v2 | J5: △ | K5: △ | L5: △ | P5: ヘッダ部 | Q5: UN01012746 | R5: BBIE | Y5: =_xlfn.LET(_xlpm.v,_xlfn.XLOOKUP(E5,'[1]SME09-01_LHM'!$D:$D,'[1]SME09-01_LHM'!$AL:$AL),IF(_xlpm.v=0,"",_xlpm.v)) | Z5: =_xlfn.LET(_xlpm.v,IF(ISTEXT(Y5),_xlfn.XLOOKUP(Y5,'JP-PINT'!A:A,'JP-PINT'!B:B),""),IF(ISERROR(_xlpm.v),"",_xlpm.v))
A6: =IF(ISTEXT(E6),_xlfn.XLOOKUP(E6,'[1]SME09-01_LHM'!$D:$D,'[1]SME09-01_LHM'!$B:$B)) -> 5 | B6: =_xlfn.XLOOKUP(F6,'[1]SME09-01_LHM'!$I:$I,'[1]SME09-01_LHM'!$B:$B) -> 5 | C6: =ROW()-25 -> -19 | D6: 鑑ヘッダ | E6: GR2 | F6: 取引設定内容/取引プロセスグループ | G6: 取引プロセスの識別番号 共通EDIプロバイダがプロセスをセットする | H6: 1..1 | I6: v1 | J6: △ | K6: △ | L6: △ | N6: ☆ | P6: ヘッダ部 | Q6: UN01005481 | R6: ASBIE | Y6: =_xlfn.LET(_xlpm.v,_xlfn.XLOOKUP(E6,'[1]SME09-01_LHM'!$D:$D,'[1]SME09-01_LHM'!$AL:$AL),IF(_xlpm.v=0,"",_xlpm.v)) -> IBG-02 | Z6: =_xlfn.LET(_xlpm.v,IF(ISTEXT(Y6),_xlfn.XLOOKUP(Y6,'JP-PINT'!A:A,'JP-PINT'!B:B),""),IF(ISERROR(_xlpm.v),"",_xlpm.v)) -> PROCESS CONTROL | AA6: 1..1
A7: =IF(ISTEXT(E7),_xlfn.XLOOKUP(E7,'[1]SME09-01_LHM'!$D:$D,'[1]SME09-01_LHM'!$B:$B)) -> 7 | B7: =_xlfn.XLOOKUP(F7,'[1]SME09-01_LHM'!$I:$I,'[1]SME09-01_LHM'!$B:$B) -> 7 | C7: =ROW()-25 -> -18 | D7: 鑑ヘッダ | E7: ID3 | F7: 取引プロセスID | G7: 取引プロセスの識別番号 共通EDIプロバイダがプロセスをセットする | H7: 0..1 | I7: v1 | J7: △ | K7: △ | L7: △ | N7: ☆ | P7: ヘッダ部 | Q7: UN01005472 | R7: BBIE | S7: JECxxxx | T7: JEC | U7: ID値 選択入力 | Y7: =_xlfn.LET(_xlpm.v,_xlfn.XLOOKUP(E7,'[1]SME09-01_LHM'!$D:$D,'[1]SME09-01_LHM'!$AL:$AL),IF(_xlpm.v=0,"",_xlpm.v)) -> IBT-023 | Z7: =_xlfn.LET(_xlpm.v,IF(ISTEXT(Y7),_xlfn.XLOOKUP(Y7,'JP-PINT'!A:A,'JP-PINT'!B:B),""),IF(ISERROR(_xlpm.v),"",_xlpm.v)) -> Business process type | AA7: 1..1
A8: =IF(ISTEXT(E8),_xlfn.XLOOKUP(E8,'[1]SME09-01_LHM'!$D:$D,'[1]SME09-01_LHM'!$B:$B)) -> 8 | B8: =_xlfn.XLOOKUP(F8,'[1]SME09-01_LHM'!$I:$I,'[1]SME09-01_LHM'!$B:$B) -> 8 | C8: =ROW()-25 -> -17 | D8: 鑑ヘッダ | E8: ID4 | F8: 取引プロセス名 | G8: 取引プロセスの名称 | H8: 0..1 | I8: v1 | J8: △ | K8: △ | L8: △ | P8: ヘッダ部 | Q8: UN01005473 | R8: BBIE | Y8: =_xlfn.LET(_xlpm.v,_xlfn.XLOOKUP(E8,'[1]SME09-01_LHM'!$D:$D,'[1]SME09-01_LHM'!$AL:$AL),IF(_xlpm.v=0,"",_xlpm.v)) | Z8: =_xlfn.LET(_xlpm.v,IF(ISTEXT(Y8),_xlfn.XLOOKUP(Y8,'JP-PINT'!A:A,'JP-PINT'!B:B),""),IF(ISERROR(_xlpm.v),"",_xlpm.v))
A9: =IF(ISTEXT(E9),_xlfn.XLOOKUP(E9,'[1]SME09-01_LHM'!$D:$D,'[1]SME09-01_LHM'!$B:$B)) -> 11 | B9: =_xlfn.XLOOKUP(F9,'[1]SME09-01_LHM'!$I:$I,'[1]SME09-01_LHM'!$B:$B) -> 11 | C9: =ROW()-25 -> -16 | D9: 鑑ヘッダ | E9: ID5 | F9: バージョンID | G9: 取引プロセスのバージョン識別番号 | H9: 0..1 | I9: v1 | J9: △ | K9: △ | L9: △ | N9: ☆ | P9: ヘッダ部 | Q9: UN01005476 | R9: BBIE | Y9: =_xlfn.LET(_xlpm.v,_xlfn.XLOOKUP(E9,'[1]SME09-01_LHM'!$D:$D,'[1]SME09-01_LHM'!$AL:$AL),IF(_xlpm.v=0,"",_xlpm.v)) -> IBT-024 | Z9: =_xlfn.LET(_xlpm.v,IF(ISTEXT(Y9),_xlfn.XLOOKUP(Y9,'JP-PINT'!A:A,'JP-PINT'!B:B),""),IF(ISERROR(_xlpm.v),"",_xlpm.v)) -> Specification identifier | AA9: 1..1
A10: =IF(ISTEXT(E10),_xlfn.XLOOKUP(E10,'[1]SME09-01_LHM'!$D:$D,'[1]SME09-01_LHM'!$B:$B)) -> 12 | B10: =_xlfn.XLOOKUP(F10,'[1]SME09-01_LHM'!$I:$I,'[1]SME09-01_LHM'!$B:$B) -> 12 | C10: =ROW()-25 -> -15 | D10: 鑑ヘッダ | E10: ID6 | F10: バージョン発行日 | G10: 取引プロセスのバージョン発行日 | H10: 0..1 | I10: v1 | J10: △ | K10: △ | L10: △ | P10: ヘッダ部 | Q10: UN01005478 | R10: BBIE | Y10: =_xlfn.LET(_xlpm.v,_xlfn.XLOOKUP(E10,'[1]SME09-01_LHM'!$D:$D,'[1]SME09-01_LHM'!$AL:$AL),IF(_xlpm.v=0,"",_xlpm.v)) | Z10: =_xlfn.LET(_xlpm.v,IF(ISTEXT(Y10),_xlfn.XLOOKUP(Y10,'JP-PINT'!A:A,'JP-PINT'!B:B),""),IF(ISERROR(_xlpm.v),"",_xlpm.v))
A11: =IF(ISTEXT(E11),_xlfn.XLOOKUP(E11,'[1]SME09-01_LHM'!$D:$D,'[1]SME09-01_LHM'!$B:$B)) -> 13 | B11: =_xlfn.XLOOKUP(F11,'[1]SME09-01_LHM'!$I:$I,'[1]SME09-01_LHM'!$B:$B) -> 13 | C11: =ROW()-25 -> -14 | D11: 鑑ヘッダ | E11: GR3 | F11: 取引設定内容/取引シナリオグループ | G11: 取引シナリオに関する情報のグループ | H11: 0..1 | I11: v1 | J11: △ | K11: △ | L11: △ | P11: ヘッダ部 | Q11: UN01005483 | R11: ASBIE | Y11: =_xlfn.LET(_xlpm.v,_xlfn.XLOOKUP(E11,'[1]SME09-01_LHM'!$D:$D,'[1]SME09-01_LHM'!$AL:$AL),IF(_xlpm.v=0,"",_xlpm.v)) | Z11: =_xlfn.LET(_xlpm.v,IF(ISTEXT(Y11),_xlfn.XLOOKUP(Y11,'JP-PINT'!A:A,'JP-PINT'!B:B),""),IF(ISERROR(_xlpm.v),"",_xlpm.v))
A12: =IF(ISTEXT(E12),_xlfn.XLOOKUP(E12,'[1]SME09-01_LHM'!$D:$D,'[1]SME09-01_LHM'!$B:$B)) -> 15 | B12: =_xlfn.XLOOKUP(F12,'[1]SME09-01_LHM'!$I:$I,'[1]SME09-01_LHM'!$B:$B) -> 15 | C12: =ROW()-25 -> -13 | D12: 鑑ヘッダ | E12: ID7 | F12: 取引シナリオID | G12: 取引シナリオの識別番号 | H12: 0..1 | I12: v1 | J12: △ | K12: △ | L12: △ | P12: ヘッダ部 | Q12: UN01005472 | R12: BBIE | Y12: =_xlfn.LET(_xlpm.v,_xlfn.XLOOKUP(E12,'[1]SME09-01_LHM'!$D:$D,'[1]SME09-01_LHM'!$AL:$AL),IF(_xlpm.v=0,"",_xlpm.v)) | Z12: =_xlfn.LET(_xlpm.v,IF(ISTEXT(Y12),_xlfn.XLOOKUP(Y12,'JP-PINT'!A:A,'JP-PINT'!B:B),""),IF(ISERROR(_xlpm.v),"",_xlpm.v))
A13: =IF(ISTEXT(E13),_xlfn.XLOOKUP(E13,'[1]SME09-01_LHM'!$D:$D,'[1]SME09-01_LHM'!$B:$B)) -> 16 | B13: =_xlfn.XLOOKUP(F13,'[1]SME09-01_LHM'!$I:$I,'[1]SME09-01_LHM'!$B:$B) -> 16 | C13: =ROW()-25 -> -12 | D13: 鑑ヘッダ | E13: ID8 | F13: 取引シナリオ名 | G13: 取引シナリオの名称 | H13: 0..1 | I13: v1 | J13: △ | K13: △ | L13: △ | P13: ヘッダ部 | Q13: UN01005473 | R13: BBIE | Y13: =_xlfn.LET(_xlpm.v,_xlfn.XLOOKUP(E13,'[1]SME09-01_LHM'!$D:$D,'[1]SME09-01_LHM'!$AL:$AL),IF(_xlpm.v=0,"",_xlpm.v)) | Z13: =_xlfn.LET(_xlpm.v,IF(ISTEXT(Y13),_xlfn.XLOOKUP(Y13,'JP-PINT'!A:A,'JP-PINT'!B:B),""),IF(ISERROR(_xlpm.v),"",_xlpm.v))
A14: =IF(ISTEXT(E14),_xlfn.XLOOKUP(E14,'[1]SME09-01_LHM'!$D:$D,'[1]SME09-01_LHM'!$B:$B)) -> 17 | B14: =_xlfn.XLOOKUP(F14,'[1]SME09-01_LHM'!$I:$I,'[1]SME09-01_LHM'!$B:$B) -> 17 | C14: =ROW()-25 -> -11 | D14: 鑑ヘッダ | E14: GR4 | F14: 取引設定内容/アプリケーショングループ | G14: アプリケーションに関する情報のグループ | H14: 0..1 | I14: v1 | J14: △ | K14: △ | L14: △ | P14: ヘッダ部 | Q14: UN01005484 | R14: ASBIE | Y14: =_xlfn.LET(_xlpm.v,_xlfn.XLOOKUP(E14,'[1]SME09-01_LHM'!$D:$D,'[1]SME09-01_LHM'!$AL:$AL),IF(_xlpm.v=0,"",_xlpm.v)) | Z14: =_xlfn.LET(_xlpm.v,IF(ISTEXT(Y14),_xlfn.XLOOKUP(Y14,'JP-PINT'!A:A,'JP-PINT'!B:B),""),IF(ISERROR(_xlpm.v),"",_xlpm.v))
A15: =IF(ISTEXT(E15),_xlfn.XLOOKUP(E15,'[1]SME09-01_LHM'!$D:$D,'[1]SME09-01_LHM'!$B:$B)) -> 19 | B15: =_xlfn.XLOOKUP(F15,'[1]SME09-01_LHM'!$I:$I,'[1]SME09-01_LHM'!$B:$B) -> 19 | C15: =ROW()-25 -> -10 | D15: 鑑ヘッダ | E15: ID9 | F15: アプリケーションID | G15: 業務アプリケーションが実装する業界・業種識別番号 | H15: 0..1 | I15: v1 | J15: △ | K15: △ | L15: △ | P15: ヘッダ部 | Q15: UN01005472 | R15: BBIE | Y15: =_xlfn.LET(_xlpm.v,_xlfn.XLOOKUP(E15,'[1]SME09-01_LHM'!$D:$D,'[1]SME09-01_LHM'!$AL:$AL),IF(_xlpm.v=0,"",_xlpm.v)) | Z15: =_xlfn.LET(_xlpm.v,IF(ISTEXT(Y15),_xlfn.XLOOKUP(Y15,'JP-PINT'!A:A,'JP-PINT'!B:B),""),IF(ISERROR(_xlpm.v),"",_xlpm.v))
A16: =IF(ISTEXT(E16),_xlfn.XLOOKUP(E16,'[1]SME09-01_LHM'!$D:$D,'[1]SME09-01_LHM'!$B:$B)) -> 20 | B16: =_xlfn.XLOOKUP(F16,'[1]SME09-01_LHM'!$I:$I,'[1]SME09-01_LHM'!$B:$B) -> 20 | C16: =ROW()-25 -> -9 | D16: 鑑ヘッダ | E16: ID10 | F16: アプリケーション名 | G16: 業務アプリケーションが実装する業界・業種名称 | H16: 0..1 | I16: v1 | J16: △ | K16: △ | L16: △ | P16: ヘッダ部 | Q16: UN01005473 | R16: BBIE | Y16: =_xlfn.LET(_xlpm.v,_xlfn.XLOOKUP(E16,'[1]SME09-01_LHM'!$D:$D,'[1]SME09-01_LHM'!$AL:$AL),IF(_xlpm.v=0,"",_xlpm.v)) | Z16: =_xlfn.LET(_xlpm.v,IF(ISTEXT(Y16),_xlfn.XLOOKUP(Y16,'JP-PINT'!A:A,'JP-PINT'!B:B),""),IF(ISERROR(_xlpm.v),"",_xlpm.v))
A17: =IF(ISTEXT(E17),_xlfn.XLOOKUP(E17,'[1]SME09-01_LHM'!$D:$D,'[1]SME09-01_LHM'!$B:$B)) -> 21 | B17: =_xlfn.XLOOKUP(F17,'[1]SME09-01_LHM'!$I:$I,'[1]SME09-01_LHM'!$B:$B) -> 21 | C17: =ROW()-25 -> -8 | D17: 鑑ヘッダ | E17: GR5 | F17: 取引設定内容/ドメイングループ | G17: SIPSのドメインに関する情報のグループ | H17: 1..1 | I17: v1 | J17: △ | K17: △ | L17: △ | P17: ヘッダ部 | Q17: UN01005486 | R17: ASBIE | Y17: =_xlfn.LET(_xlpm.v,_xlfn.XLOOKUP(E17,'[1]SME09-01_LHM'!$D:$D,'[1]SME09-01_LHM'!$AL:$AL),IF(_xlpm.v=0,"",_xlpm.v)) | Z17: =_xlfn.LET(_xlpm.v,IF(ISTEXT(Y17),_xlfn.XLOOKUP(Y17,'JP-PINT'!A:A,'JP-PINT'!B:B),""),IF(ISERROR(_xlpm.v),"",_xlpm.v))
A18: =IF(ISTEXT(E18),_xlfn.XLOOKUP(E18,'[1]SME09-01_LHM'!$D:$D,'[1]SME09-01_LHM'!$B:$B)) -> 23 | B18: =_xlfn.XLOOKUP(F18,'[1]SME09-01_LHM'!$I:$I,'[1]SME09-01_LHM'!$B:$B) -> 23 | C18: =ROW()-25 -> -7 | D18: 鑑ヘッダ | E18: ID11 | F18: ドメインID | G18: SIPSが付与したメッセージドメイン識別番号 中小企業共通EDIドメイン＝JPSSMED | H18: 0..1 | I18: v1 | J18: △ | K18: △ | L18: △ | P18: ヘッダ部 | Q18: UN01005472 | R18: BBIE | S18: JECxxxx | T18: JEC | U18: ID値 固定入力 | V18: JPSSMED | Y18: =_xlfn.LET(_xlpm.v,_xlfn.XLOOKUP(E18,'[1]SME09-01_LHM'!$D:$D,'[1]SME09-01_LHM'!$AL:$AL),IF(_xlpm.v=0,"",_xlpm.v)) | Z18: =_xlfn.LET(_xlpm.v,IF(ISTEXT(Y18),_xlfn.XLOOKUP(Y18,'JP-PINT'!A:A,'JP-PINT'!B:B),""),IF(ISERROR(_xlpm.v),"",_xlpm.v))
A19: =IF(ISTEXT(E19),_xlfn.XLOOKUP(E19,'[1]SME09-01_LHM'!$D:$D,'[1]SME09-01_LHM'!$B:$B)) -> 24 | B19: =_xlfn.XLOOKUP(F19,'[1]SME09-01_LHM'!$I:$I,'[1]SME09-01_LHM'!$B:$B) -> 24 | C19: =ROW()-25 -> -6 | D19: 鑑ヘッダ | E19: ID12 | F19: ドメイン名 | G19: SIPSが付与したメッセージドメイン名称 | H19: 0..1 | I19: v1 | J19: △ | K19: △ | L19: △ | P19: ヘッダ部 | Q19: UN01005473 | R19: BBIE | Y19: =_xlfn.LET(_xlpm.v,_xlfn.XLOOKUP(E19,'[1]SME09-01_LHM'!$D:$D,'[1]SME09-01_LHM'!$AL:$AL),IF(_xlpm.v=0,"",_xlpm.v)) | Z19: =_xlfn.LET(_xlpm.v,IF(ISTEXT(Y19),_xlfn.XLOOKUP(Y19,'JP-PINT'!A:A,'JP-PINT'!B:B),""),IF(ISERROR(_xlpm.v),"",_xlpm.v))
A20: =IF(ISTEXT(E20),_xlfn.XLOOKUP(E20,'[1]SME09-01_LHM'!$D:$D,'[1]SME09-01_LHM'!$B:$B)) -> 27 | B20: =_xlfn.XLOOKUP(F20,'[1]SME09-01_LHM'!$I:$I,'[1]SME09-01_LHM'!$B:$B) -> 11 | C20: =ROW()-25 -> -5 | D20: 鑑ヘッダ | E20: ID13 | F20: バージョンID | G20: ドメインのバージョン識別番号 | H20: 0..1 | I20: v1 | J20: △ | K20: △ | L20: △ | P20: ヘッダ部 | Q20: UN01005476 | R20: BBIE | Y20: =_xlfn.LET(_xlpm.v,_xlfn.XLOOKUP(E20,'[1]SME09-01_LHM'!$D:$D,'[1]SME09-01_LHM'!$AL:$AL),IF(_xlpm.v=0,"",_xlpm.v)) | Z20: =_xlfn.LET(_xlpm.v,IF(ISTEXT(Y20),_xlfn.XLOOKUP(Y20,'JP-PINT'!A:A,'JP-PINT'!B:B),""),IF(ISERROR(_xlpm.v),"",_xlpm.v))
A21: =IF(ISTEXT(E21),_xlfn.XLOOKUP(E21,'[1]SME09-01_LHM'!$D:$D,'[1]SME09-01_LHM'!$B:$B)) -> 28 | B21: =_xlfn.XLOOKUP(F21,'[1]SME09-01_LHM'!$I:$I,'[1]SME09-01_LHM'!$B:$B) -> 12 | C21: =ROW()-25 -> -4 | D21: 鑑ヘッダ | E21: ID14 | F21: バージョン発行日 | G21: ドメインのバージョン発行日 | H21: 0..1 | I21: v1 | J21: △ | K21: △ | L21: △ | P21: ヘッダ部 | Q21: UN01005478 | R21: BBIE | Y21: =_xlfn.LET(_xlpm.v,_xlfn.XLOOKUP(E21,'[1]SME09-01_LHM'!$D:$D,'[1]SME09-01_LHM'!$AL:$AL),IF(_xlpm.v=0,"",_xlpm.v)) | Z21: =_xlfn.LET(_xlpm.v,IF(ISTEXT(Y21),_xlfn.XLOOKUP(Y21,'JP-PINT'!A:A,'JP-PINT'!B:B),""),IF(ISERROR(_xlpm.v),"",_xlpm.v))
A22: =IF(ISTEXT(E22),_xlfn.XLOOKUP(E22,'[1]SME09-01_LHM'!$D:$D,'[1]SME09-01_LHM'!$B:$B)) -> 29 | B22: =_xlfn.XLOOKUP(F22,'[1]SME09-01_LHM'!$I:$I,'[1]SME09-01_LHM'!$B:$B) -> 29 | C22: =ROW()-25 -> -3 | D22: 鑑ヘッダ | E22: SIGR1 | F22: インボイス文書グループ | G22: インボイス文書に関する情報項目のグループ | H22: 1..1 | I22: v1 | J22: ○ | K22: ○ | L22: ○ | P22: ヘッダ部 | Q22: UN01005861 | R22: ASMA | W22: ASMA | X22: ASMA | Y22: =_xlfn.LET(_xlpm.v,_xlfn.XLOOKUP(E22,'[1]SME09-01_LHM'!$D:$D,'[1]SME09-01_LHM'!$AL:$AL),IF(_xlpm.v=0,"",_xlpm.v)) | Z22: =_xlfn.LET(_xlpm.v,IF(ISTEXT(Y22),_xlfn.XLOOKUP(Y22,'JP-PINT'!A:A,'JP-PINT'!B:B),""),IF(ISERROR(_xlpm.v),"",_xlpm.v))
A23: =IF(ISTEXT(E23),_xlfn.XLOOKUP(E23,'[1]SME09-01_LHM'!$D:$D,'[1]SME09-01_LHM'!$B:$B)) -> 30 | B23: =_xlfn.XLOOKUP(F23,'[1]SME09-01_LHM'!$I:$I,'[1]SME09-01_LHM'!$B:$B) -> 30 | C23: =ROW()-25 -> -2 | D23: 鑑ヘッダ | E23: SIID1 | F23: インボイス文書ID | G23: インボイス文書を識別する文書ID | H23: 1..1 | I23: v1/v3 | J23: ○ | K23: ○ | L23: ○ | M23: ※ | N23: ☆ | O23: ○ | P23: ヘッダ部 | Q23: UN01005862 | R23: BBIE | W23: BBIE | X23: BBIE | Y23: =_xlfn.LET(_xlpm.v,_xlfn.XLOOKUP(E23,'[1]SME09-01_LHM'!$D:$D,'[1]SME09-01_LHM'!$AL:$AL),IF(_xlpm.v=0,"",_xlpm.v)) -> IBT-001 | Z23: =_xlfn.LET(_xlpm.v,IF(ISTEXT(Y23),_xlfn.XLOOKUP(Y23,'JP-PINT'!A:A,'JP-PINT'!B:B),""),IF(ISERROR(_xlpm.v),"",_xlpm.v)) -> Invoice number | AA23: 1..1
A24: =IF(ISTEXT(E24),_xlfn.XLOOKUP(E24,'[1]SME09-01_LHM'!$D:$D,'[1]SME09-01_LHM'!$B:$B)) -> 31 | B24: =_xlfn.XLOOKUP(F24,'[1]SME09-01_LHM'!$I:$I,'[1]SME09-01_LHM'!$B:$B) -> 31 | C24: =ROW()-25 -> -1 | D24: 鑑ヘッダ | E24: SIID2 | F24: インボイス文書名 | G24: インボイス文書の文書名称 | H24: 0..1 | I24: v1 | J24: ＊ | K24: ＊ | L24: ＊ | P24: ヘッダ部 | Q24: UN01005863 | R24: BBIE | W24: BBIE | X24: BBIE | Y24: =_xlfn.LET(_xlpm.v,_xlfn.XLOOKUP(E24,'[1]SME09-01_LHM'!$D:$D,'[1]SME09-01_LHM'!$AL:$AL),IF(_xlpm.v=0,"",_xlpm.v)) | Z24: =_xlfn.LET(_xlpm.v,IF(ISTEXT(Y24),_xlfn.XLOOKUP(Y24,'JP-PINT'!A:A,'JP-PINT'!B:B),""),IF(ISERROR(_xlpm.v),"",_xlpm.v))
A25: =IF(ISTEXT(E25),_xlfn.XLOOKUP(E25,'[1]SME09-01_LHM'!$D:$D,'[1]SME09-01_LHM'!$B:$B)) -> 32 | B25: =_xlfn.XLOOKUP(F25,'[1]SME09-01_LHM'!$I:$I,'[1]SME09-01_LHM'!$B:$B) -> 32 | C25: =ROW()-25 -> 0 | D25: 鑑ヘッダ | E25: SIID3 | F25: インボイス文書タイプコード | G25: インボイス文書のタイプを識別するコード | H25: 0..1 | I25: v1 | J25: ● | K25: ● | L25: ● | N25: ☆ | P25: ヘッダ部 | Q25: UN01005864 | R25: BBIE | S25: UNCL1001 | T25: UN/CEFACT | U25: コード値 選択入力 | W25: BBIE | X25: BBIE | Y25: =_xlfn.LET(_xlpm.v,_xlfn.XLOOKUP(E25,'[1]SME09-01_LHM'!$D:$D,'[1]SME09-01_LHM'!$AL:$AL),IF(_xlpm.v=0,"",_xlpm.v)) -> IBT-003 | Z25: =_xlfn.LET(_xlpm.v,IF(ISTEXT(Y25),_xlfn.XLOOKUP(Y25,'JP-PINT'!A:A,'JP-PINT'!B:B),""),IF(ISERROR(_xlpm.v),"",_xlpm.v)) -> Invoice type code | AA25: 1..1
A26: =IF(ISTEXT(E26),_xlfn.XLOOKUP(E26,'[1]SME09-01_LHM'!$D:$D,'[1]SME09-01_LHM'!$B:$B)) -> 33 | B26: =_xlfn.XLOOKUP(F26,'[1]SME09-01_LHM'!$I:$I,'[1]SME09-01_LHM'!$B:$B) -> 33 | C26: =ROW()-25 -> 1 | D26: 鑑ヘッダ | E26: SIID4 | F26: インボイス文書発効日 | G26: インボイス文書の発行日付，またはインボイス文書の書面上の発行日付。 | H26: 1..1 | I26: v1/v3 | J26: ○ | K26: ○ | L26: ○ | M26: ― | N26: ☆ | O26: ○ | P26: ヘッダ部 | Q26: UN01005865 | R26: BBIE | W26: BBIE | X26: BBIE | Y26: =_xlfn.LET(_xlpm.v,_xlfn.XLOOKUP(E26,'[1]SME09-01_LHM'!$D:$D,'[1]SME09-01_LHM'!$AL:$AL),IF(_xlpm.v=0,"",_xlpm.v)) -> IBT-002 | Z26: =_xlfn.LET(_xlpm.v,IF(ISTEXT(Y26),_xlfn.XLOOKUP(Y26,'JP-PINT'!A:A,'JP-PINT'!B:B),""),IF(ISERROR(_xlpm.v),"",_xlpm.v)) -> Invoice issue date | AA26: 1..1
A27: =IF(ISTEXT(E27),_xlfn.XLOOKUP(E27,'[1]SME09-01_LHM'!$D:$D,'[1]SME09-01_LHM'!$B:$B)) -> 34 | B27: =_xlfn.XLOOKUP(F27,'[1]SME09-01_LHM'!$I:$I,'[1]SME09-01_LHM'!$B:$B) -> 34 | C27: =ROW()-25 -> 2 | D27: 鑑ヘッダ | E27: IID421 | F27: インボイス文書言語ID | G27: インボイス文書の言語ID | H27: 0..1 | I27: v4.3 | J27: ● | K27: ● | L27: ● | P27: ヘッダ部 | Q27: UN01005868 | R27: BBIE | S27: 言語コード ISO639 | T27: ISO | U27: コード値 選択入力 | V27: デフォルト '=JP | W27: BBIE | X27: BBIE | Y27: =_xlfn.LET(_xlpm.v,_xlfn.XLOOKUP(E27,'[1]SME09-01_LHM'!$D:$D,'[1]SME09-01_LHM'!$AL:$AL),IF(_xlpm.v=0,"",_xlpm.v)) | Z27: =_xlfn.LET(_xlpm.v,IF(ISTEXT(Y27),_xlfn.XLOOKUP(Y27,'JP-PINT'!A:A,'JP-PINT'!B:B),""),IF(ISERROR(_xlpm.v),"",_xlpm.v))
A28: =IF(ISTEXT(E28),_xlfn.XLOOKUP(E28,'[1]SME09-01_LHM'!$D:$D,'[1]SME09-01_LHM'!$B:$B)) -> 35 | B28: =_xlfn.XLOOKUP(F28,'[1]SME09-01_LHM'!$I:$I,'[1]SME09-01_LHM'!$B:$B) -> 35 | C28: =ROW()-25 -> 3 | D28: 鑑ヘッダ | E28: SIID5 | F28: インボイス文書目的コード | G28: 発注者がインボイス文書の目的（新規、変更、取消、打切り）を管理するために付番したコード | H28: 0..1 | I28: v2 | J28: ▼ | K28: ▼ | L28: ▼ | P28: ヘッダ部 | Q28: UN01005869 | R28: BBIE | S28: UNCL1225 | T28: UN/CEFACT | U28: コード値 選択入力 | V28: デフォルト＝９（新規） | W28: BBIE | X28: BBIE | Y28: =_xlfn.LET(_xlpm.v,_xlfn.XLOOKUP(E28,'[1]SME09-01_LHM'!$D:$D,'[1]SME09-01_LHM'!$AL:$AL),IF(_xlpm.v=0,"",_xlpm.v)) | Z28: =_xlfn.LET(_xlpm.v,IF(ISTEXT(Y28),_xlfn.XLOOKUP(Y28,'JP-PINT'!A:A,'JP-PINT'!B:B),""),IF(ISERROR(_xlpm.v),"",_xlpm.v))
A29: =IF(ISTEXT(E29),_xlfn.XLOOKUP(E29,'[1]SME09-01_LHM'!$D:$D,'[1]SME09-01_LHM'!$B:$B)) -> 36 | B29: =_xlfn.XLOOKUP(F29,'[1]SME09-01_LHM'!$I:$I,'[1]SME09-01_LHM'!$B:$B) -> 36 | C29: =ROW()-25 -> 4 | D29: 鑑ヘッダ | E29: SIID6 | F29: インボイス文書履歴ID | G29: インボイス文書の変更履歴を管理するID | H29: 0..1 | I29: v4 | J29: ▼ | K29: ▼ | L29: ▼ | P29: ヘッダ部 | Q29: UN01005874 | R29: BBIE | W29: BBIE | X29: BBIE | Y29: =_xlfn.LET(_xlpm.v,_xlfn.XLOOKUP(E29,'[1]SME09-01_LHM'!$D:$D,'[1]SME09-01_LHM'!$AL:$AL),IF(_xlpm.v=0,"",_xlpm.v)) | Z29: =_xlfn.LET(_xlpm.v,IF(ISTEXT(Y29),_xlfn.XLOOKUP(Y29,'JP-PINT'!A:A,'JP-PINT'!B:B),""),IF(ISERROR(_xlpm.v),"",_xlpm.v))
A30: =IF(ISTEXT(E30),_xlfn.XLOOKUP(E30,'[1]SME09-01_LHM'!$D:$D,'[1]SME09-01_LHM'!$B:$B)) -> 37 | B30: =_xlfn.XLOOKUP(F30,'[1]SME09-01_LHM'!$I:$I,'[1]SME09-01_LHM'!$B:$B) -> 37 | C30: =ROW()-25 -> 5 | D30: 鑑ヘッダ | E30: SIID7 | F30: インボイス文書類型コード | G30: インボイス文書の類型を識別するコード | H30: 0..1 | I30: v4 | J30: ● | K30: ● | L30: ● | P30: ヘッダ部 | Q30: UN01005875 | R30: BBIE | S30: JECxxxx | T30: JEC | U30: コード値 選択入力 | W30: BBIE | X30: BBIE | Y30: =_xlfn.LET(_xlpm.v,_xlfn.XLOOKUP(E30,'[1]SME09-01_LHM'!$D:$D,'[1]SME09-01_LHM'!$AL:$AL),IF(_xlpm.v=0,"",_xlpm.v)) | Z30: =_xlfn.LET(_xlpm.v,IF(ISTEXT(Y30),_xlfn.XLOOKUP(Y30,'JP-PINT'!A:A,'JP-PINT'!B:B),""),IF(ISERROR(_xlpm.v),"",_xlpm.v))
A31: =IF(ISTEXT(E31),_xlfn.XLOOKUP(E31,'[1]SME09-01_LHM'!$D:$D,'[1]SME09-01_LHM'!$B:$B)) -> 38 | B31: =_xlfn.XLOOKUP(F31,'[1]SME09-01_LHM'!$I:$I,'[1]SME09-01_LHM'!$B:$B) -> 38 | C31: =ROW()-25 -> 6 | D31: 鑑ヘッダ | E31: SIID8 | F31: インボイス文書サブタイプコード | G31: 地域固有の文書のタイプを識別するコード | H31: 0..1 | I31: v4 | J31: ● | K31: ● | L31: ● | P31: ヘッダ部 | Q31: UN01014636 | R31: BBIE | S31: JECxxxx | T31: JEC | U31: コード値 選択入力 | V31: デフォルト＝38002 （コア仕入明細書） | W31: BBIE | X31: BBIE | Y31: =_xlfn.LET(_xlpm.v,_xlfn.XLOOKUP(E31,'[1]SME09-01_LHM'!$D:$D,'[1]SME09-01_LHM'!$AL:$AL),IF(_xlpm.v=0,"",_xlpm.v)) | Z31: =_xlfn.LET(_xlpm.v,IF(ISTEXT(Y31),_xlfn.XLOOKUP(Y31,'JP-PINT'!A:A,'JP-PINT'!B:B),""),IF(ISERROR(_xlpm.v),"",_xlpm.v))
A32: =IF(ISTEXT(E32),_xlfn.XLOOKUP(E32,'[1]SME09-01_LHM'!$D:$D,'[1]SME09-01_LHM'!$B:$B)) -> 0 | B32: =_xlfn.XLOOKUP(F32,'[1]SME09-01_LHM'!$I:$I,'[1]SME09-01_LHM'!$B:$B) -> 0 | C32: =ROW()-25 -> 7 | D32: 鑑ヘッダ | E32: SIID801 | F32: 鑑ヘッダ回答タイプコード | G32: 受注者の仕入明細回答書に対する発注者の回答に利用 鑑ヘッダ回答書の回答タイプを示すコード。 回答タイプは一括確認、部分確認、一括不可 デフォルトは一括確認 部分確認の場合は明細文書または明細行の回答タイプコードを利用して確認不可の項目を指定する | H32: 0..1 | I32: v4 | J32: ＊ | K32: ＊ | L32: ＊ | P32: ヘッダ部 | Q32: UN01015491 | R32: BBIE | S32: UNCL4343 | T32: UN/CEFACT | U32: コード値 選択入力 | V32: デフォルト＝AP （一括確認回答） | W32: BBIE | X32: BBIE | Y32: =_xlfn.LET(_xlpm.v,_xlfn.XLOOKUP(E32,'[1]SME09-01_LHM'!$D:$D,'[1]SME09-01_LHM'!$AL:$AL),IF(_xlpm.v=0,"",_xlpm.v)) | Z32: =_xlfn.LET(_xlpm.v,IF(ISTEXT(Y32),_xlfn.XLOOKUP(Y32,'JP-PINT'!A:A,'JP-PINT'!B:B),""),IF(ISERROR(_xlpm.v),"",_xlpm.v))
A33: =IF(ISTEXT(E33),_xlfn.XLOOKUP(E33,'[1]SME09-01_LHM'!$D:$D,'[1]SME09-01_LHM'!$B:$B)) -> 39 | B33: =_xlfn.XLOOKUP(F33,'[1]SME09-01_LHM'!$I:$I,'[1]SME09-01_LHM'!$B:$B) -> 39 | C33: =ROW()-25 -> 8 | D33: 鑑ヘッダ | E33: SIGR2 | F33: インボイス文書／注釈グループ | G33: インボイス文書の注釈を記述するためのグループ | H33: 0..n | I33: v1 | J33: ＊ | K33: ＊ | L33: ＊ | P33: ヘッダ部 | Q33: UN01005876 | R33: ASBIE | W33: ASBIE | X33: ASBIE | Y33: =_xlfn.LET(_xlpm.v,_xlfn.XLOOKUP(E33,'[1]SME09-01_LHM'!$D:$D,'[1]SME09-01_LHM'!$AL:$AL),IF(_xlpm.v=0,"",_xlpm.v)) | Z33: =_xlfn.LET(_xlpm.v,IF(ISTEXT(Y33),_xlfn.XLOOKUP(Y33,'JP-PINT'!A:A,'JP-PINT'!B:B),""),IF(ISERROR(_xlpm.v),"",_xlpm.v))
A34: =IF(ISTEXT(E34),_xlfn.XLOOKUP(E34,'[1]SME09-01_LHM'!$D:$D,'[1]SME09-01_LHM'!$B:$B)) -> 41 | B34: =_xlfn.XLOOKUP(F34,'[1]SME09-01_LHM'!$I:$I,'[1]SME09-01_LHM'!$B:$B) -> 41 | C34: =ROW()-25 -> 9 | D34: 鑑ヘッダ | E34: SIID9 | F34: インボイス文書注釈表題 | G34: 注釈内容の表題を示す。 | H34: 0..1 | I34: v1 | J34: ＊ | K34: ＊ | L34: ＊ | P34: ヘッダ部 | Q34: UN01005558 | R34: BBIE | W34: BBIE | X34: BBIE | Y34: =_xlfn.LET(_xlpm.v,_xlfn.XLOOKUP(E34,'[1]SME09-01_LHM'!$D:$D,'[1]SME09-01_LHM'!$AL:$AL),IF(_xlpm.v=0,"",_xlpm.v)) | Z34: =_xlfn.LET(_xlpm.v,IF(ISTEXT(Y34),_xlfn.XLOOKUP(Y34,'JP-PINT'!A:A,'JP-PINT'!B:B),""),IF(ISERROR(_xlpm.v),"",_xlpm.v))
A35: =IF(ISTEXT(E35),_xlfn.XLOOKUP(E35,'[1]SME09-01_LHM'!$D:$D,'[1]SME09-01_LHM'!$B:$B)) -> 42 | B35: =_xlfn.XLOOKUP(F35,'[1]SME09-01_LHM'!$I:$I,'[1]SME09-01_LHM'!$B:$B) -> 42 | C35: =ROW()-25 -> 10 | D35: 鑑ヘッダ | E35: SIID10 | F35: インボイス文書注釈内容 | G35: 注釈項目毎の内容情報を入力するフリースペース。 | H35: 0..1 | I35: v1 | J35: ＊ | K35: ＊ | L35: ＊ | M35: ※ | N35: ★ | P35: ヘッダ部 | Q35: UN01005560 | R35: BBIE | W35: BBIE | X35: BBIE | Y35: =_xlfn.LET(_xlpm.v,_xlfn.XLOOKUP(E35,'[1]SME09-01_LHM'!$D:$D,'[1]SME09-01_LHM'!$AL:$AL),IF(_xlpm.v=0,"",_xlpm.v)) -> IBT-022 | Z35: =_xlfn.LET(_xlpm.v,IF(ISTEXT(Y35),_xlfn.XLOOKUP(Y35,'JP-PINT'!A:A,'JP-PINT'!B:B),""),IF(ISERROR(_xlpm.v),"",_xlpm.v)) -> Invoice note | AA35: 0..1
A36: =IF(ISTEXT(E36),_xlfn.XLOOKUP(E36,'[1]SME09-01_LHM'!$D:$D,'[1]SME09-01_LHM'!$B:$B)) -> 43 | B36: =_xlfn.XLOOKUP(F36,'[1]SME09-01_LHM'!$I:$I,'[1]SME09-01_LHM'!$B:$B) -> 43 | C36: =ROW()-25 -> 11 | D36: 鑑ヘッダ | E36: SIID11 | F36: インボイス文書注釈ID | G36: 注釈の識別ID | H36: 0..1 | I36: v1 | J36: △ | K36: △ | L36: △ | P36: ヘッダ部 | Q36: UN01005562 | R36: BBIE | W36: BBIE | X36: BBIE | Y36: =_xlfn.LET(_xlpm.v,_xlfn.XLOOKUP(E36,'[1]SME09-01_LHM'!$D:$D,'[1]SME09-01_LHM'!$AL:$AL),IF(_xlpm.v=0,"",_xlpm.v)) | Z36: =_xlfn.LET(_xlpm.v,IF(ISTEXT(Y36),_xlfn.XLOOKUP(Y36,'JP-PINT'!A:A,'JP-PINT'!B:B),""),IF(ISERROR(_xlpm.v),"",_xlpm.v))
A37: =IF(ISTEXT(E37),_xlfn.XLOOKUP(E37,'[1]SME09-01_LHM'!$D:$D,'[1]SME09-01_LHM'!$B:$B)) -> 43.1 | B37: =_xlfn.XLOOKUP(F37,'[1]SME09-01_LHM'!$I:$I,'[1]SME09-01_LHM'!$B:$B) -> 43.1 | C37: =ROW()-25 -> 12 | D37: 鑑ヘッダ | E37: SIGR3 | F37: インボイス文書／参照文書グループ | G37: インボイス文書が参照する文書グループ | H37: 0..n | I37: v4 | J37: ● | K37: ● | L37: ● | N37: ★ | P37: ヘッダ部 | Q37: UN01012702 | R37: ASBIE | W37: ASBIE | X37: ASBIE | Y37: =_xlfn.LET(_xlpm.v,_xlfn.XLOOKUP(E37,'[1]SME09-01_LHM'!$D:$D,'[1]SME09-01_LHM'!$AL:$AL),IF(_xlpm.v=0,"",_xlpm.v)) -> IBG-03 | Z37: =_xlfn.LET(_xlpm.v,IF(ISTEXT(Y37),_xlfn.XLOOKUP(Y37,'JP-PINT'!A:A,'JP-PINT'!B:B),""),IF(ISERROR(_xlpm.v),"",_xlpm.v)) -> PRECEDING INVOICE REFERENCE | AA37: 0..n
A38: =IF(ISTEXT(E38),_xlfn.XLOOKUP(E38,'[1]SME09-01_LHM'!$D:$D,'[1]SME09-01_LHM'!$B:$B)) -> 43.3 | B38: =_xlfn.XLOOKUP(F38,'[1]SME09-01_LHM'!$I:$I,'[1]SME09-01_LHM'!$B:$B) -> 43.3 | C38: =ROW()-25 -> 13 | D38: 鑑ヘッダ | E38: SIID12 | F38: （鑑ヘッダ参照）文書ID | G38: インボイス文書が参照する参照文書のID | H38: 1..1 | I38: v4 | J38: ○ | K38: ○ | L38: ○ | N38: ☆ | P38: ヘッダ部 | Q38: UN01005580 | R38: BBIE | W38: BBIE | X38: BBIE | Y38: =_xlfn.LET(_xlpm.v,_xlfn.XLOOKUP(E38,'[1]SME09-01_LHM'!$D:$D,'[1]SME09-01_LHM'!$AL:$AL),IF(_xlpm.v=0,"",_xlpm.v)) -> IBT-025 | Z38: =_xlfn.LET(_xlpm.v,IF(ISTEXT(Y38),_xlfn.XLOOKUP(Y38,'JP-PINT'!A:A,'JP-PINT'!B:B),""),IF(ISERROR(_xlpm.v),"",_xlpm.v)) -> > Preceding Invoice reference | AA38: 1..1
A39: =IF(ISTEXT(E39),_xlfn.XLOOKUP(E39,'[1]SME09-01_LHM'!$D:$D,'[1]SME09-01_LHM'!$B:$B)) -> 47 | B39: =_xlfn.XLOOKUP(F39,'[1]SME09-01_LHM'!$I:$I,'[1]SME09-01_LHM'!$B:$B) -> 47 | C39: =ROW()-25 -> 14 | D39: 鑑ヘッダ | E39: SIID404 | F39: （鑑ヘッダ参照）文書URL_ID | G39: インボイス文書が参照する文書が所在するURL_ID | H39: 0..1 | I39: v4.2 | J39: ＊ | K39: ＊ | L39: ＊ | P39: ヘッダ部 | Q39: UN01005581 | R39: BBIE | W39: BBIE | X39: BBIE | Y39: =_xlfn.LET(_xlpm.v,_xlfn.XLOOKUP(E39,'[1]SME09-01_LHM'!$D:$D,'[1]SME09-01_LHM'!$AL:$AL),IF(_xlpm.v=0,"",_xlpm.v)) -> IBT-124 | Z39: =_xlfn.LET(_xlpm.v,IF(ISTEXT(Y39),_xlfn.XLOOKUP(Y39,'JP-PINT'!A:A,'JP-PINT'!B:B),""),IF(ISERROR(_xlpm.v),"",_xlpm.v)) -> > External document location | AA39: 0,,1
A40: =IF(ISTEXT(E40),_xlfn.XLOOKUP(E40,'[1]SME09-01_LHM'!$D:$D,'[1]SME09-01_LHM'!$B:$B)) -> 43.4 | B40: =_xlfn.XLOOKUP(F40,'[1]SME09-01_LHM'!$I:$I,'[1]SME09-01_LHM'!$B:$B) -> 43.4 | C40: =ROW()-25 -> 15 | D40: 鑑ヘッダ | E40: SIID13 | F40: （鑑ヘッダ参照）文書発行日 | G40: インボイス文書が参照する参照文書の発行日 | H40: 0..1 | I40: v4 | J40: ＊ | K40: ＊ | L40: ＊ | P40: ヘッダ部 | Q40: UN01005582 | R40: BBIE | W40: BBIE | X40: BBIE | Y40: =_xlfn.LET(_xlpm.v,_xlfn.XLOOKUP(E40,'[1]SME09-01_LHM'!$D:$D,'[1]SME09-01_LHM'!$AL:$AL),IF(_xlpm.v=0,"",_xlpm.v)) -> IBT-026 | Z40: =_xlfn.LET(_xlpm.v,IF(ISTEXT(Y40),_xlfn.XLOOKUP(Y40,'JP-PINT'!A:A,'JP-PINT'!B:B),""),IF(ISERROR(_xlpm.v),"",_xlpm.v)) -> > Preceding Invoice issue date
A41: =IF(ISTEXT(E41),_xlfn.XLOOKUP(E41,'[1]SME09-01_LHM'!$D:$D,'[1]SME09-01_LHM'!$B:$B)) -> 43.5 | B41: =_xlfn.XLOOKUP(F41,'[1]SME09-01_LHM'!$I:$I,'[1]SME09-01_LHM'!$B:$B) -> 43.5 | C41: =ROW()-25 -> 16 | D41: 鑑ヘッダ | E41: SIID14 | F41: （鑑ヘッダ参照）文書参照タイプコード | G41: この調整で参照するインボイス文書の参照タイプを指定するコード | H41: 0..1 | I41: v4.1 | J41: ● | K41: ● | L41: ● | P41: ヘッダ部 | Q41: UN01005586 | R41: BBIE | S41: UNCL1153 | T41: UN/CEFACT | U41: コード値 選択入力 | V41: '＝OI (Previous invoice number)（デフォルト） ＝OH（Current invoice number） | W41: BBIE | X41: BBIE | Y41: =_xlfn.LET(_xlpm.v,_xlfn.XLOOKUP(E41,'[1]SME09-01_LHM'!$D:$D,'[1]SME09-01_LHM'!$AL:$AL),IF(_xlpm.v=0,"",_xlpm.v)) | Z41: =_xlfn.LET(_xlpm.v,IF(ISTEXT(Y41),_xlfn.XLOOKUP(Y41,'JP-PINT'!A:A,'JP-PINT'!B:B),""),IF(ISERROR(_xlpm.v),"",_xlpm.v))
A42: =IF(ISTEXT(E42),_xlfn.XLOOKUP(E42,'[1]SME09-01_LHM'!$D:$D,'[1]SME09-01_LHM'!$B:$B)) -> 50 | B42: =_xlfn.XLOOKUP(F42,'[1]SME09-01_LHM'!$I:$I,'[1]SME09-01_LHM'!$B:$B) -> 50 | C42: =ROW()-25 -> 17 | D42: 鑑ヘッダ | E42: SIID15 | F42: （鑑ヘッダ参照）文書履歴ID | G42: インボイス文書が参照する文書の変更履歴を管理するID。 | H42: 0..1 | I42: v4 | J42: ＊ | K42: ＊ | L42: ＊ | P42: ヘッダ部 | Q42: UN01005588 | R42: BBIE | W42: BBIE | X42: BBIE | Y42: =_xlfn.LET(_xlpm.v,_xlfn.XLOOKUP(E42,'[1]SME09-01_LHM'!$D:$D,'[1]SME09-01_LHM'!$AL:$AL),IF(_xlpm.v=0,"",_xlpm.v)) | Z42: =_xlfn.LET(_xlpm.v,IF(ISTEXT(Y42),_xlfn.XLOOKUP(Y42,'JP-PINT'!A:A,'JP-PINT'!B:B),""),IF(ISERROR(_xlpm.v),"",_xlpm.v))
A43: =IF(ISTEXT(E43),_xlfn.XLOOKUP(E43,'[1]SME09-01_LHM'!$D:$D,'[1]SME09-01_LHM'!$B:$B)) -> 51 | B43: =_xlfn.XLOOKUP(F43,'[1]SME09-01_LHM'!$I:$I,'[1]SME09-01_LHM'!$B:$B) -> 51 | C43: =ROW()-25 -> 18 | D43: 鑑ヘッダ | E43: SIID405 | F43: （鑑ヘッダ参照）文書情報 | G43: インボイス文書が参照する参照文書に記載の情報 | H43: 0..1 | I43: v4.2 | J43: ＊ | K43: ＊ | L43: ＊ | N43: ★ | P43: ヘッダ部 | Q43: UN01006415 | R43: BBIE | W43: BBIE | X43: BBIE | Y43: =_xlfn.LET(_xlpm.v,_xlfn.XLOOKUP(E43,'[1]SME09-01_LHM'!$D:$D,'[1]SME09-01_LHM'!$AL:$AL),IF(_xlpm.v=0,"",_xlpm.v)) -> IBT-123 | Z43: =_xlfn.LET(_xlpm.v,IF(ISTEXT(Y43),_xlfn.XLOOKUP(Y43,'JP-PINT'!A:A,'JP-PINT'!B:B),""),IF(ISERROR(_xlpm.v),"",_xlpm.v)) -> > Supporting document description | AA43: 0..1
A44: =IF(ISTEXT(E44),_xlfn.XLOOKUP(E44,'[1]SME09-01_LHM'!$D:$D,'[1]SME09-01_LHM'!$B:$B)) -> 52 | B44: =_xlfn.XLOOKUP(F44,'[1]SME09-01_LHM'!$I:$I,'[1]SME09-01_LHM'!$B:$B) -> 52 | C44: =ROW()-25 -> 19 | D44: 鑑ヘッダ | E44: SIID16 | F44: （鑑ヘッダ参照）文書タイプコード | G44: インボイス文書が参照する参照文書の文書タイプを識別するコード | H44: 0..1 | I44: v4 | J44: ＊ | K44: ＊ | L44: ＊ | P44: ヘッダ部 | Q44: UN01009672 | R44: BBIE | S44: UNCL1001 | T44: UN/CEFACT | W44: BBIE | X44: BBIE | Y44: =_xlfn.LET(_xlpm.v,_xlfn.XLOOKUP(E44,'[1]SME09-01_LHM'!$D:$D,'[1]SME09-01_LHM'!$AL:$AL),IF(_xlpm.v=0,"",_xlpm.v)) | Z44: =_xlfn.LET(_xlpm.v,IF(ISTEXT(Y44),_xlfn.XLOOKUP(Y44,'JP-PINT'!A:A,'JP-PINT'!B:B),""),IF(ISERROR(_xlpm.v),"",_xlpm.v))
A45: =IF(ISTEXT(E45),_xlfn.XLOOKUP(E45,'[1]SME09-01_LHM'!$D:$D,'[1]SME09-01_LHM'!$B:$B)) -> 54.7 | B45: =_xlfn.XLOOKUP(F45,'[1]SME09-01_LHM'!$I:$I,'[1]SME09-01_LHM'!$B:$B) -> 54.7 | C45: =ROW()-25 -> 20 | D45: 鑑ヘッダ | E45: SIID18 | F45: （鑑ヘッダ参照）文書サブタイプコード | G45: インボイス文書が参照する参照文書の文書サブタイプを識別するコード | H45: 0..1 | I45: v4 | J45: ＊ | K45: ＊ | L45: ＊ | P45: ヘッダ部 | Q45: UN01014899 | R45: BBIE | S45: JECxxxx | T45: JEC | W45: BBIE | X45: BBIE | Y45: =_xlfn.LET(_xlpm.v,_xlfn.XLOOKUP(E45,'[1]SME09-01_LHM'!$D:$D,'[1]SME09-01_LHM'!$AL:$AL),IF(_xlpm.v=0,"",_xlpm.v)) | Z45: =_xlfn.LET(_xlpm.v,IF(ISTEXT(Y45),_xlfn.XLOOKUP(Y45,'JP-PINT'!A:A,'JP-PINT'!B:B),""),IF(ISERROR(_xlpm.v),"",_xlpm.v))
A46: =IF(ISTEXT(E46),_xlfn.XLOOKUP(E46,'[1]SME09-01_LHM'!$D:$D,'[1]SME09-01_LHM'!$B:$B)) -> 55 | B46: =_xlfn.XLOOKUP(F46,'[1]SME09-01_LHM'!$I:$I,'[1]SME09-01_LHM'!$B:$B) -> 55 | C46: =ROW()-25 -> 21 | D46: 鑑ヘッダ | E46: SIGR4 | F46: インボイス文書／添付ファイルグループ | G46: 添付バイナリファイルを記述するためのグループ | H46: 0..n | I46: v4 | J46: ＊ | K46: ＊ | L46: ＊ | N46: ★ | P46: ヘッダ部 | Q46: UN01015490 | R46: ASBIE | W46: ASBIE | X46: ASBIE | Y46: =_xlfn.LET(_xlpm.v,_xlfn.XLOOKUP(E46,'[1]SME09-01_LHM'!$D:$D,'[1]SME09-01_LHM'!$AL:$AL),IF(_xlpm.v=0,"",_xlpm.v)) -> IBT-125 | Z46: =_xlfn.LET(_xlpm.v,IF(ISTEXT(Y46),_xlfn.XLOOKUP(Y46,'JP-PINT'!A:A,'JP-PINT'!B:B),""),IF(ISERROR(_xlpm.v),"",_xlpm.v)) -> > Attached document | AA46: 0..1
A47: =IF(ISTEXT(E47),_xlfn.XLOOKUP(E47,'[1]SME09-01_LHM'!$D:$D,'[1]SME09-01_LHM'!$B:$B)) -> 57 | B47: =_xlfn.XLOOKUP(F47,'[1]SME09-01_LHM'!$I:$I,'[1]SME09-01_LHM'!$B:$B) -> 57 | C47: =ROW()-25 -> 22 | D47: 鑑ヘッダ | E47: SIID19 | F47: 添付バイナリファイルID | G47: 添付バイナリファイルのID | H47: 0..1 | I47: v4 | J47: ＊ | K47: ＊ | L47: ＊ | P47: ヘッダ部 | Q47: UN01006015 | R47: BBIE | W47: BBIE | X47: BBIE | Y47: =_xlfn.LET(_xlpm.v,_xlfn.XLOOKUP(E47,'[1]SME09-01_LHM'!$D:$D,'[1]SME09-01_LHM'!$AL:$AL),IF(_xlpm.v=0,"",_xlpm.v)) | Z47: =_xlfn.LET(_xlpm.v,IF(ISTEXT(Y47),_xlfn.XLOOKUP(Y47,'JP-PINT'!A:A,'JP-PINT'!B:B),""),IF(ISERROR(_xlpm.v),"",_xlpm.v))
A48: =IF(ISTEXT(E48),_xlfn.XLOOKUP(E48,'[1]SME09-01_LHM'!$D:$D,'[1]SME09-01_LHM'!$B:$B)) -> 0 | B48: =_xlfn.XLOOKUP(F48,'[1]SME09-01_LHM'!$I:$I,'[1]SME09-01_LHM'!$B:$B) -> 0 | C48: =ROW()-25 -> 23 | D48: 鑑ヘッダ | E48: SIID502 | F48: 添付バイナリファイル版数 | G48: 添付バイナリファイルのバージョンID | H48: 0..1 | I48: v4 | J48: ＊ | K48: ＊ | L48: ＊ | P48: ヘッダ部 | Q48: UN01006018 | R48: BBIE | W48: BBIE | X48: BBIE | Y48: =_xlfn.LET(_xlpm.v,_xlfn.XLOOKUP(E48,'[1]SME09-01_LHM'!$D:$D,'[1]SME09-01_LHM'!$AL:$AL),IF(_xlpm.v=0,"",_xlpm.v)) | Z48: =_xlfn.LET(_xlpm.v,IF(ISTEXT(Y48),_xlfn.XLOOKUP(Y48,'JP-PINT'!A:A,'JP-PINT'!B:B),""),IF(ISERROR(_xlpm.v),"",_xlpm.v))
A49: =IF(ISTEXT(E49),_xlfn.XLOOKUP(E49,'[1]SME09-01_LHM'!$D:$D,'[1]SME09-01_LHM'!$B:$B)) -> 59 | B49: =_xlfn.XLOOKUP(F49,'[1]SME09-01_LHM'!$I:$I,'[1]SME09-01_LHM'!$B:$B) -> 59 | C49: =ROW()-25 -> 24 | D49: 鑑ヘッダ | E49: SIID20 | F49: 添付バイナリファイル名 | G49: 添付バイナリファイルの名称 | H49: 0..1 | I49: v4 | J49: ＊ | K49: ＊ | L49: ＊ | N49: ☆ | P49: ヘッダ部 | Q49: UN01006019 | R49: BBIE | W49: BBIE | X49: BBIE | Y49: =_xlfn.LET(_xlpm.v,_xlfn.XLOOKUP(E49,'[1]SME09-01_LHM'!$D:$D,'[1]SME09-01_LHM'!$AL:$AL),IF(_xlpm.v=0,"",_xlpm.v)) -> IBT-125-2 | Z49: =_xlfn.LET(_xlpm.v,IF(ISTEXT(Y49),_xlfn.XLOOKUP(Y49,'JP-PINT'!A:A,'JP-PINT'!B:B),""),IF(ISERROR(_xlpm.v),"",_xlpm.v)) -> >> Attached document Filename | AA49: 1..1
A50: =IF(ISTEXT(E50),_xlfn.XLOOKUP(E50,'[1]SME09-01_LHM'!$D:$D,'[1]SME09-01_LHM'!$B:$B)) -> 60 | B50: =_xlfn.XLOOKUP(F50,'[1]SME09-01_LHM'!$I:$I,'[1]SME09-01_LHM'!$B:$B) -> 60 | C50: =ROW()-25 -> 25 | D50: 鑑ヘッダ | E50: SIID21 | F50: 添付バイナリファイルURI ID | G50: 添付バイナリファイルの保管URSIID | H50: 0..1 | I50: v4 | J50: ＊ | K50: ＊ | L50: ＊ | P50: ヘッダ部 | Q50: UN01006020 | R50: BBIE | W50: BBIE | X50: BBIE | Y50: =_xlfn.LET(_xlpm.v,_xlfn.XLOOKUP(E50,'[1]SME09-01_LHM'!$D:$D,'[1]SME09-01_LHM'!$AL:$AL),IF(_xlpm.v=0,"",_xlpm.v)) | Z50: =_xlfn.LET(_xlpm.v,IF(ISTEXT(Y50),_xlfn.XLOOKUP(Y50,'JP-PINT'!A:A,'JP-PINT'!B:B),""),IF(ISERROR(_xlpm.v),"",_xlpm.v))
A51: =IF(ISTEXT(E51),_xlfn.XLOOKUP(E51,'[1]SME09-01_LHM'!$D:$D,'[1]SME09-01_LHM'!$B:$B)) -> 61 | B51: =_xlfn.XLOOKUP(F51,'[1]SME09-01_LHM'!$I:$I,'[1]SME09-01_LHM'!$B:$B) -> 61 | C51: =ROW()-25 -> 26 | D51: 鑑ヘッダ | E51: SIID22 | F51: 添付バイナリファイルのMIMEコード | G51: 添付バイナリファイルのMIMEコード | H51: 0..1 | I51: v4 | J51: ＊ | K51: ＊ | L51: ＊ | N51: ☆ | P51: ヘッダ部 | Q51: UN01006021 | R51: BBIE | S51: RFC1341 | T51: IETF | W51: BBIE | X51: BBIE | Y51: =_xlfn.LET(_xlpm.v,_xlfn.XLOOKUP(E51,'[1]SME09-01_LHM'!$D:$D,'[1]SME09-01_LHM'!$AL:$AL),IF(_xlpm.v=0,"",_xlpm.v)) -> IBT-125-1 | Z51: =_xlfn.LET(_xlpm.v,IF(ISTEXT(Y51),_xlfn.XLOOKUP(Y51,'JP-PINT'!A:A,'JP-PINT'!B:B),""),IF(ISERROR(_xlpm.v),"",_xlpm.v)) -> >> Attached document Mime code | AA51: 1..1
A52: =IF(ISTEXT(E52),_xlfn.XLOOKUP(E52,'[1]SME09-01_LHM'!$D:$D,'[1]SME09-01_LHM'!$B:$B)) -> 0 | B52: =_xlfn.XLOOKUP(F52,'[1]SME09-01_LHM'!$I:$I,'[1]SME09-01_LHM'!$B:$B) -> 0 | C52: =ROW()-25 -> 27 | D52: 鑑ヘッダ | E52: SIID503 | F52: 添付バイナリファイルエンコードコード | G52: 添付バイナリファイルのエンコード用コード | H52: 0..1 | I52: v4 | J52: ＊ | K52: ＊ | L52: ＊ | P52: ヘッダ部 | Q52: UN01006022 | R52: BBIE | W52: BBIE | X52: BBIE | Y52: =_xlfn.LET(_xlpm.v,_xlfn.XLOOKUP(E52,'[1]SME09-01_LHM'!$D:$D,'[1]SME09-01_LHM'!$AL:$AL),IF(_xlpm.v=0,"",_xlpm.v)) | Z52: =_xlfn.LET(_xlpm.v,IF(ISTEXT(Y52),_xlfn.XLOOKUP(Y52,'JP-PINT'!A:A,'JP-PINT'!B:B),""),IF(ISERROR(_xlpm.v),"",_xlpm.v))
A53: =IF(ISTEXT(E53),_xlfn.XLOOKUP(E53,'[1]SME09-01_LHM'!$D:$D,'[1]SME09-01_LHM'!$B:$B)) -> 0 | B53: =_xlfn.XLOOKUP(F53,'[1]SME09-01_LHM'!$I:$I,'[1]SME09-01_LHM'!$B:$B) -> 0 | C53: =ROW()-25 -> 28 | D53: 鑑ヘッダ | E53: SIID504 | F53: 添付バイナリファイル出力コード | G53: 添付バイナリファイルの出力コード | H53: 0..1 | I53: v4 | J53: ＊ | K53: ＊ | L53: ＊ | P53: ヘッダ部 | Q53: UN01006024 | R53: BBIE | W53: BBIE | X53: BBIE | Y53: =_xlfn.LET(_xlpm.v,_xlfn.XLOOKUP(E53,'[1]SME09-01_LHM'!$D:$D,'[1]SME09-01_LHM'!$AL:$AL),IF(_xlpm.v=0,"",_xlpm.v)) | Z53: =_xlfn.LET(_xlpm.v,IF(ISTEXT(Y53),_xlfn.XLOOKUP(Y53,'JP-PINT'!A:A,'JP-PINT'!B:B),""),IF(ISERROR(_xlpm.v),"",_xlpm.v))
A54: =IF(ISTEXT(E54),_xlfn.XLOOKUP(E54,'[1]SME09-01_LHM'!$D:$D,'[1]SME09-01_LHM'!$B:$B)) -> 64 | B54: =_xlfn.XLOOKUP(F54,'[1]SME09-01_LHM'!$I:$I,'[1]SME09-01_LHM'!$B:$B) -> 64 | C54: =ROW()-25 -> 29 | D54: 鑑ヘッダ | E54: SIID23 | F54: 添付バイナリファイルの説明文 | G54: 添付バイナリファイルの説明文 | H54: 0..1 | I54: v4 | J54: ＊ | K54: ＊ | L54: ＊ | P54: ヘッダ部 | Q54: UN01006026 | R54: BBIE | W54: BBIE | X54: BBIE | Y54: =_xlfn.LET(_xlpm.v,_xlfn.XLOOKUP(E54,'[1]SME09-01_LHM'!$D:$D,'[1]SME09-01_LHM'!$AL:$AL),IF(_xlpm.v=0,"",_xlpm.v)) | Z54: =_xlfn.LET(_xlpm.v,IF(ISTEXT(Y54),_xlfn.XLOOKUP(Y54,'JP-PINT'!A:A,'JP-PINT'!B:B),""),IF(ISERROR(_xlpm.v),"",_xlpm.v))
A55: =IF(ISTEXT(E55),_xlfn.XLOOKUP(E55,'[1]SME09-01_LHM'!$D:$D,'[1]SME09-01_LHM'!$B:$B)) -> 68 | B55: =_xlfn.XLOOKUP(F55,'[1]SME09-01_LHM'!$I:$I,'[1]SME09-01_LHM'!$B:$B) -> 68 | C55: =ROW()-25 -> 30 | D55: 鑑ヘッダ | E55: IGR5 | F55: インボイス文書契約／受注者グループ | G55: 受注者に関する情報からなるグループ。 | H55: 1..1 | I55: v1 | J55: ○ | K55: ○ | L55: ○ | N55: ☆ | P55: ヘッダ部 | Q55: UN01005879 | R55: ASBIE | W55: ASBIE | X55: ASBIE | Y55: =_xlfn.LET(_xlpm.v,_xlfn.XLOOKUP(E55,'[1]SME09-01_LHM'!$D:$D,'[1]SME09-01_LHM'!$AL:$AL),IF(_xlpm.v=0,"",_xlpm.v)) -> IBG-04 | Z55: =_xlfn.LET(_xlpm.v,IF(ISTEXT(Y55),_xlfn.XLOOKUP(Y55,'JP-PINT'!A:A,'JP-PINT'!B:B),""),IF(ISERROR(_xlpm.v),"",_xlpm.v)) -> SELLER | AA55: 1..1
A56: =IF(ISTEXT(E56),_xlfn.XLOOKUP(E56,'[1]SME09-01_LHM'!$D:$D,'[1]SME09-01_LHM'!$B:$B)) -> 70 | B56: =_xlfn.XLOOKUP(F56,'[1]SME09-01_LHM'!$I:$I,'[1]SME09-01_LHM'!$B:$B) -> 70 | C56: =ROW()-25 -> 31 | D56: 鑑ヘッダ | E56: IID24 | F56: 受注者ID | G56: 注文を受ける企業/工場・事業所・事業部門等を表すID。デフォルトはデータなし。 | H56: 0..1 | I56: v1 | J56: ＊ | K56: ＊ | L56: ＊ | M56: ※ | N56: ★ | P56: ヘッダ部 | Q56: UN01005757 | R56: BBIE | W56: BBIE | X56: BBIE | Y56: =_xlfn.LET(_xlpm.v,_xlfn.XLOOKUP(E56,'[1]SME09-01_LHM'!$D:$D,'[1]SME09-01_LHM'!$AL:$AL),IF(_xlpm.v=0,"",_xlpm.v)) -> IBT-029 | Z56: =_xlfn.LET(_xlpm.v,IF(ISTEXT(Y56),_xlfn.XLOOKUP(Y56,'JP-PINT'!A:A,'JP-PINT'!B:B),""),IF(ISERROR(_xlpm.v),"",_xlpm.v)) -> > Seller identifier | AA56: 0..n
A57: =IF(ISTEXT(E57),_xlfn.XLOOKUP(E57,'[1]SME09-01_LHM'!$D:$D,'[1]SME09-01_LHM'!$B:$B)) -> 71 | B57: =_xlfn.XLOOKUP(F57,'[1]SME09-01_LHM'!$I:$I,'[1]SME09-01_LHM'!$B:$B) -> 71 | C57: =ROW()-25 -> 32 | D57: 鑑ヘッダ | E57: IID25 | F57: 受注者国際企業ID | G57: 企業を表す国際企業ID。ISO6523に登録された国際企業登録機関を属性で指定する。 | H57: 0..1 | I57: v1 | J57: ＊ | K57: ＊ | L57: ＊ | N57: ★ | P57: ヘッダ部 | Q57: UN01005758 | R57: BBIE | S57: ISO6523 | T57: ISO | U57: 属性コード値 選択入力 | V57: 6523企業ID/＠ 6523企業コード発番機関コード値 | W57: BBIE | X57: BBIE | Y57: =_xlfn.LET(_xlpm.v,_xlfn.XLOOKUP(E57,'[1]SME09-01_LHM'!$D:$D,'[1]SME09-01_LHM'!$AL:$AL),IF(_xlpm.v=0,"",_xlpm.v)) -> IBT-030 | Z57: =_xlfn.LET(_xlpm.v,IF(ISTEXT(Y57),_xlfn.XLOOKUP(Y57,'JP-PINT'!A:A,'JP-PINT'!B:B),""),IF(ISERROR(_xlpm.v),"",_xlpm.v)) -> > Seller legal registration identifier | AA57: 0..1
A58: =IF(ISTEXT(E58),_xlfn.XLOOKUP(E58,'[1]SME09-01_LHM'!$D:$D,'[1]SME09-01_LHM'!$B:$B)) -> 72 | B58: =_xlfn.XLOOKUP(F58,'[1]SME09-01_LHM'!$I:$I,'[1]SME09-01_LHM'!$B:$B) -> 72 | C58: =ROW()-25 -> 33 | D58: 鑑ヘッダ | E58: IID26 | F58: 受注者名称 | G58: 注文を受ける企業/工場・事業所・事業部門等を表す名称。仕入明細書を交付される事業者名。 | H58: 0..1 | I58: v1 | J58: ◎ | K58: ◎ | L58: ◎ | M58: ※ | N58: ☆ | O58: ○ | P58: ヘッダ部 | Q58: UN01005759 | R58: BBIE | W58: BBIE | X58: BBIE | Y58: =_xlfn.LET(_xlpm.v,_xlfn.XLOOKUP(E58,'[1]SME09-01_LHM'!$D:$D,'[1]SME09-01_LHM'!$AL:$AL),IF(_xlpm.v=0,"",_xlpm.v)) -> IBT-027 | Z58: =_xlfn.LET(_xlpm.v,IF(ISTEXT(Y58),_xlfn.XLOOKUP(Y58,'JP-PINT'!A:A,'JP-PINT'!B:B),""),IF(ISERROR(_xlpm.v),"",_xlpm.v)) -> > Seller name | AA58: 1..1
A59: =IF(ISTEXT(E59),_xlfn.XLOOKUP(E59,'[1]SME09-01_LHM'!$D:$D,'[1]SME09-01_LHM'!$B:$B)) -> 100.3 | B59: =_xlfn.XLOOKUP(F59,'[1]SME09-01_LHM'!$I:$I,'[1]SME09-01_LHM'!$B:$B) -> 100.3 | C59: =ROW()-25 -> 34 | D59: 鑑ヘッダ | E59: IID27 | F59: 受注者適格請求書発行事業者登録番号 | G59: 国税庁へ登録された適格請求書発行事業者登録番号（区分記載請求書発行者についてはなし） T1234567890123 | H59: 0..1 | I59: v4 | J59: ◎ | K59: ◎ | L59: ◎ | M59: ※ | N59: ☆ | O59: ○ | P59: ヘッダ部 | Q59: UN01013039 | R59: BBIE | S59: ISO6523 | T59: ISO | U59: 属性コード値 固定入力 | V59: 6523企業ID/＠ 6523国際アドレス登録機関コード値 ＝0221（デジタル庁） | W59: BBIE | X59: BBIE | Y59: =_xlfn.LET(_xlpm.v,_xlfn.XLOOKUP(E59,'[1]SME09-01_LHM'!$D:$D,'[1]SME09-01_LHM'!$AL:$AL),IF(_xlpm.v=0,"",_xlpm.v)) -> IBT-031 | Z59: =_xlfn.LET(_xlpm.v,IF(ISTEXT(Y59),_xlfn.XLOOKUP(Y59,'JP-PINT'!A:A,'JP-PINT'!B:B),""),IF(ISERROR(_xlpm.v),"",_xlpm.v)) -> > Seller TAX identifier | AA59: 1..1
A60: 107 | B60: =_xlfn.XLOOKUP(F60,'[1]SME09-01_LHM'!$I:$I,'[1]SME09-01_LHM'!$B:$B) -> #N/A | C60: =ROW()-25 -> 35 | D60: 鑑ヘッダ | E60: IID28 | F60: 受注者タイプコード | G60: 適格請求書発行事業者のタイプを識別するコード | H60: 0..1 | I60: v4.1 | J60: ＊ | K60: ＊ | L60: ＊ | P60: ヘッダ部 | Q60: UN01012925 | R60: BBIE | S60: JECxxxx | T60: JEC | W60: BBIE | X60: BBIE | Y60: =_xlfn.LET(_xlpm.v,_xlfn.XLOOKUP(E60,'[1]SME09-01_LHM'!$D:$D,'[1]SME09-01_LHM'!$AL:$AL),IF(_xlpm.v=0,"",_xlpm.v)) -> #N/A | Z60: =_xlfn.LET(_xlpm.v,IF(ISTEXT(Y60),_xlfn.XLOOKUP(Y60,'JP-PINT'!A:A,'JP-PINT'!B:B),""),IF(ISERROR(_xlpm.v),"",_xlpm.v))
A61: =IF(ISTEXT(E61),_xlfn.XLOOKUP(E61,'[1]SME09-01_LHM'!$D:$D,'[1]SME09-01_LHM'!$B:$B)) -> 75 | B61: =_xlfn.XLOOKUP(F61,'[1]SME09-01_LHM'!$I:$I,'[1]SME09-01_LHM'!$B:$B) -> 75 | C61: =ROW()-25 -> 36 | D61: 鑑ヘッダ | E61: IGR6 | F61: 受注者／連絡先グループ | G61: 連絡先に関する情報からなるグループ。 | H61: 0..1 | I61: v1 | J61: ＊ | K61: ＊ | L61: ＊ | N61: ★ | P61: ヘッダ部 | Q61: UN01005761 | R61: ASBIE | W61: ASBIE | X61: ASBIE | Y61: =_xlfn.LET(_xlpm.v,_xlfn.XLOOKUP(E61,'[1]SME09-01_LHM'!$D:$D,'[1]SME09-01_LHM'!$AL:$AL),IF(_xlpm.v=0,"",_xlpm.v)) -> IBG-06 | Z61: =_xlfn.LET(_xlpm.v,IF(ISTEXT(Y61),_xlfn.XLOOKUP(Y61,'JP-PINT'!A:A,'JP-PINT'!B:B),""),IF(ISERROR(_xlpm.v),"",_xlpm.v)) -> > SELLER CONTACT | AA61: 0..1
A62: =IF(ISTEXT(E62),_xlfn.XLOOKUP(E62,'[1]SME09-01_LHM'!$D:$D,'[1]SME09-01_LHM'!$B:$B)) -> 77 | B62: =_xlfn.XLOOKUP(F62,'[1]SME09-01_LHM'!$I:$I,'[1]SME09-01_LHM'!$B:$B) -> 77 | C62: =ROW()-25 -> 37 | D62: 鑑ヘッダ | E62: IID29 | F62: 受注部門ID | G62: 受注者の受注部門を表すID。 | H62: 0..1 | I62: v1 | J62: ＊ | K62: ＊ | L62: ＊ | P62: ヘッダ部 | Q62: UN01005719 | R62: BBIE | W62: BBIE | X62: BBIE | Y62: =_xlfn.LET(_xlpm.v,_xlfn.XLOOKUP(E62,'[1]SME09-01_LHM'!$D:$D,'[1]SME09-01_LHM'!$AL:$AL),IF(_xlpm.v=0,"",_xlpm.v)) | Z62: =_xlfn.LET(_xlpm.v,IF(ISTEXT(Y62),_xlfn.XLOOKUP(Y62,'JP-PINT'!A:A,'JP-PINT'!B:B),""),IF(ISERROR(_xlpm.v),"",_xlpm.v))
A63: =IF(ISTEXT(E63),_xlfn.XLOOKUP(E63,'[1]SME09-01_LHM'!$D:$D,'[1]SME09-01_LHM'!$B:$B)) -> 78 | B63: =_xlfn.XLOOKUP(F63,'[1]SME09-01_LHM'!$I:$I,'[1]SME09-01_LHM'!$B:$B) -> 78 | C63: =ROW()-25 -> 38 | D63: 鑑ヘッダ | E63: IID30 | F63: 受注者担当名 | G63: 受注者連絡先の個人の、文字で表現された名前。 | H63: 0..1 | I63: v1 | J63: ＊ | K63: ＊ | L63: ＊ | N63: （★） | P63: ヘッダ部 | Q63: UN01005720 | R63: BBIE | W63: BBIE | X63: BBIE | Y63: =_xlfn.LET(_xlpm.v,_xlfn.XLOOKUP(E63,'[1]SME09-01_LHM'!$D:$D,'[1]SME09-01_LHM'!$AL:$AL),IF(_xlpm.v=0,"",_xlpm.v)) -> IBT-041 | Z63: =_xlfn.LET(_xlpm.v,IF(ISTEXT(Y63),_xlfn.XLOOKUP(Y63,'JP-PINT'!A:A,'JP-PINT'!B:B),""),IF(ISERROR(_xlpm.v),"",_xlpm.v)) -> >> Seller contact point | AA63: 0..1
A64: =IF(ISTEXT(E64),_xlfn.XLOOKUP(E64,'[1]SME09-01_LHM'!$D:$D,'[1]SME09-01_LHM'!$B:$B)) -> 79 | B64: =_xlfn.XLOOKUP(F64,'[1]SME09-01_LHM'!$I:$I,'[1]SME09-01_LHM'!$B:$B) -> 79 | C64: =ROW()-25 -> 39 | D64: 鑑ヘッダ | E64: IID31 | F64: 受注者部門名 | G64: 受注者の受注部門の名称。 | H64: 0..1 | I64: v1 | J64: ＊ | K64: ＊ | L64: ＊ | N64: （★） | P64: ヘッダ部 | Q64: UN01005721 | R64: BBIE | W64: BBIE | X64: BBIE | Y64: =_xlfn.LET(_xlpm.v,_xlfn.XLOOKUP(E64,'[1]SME09-01_LHM'!$D:$D,'[1]SME09-01_LHM'!$AL:$AL),IF(_xlpm.v=0,"",_xlpm.v)) -> IBT-041 | Z64: =_xlfn.LET(_xlpm.v,IF(ISTEXT(Y64),_xlfn.XLOOKUP(Y64,'JP-PINT'!A:A,'JP-PINT'!B:B),""),IF(ISERROR(_xlpm.v),"",_xlpm.v)) -> >> Seller contact point | AA64: 0..1
A65: =IF(ISTEXT(E65),_xlfn.XLOOKUP(E65,'[1]SME09-01_LHM'!$D:$D,'[1]SME09-01_LHM'!$B:$B)) -> 80 | B65: =_xlfn.XLOOKUP(F65,'[1]SME09-01_LHM'!$I:$I,'[1]SME09-01_LHM'!$B:$B) -> 80 | C65: =ROW()-25 -> 40 | D65: 鑑ヘッダ | E65: IID32 | F65: 受注者担当ID | G65: 受注者個人を表すID | H65: 0..1 | I65: v4 | J65: ＊ | K65: ＊ | L65: ＊ | P65: ヘッダ部 | Q65: UN01005725 | R65: BBIE | W65: BBIE | X65: BBIE | Y65: =_xlfn.LET(_xlpm.v,_xlfn.XLOOKUP(E65,'[1]SME09-01_LHM'!$D:$D,'[1]SME09-01_LHM'!$AL:$AL),IF(_xlpm.v=0,"",_xlpm.v)) | Z65: =_xlfn.LET(_xlpm.v,IF(ISTEXT(Y65),_xlfn.XLOOKUP(Y65,'JP-PINT'!A:A,'JP-PINT'!B:B),""),IF(ISERROR(_xlpm.v),"",_xlpm.v))
A66: =IF(ISTEXT(E66),_xlfn.XLOOKUP(E66,'[1]SME09-01_LHM'!$D:$D,'[1]SME09-01_LHM'!$B:$B)) -> 83 | B66: =_xlfn.XLOOKUP(F66,'[1]SME09-01_LHM'!$I:$I,'[1]SME09-01_LHM'!$B:$B) -> 83 | C66: =ROW()-25 -> 41 | D66: 鑑ヘッダ | E66: IID33 | F66: 受注者電話番号 | G66: 受注者の電話番号。 | H66: 0..1 | I66: v1 | J66: ＊ | K66: ＊ | L66: ＊ | N66: ★ | P66: ヘッダ部 | Q66: UN01005860 | R66: BBIE | W66: BBIE | X66: BBIE | Y66: =_xlfn.LET(_xlpm.v,_xlfn.XLOOKUP(E66,'[1]SME09-01_LHM'!$D:$D,'[1]SME09-01_LHM'!$AL:$AL),IF(_xlpm.v=0,"",_xlpm.v)) -> IBT-042 | Z66: =_xlfn.LET(_xlpm.v,IF(ISTEXT(Y66),_xlfn.XLOOKUP(Y66,'JP-PINT'!A:A,'JP-PINT'!B:B),""),IF(ISERROR(_xlpm.v),"",_xlpm.v)) -> >> Seller contact telephone number | AA66: 0..1
A67: =IF(ISTEXT(E67),_xlfn.XLOOKUP(E67,'[1]SME09-01_LHM'!$D:$D,'[1]SME09-01_LHM'!$B:$B)) -> 86 | B67: =_xlfn.XLOOKUP(F67,'[1]SME09-01_LHM'!$I:$I,'[1]SME09-01_LHM'!$B:$B) -> 86 | C67: =ROW()-25 -> 42 | D67: 鑑ヘッダ | E67: IID34 | F67: 受注者FAX番号 | G67: 受注者のFAX番号 | H67: 0..1 | I67: v1 | J67: ＊ | K67: ＊ | L67: ＊ | P67: ヘッダ部 | Q67: UN01005860 | R67: BBIE | W67: BBIE | X67: BBIE | Y67: =_xlfn.LET(_xlpm.v,_xlfn.XLOOKUP(E67,'[1]SME09-01_LHM'!$D:$D,'[1]SME09-01_LHM'!$AL:$AL),IF(_xlpm.v=0,"",_xlpm.v)) | Z67: =_xlfn.LET(_xlpm.v,IF(ISTEXT(Y67),_xlfn.XLOOKUP(Y67,'JP-PINT'!A:A,'JP-PINT'!B:B),""),IF(ISERROR(_xlpm.v),"",_xlpm.v))
A68: =IF(ISTEXT(E68),_xlfn.XLOOKUP(E68,'[1]SME09-01_LHM'!$D:$D,'[1]SME09-01_LHM'!$B:$B)) -> 89 | B68: =_xlfn.XLOOKUP(F68,'[1]SME09-01_LHM'!$I:$I,'[1]SME09-01_LHM'!$B:$B) -> 89 | C68: =ROW()-25 -> 43 | D68: 鑑ヘッダ | E68: IID35 | F68: 受注者メールアドレス | G68: 受注者の電子メールアドレス。 | H68: 0..1 | I68: v1 | J68: ＊ | K68: ＊ | L68: ＊ | N68: ★ | P68: ヘッダ部 | Q68: UN01005858 | R68: BBIE | W68: BBIE | X68: BBIE | Y68: =_xlfn.LET(_xlpm.v,_xlfn.XLOOKUP(E68,'[1]SME09-01_LHM'!$D:$D,'[1]SME09-01_LHM'!$AL:$AL),IF(_xlpm.v=0,"",_xlpm.v)) -> IBT-043 | Z68: =_xlfn.LET(_xlpm.v,IF(ISTEXT(Y68),_xlfn.XLOOKUP(Y68,'JP-PINT'!A:A,'JP-PINT'!B:B),""),IF(ISERROR(_xlpm.v),"",_xlpm.v)) -> >> Seller contact email address | AA68: 0..1
A69: =IF(ISTEXT(E69),_xlfn.XLOOKUP(E69,'[1]SME09-01_LHM'!$D:$D,'[1]SME09-01_LHM'!$B:$B)) -> 90 | B69: =_xlfn.XLOOKUP(F69,'[1]SME09-01_LHM'!$I:$I,'[1]SME09-01_LHM'!$B:$B) -> 90 | C69: =ROW()-25 -> 44 | D69: 鑑ヘッダ | E69: IGR7 | F69: 受注者／住所グループ | G69: 受注者住所に関する情報からなるグループ。 | H69: 0..1 | I69: v1 | J69: ● | K69: ● | L69: ● | N69: ☆ | P69: ヘッダ部 | Q69: UN01005762 | R69: ASBIE | W69: ASBIE | X69: ASBIE | Y69: =_xlfn.LET(_xlpm.v,_xlfn.XLOOKUP(E69,'[1]SME09-01_LHM'!$D:$D,'[1]SME09-01_LHM'!$AL:$AL),IF(_xlpm.v=0,"",_xlpm.v)) -> IBG-05 | Z69: =_xlfn.LET(_xlpm.v,IF(ISTEXT(Y69),_xlfn.XLOOKUP(Y69,'JP-PINT'!A:A,'JP-PINT'!B:B),""),IF(ISERROR(_xlpm.v),"",_xlpm.v)) -> > SELLER POSTAL ADDRESS | AA69: 1..1
A70: =IF(ISTEXT(E70),_xlfn.XLOOKUP(E70,'[1]SME09-01_LHM'!$D:$D,'[1]SME09-01_LHM'!$B:$B)) -> 92 | B70: =_xlfn.XLOOKUP(F70,'[1]SME09-01_LHM'!$I:$I,'[1]SME09-01_LHM'!$B:$B) -> 92 | C70: =ROW()-25 -> 45 | D70: 鑑ヘッダ | E70: IID36 | F70: 受注者郵便番号 | G70: 受注者の郵便番号。 | H70: 0..1 | I70: v1 | J70: ＊ | K70: ＊ | L70: ＊ | N70: ★ | P70: ヘッダ部 | Q70: UN01005689 | R70: BBIE | W70: BBIE | X70: BBIE | Y70: =_xlfn.LET(_xlpm.v,_xlfn.XLOOKUP(E70,'[1]SME09-01_LHM'!$D:$D,'[1]SME09-01_LHM'!$AL:$AL),IF(_xlpm.v=0,"",_xlpm.v)) -> IBT-038 | Z70: =_xlfn.LET(_xlpm.v,IF(ISTEXT(Y70),_xlfn.XLOOKUP(Y70,'JP-PINT'!A:A,'JP-PINT'!B:B),""),IF(ISERROR(_xlpm.v),"",_xlpm.v)) -> >> Seller post code | AA70: 0..1
A71: =IF(ISTEXT(E71),_xlfn.XLOOKUP(E71,'[1]SME09-01_LHM'!$D:$D,'[1]SME09-01_LHM'!$B:$B)) -> 93 | B71: =_xlfn.XLOOKUP(F71,'[1]SME09-01_LHM'!$I:$I,'[1]SME09-01_LHM'!$B:$B) -> 93 | C71: =ROW()-25 -> 46 | D71: 鑑ヘッダ | E71: IID37 | F71: 受注者住所1 | G71: 受注者の住所1行目。 | H71: 0..1 | I71: v1 | J71: ＊ | K71: ＊ | L71: ＊ | N71: ★ | P71: ヘッダ部 | Q71: UN01005692 | R71: BBIE | W71: BBIE | X71: BBIE | Y71: =_xlfn.LET(_xlpm.v,_xlfn.XLOOKUP(E71,'[1]SME09-01_LHM'!$D:$D,'[1]SME09-01_LHM'!$AL:$AL),IF(_xlpm.v=0,"",_xlpm.v)) -> IBT-035 | Z71: =_xlfn.LET(_xlpm.v,IF(ISTEXT(Y71),_xlfn.XLOOKUP(Y71,'JP-PINT'!A:A,'JP-PINT'!B:B),""),IF(ISERROR(_xlpm.v),"",_xlpm.v)) -> >> Seller address line 1 | AA71: 0..1
A72: =IF(ISTEXT(E72),_xlfn.XLOOKUP(E72,'[1]SME09-01_LHM'!$D:$D,'[1]SME09-01_LHM'!$B:$B)) -> 94 | B72: =_xlfn.XLOOKUP(F72,'[1]SME09-01_LHM'!$I:$I,'[1]SME09-01_LHM'!$B:$B) -> 94 | C72: =ROW()-25 -> 47 | D72: 鑑ヘッダ | E72: IID38 | F72: 受注者住所2 | G72: 受注者の住所2行目。 | H72: 0..1 | I72: v4 | J72: ＊ | K72: ＊ | N72: ★ | P72: ヘッダ部 | Q72: UN01005693 | R72: BBIE | W72: BBIE | Y72: =_xlfn.LET(_xlpm.v,_xlfn.XLOOKUP(E72,'[1]SME09-01_LHM'!$D:$D,'[1]SME09-01_LHM'!$AL:$AL),IF(_xlpm.v=0,"",_xlpm.v)) -> IBT-036 | Z72: =_xlfn.LET(_xlpm.v,IF(ISTEXT(Y72),_xlfn.XLOOKUP(Y72,'JP-PINT'!A:A,'JP-PINT'!B:B),""),IF(ISERROR(_xlpm.v),"",_xlpm.v)) -> >> Seller address line 2 | AA72: 0..1
A73: =IF(ISTEXT(E73),_xlfn.XLOOKUP(E73,'[1]SME09-01_LHM'!$D:$D,'[1]SME09-01_LHM'!$B:$B)) -> 95 | B73: =_xlfn.XLOOKUP(F73,'[1]SME09-01_LHM'!$I:$I,'[1]SME09-01_LHM'!$B:$B) -> 95 | C73: =ROW()-25 -> 48 | D73: 鑑ヘッダ | E73: IID39 | F73: 受注者住所3 | G73: 受注者の住所3行目。 | H73: 0..1 | I73: v4 | J73: ＊ | K73: ＊ | N73: ★ | P73: ヘッダ部 | Q73: UN01005694 | R73: BBIE | W73: BBIE | Y73: =_xlfn.LET(_xlpm.v,_xlfn.XLOOKUP(E73,'[1]SME09-01_LHM'!$D:$D,'[1]SME09-01_LHM'!$AL:$AL),IF(_xlpm.v=0,"",_xlpm.v)) -> IBT-162 | Z73: =_xlfn.LET(_xlpm.v,IF(ISTEXT(Y73),_xlfn.XLOOKUP(Y73,'JP-PINT'!A:A,'JP-PINT'!B:B),""),IF(ISERROR(_xlpm.v),"",_xlpm.v)) -> >> Seller address line 3 | AA73: 0..1
A74: =IF(ISTEXT(E74),_xlfn.XLOOKUP(E74,'[1]SME09-01_LHM'!$D:$D,'[1]SME09-01_LHM'!$B:$B)) -> 96 | B74: =_xlfn.XLOOKUP(F74,'[1]SME09-01_LHM'!$I:$I,'[1]SME09-01_LHM'!$B:$B) -> 96 | C74: =ROW()-25 -> 49 | D74: 鑑ヘッダ | E74: IID40 | F74: 受注者国ID | G74: 受注者の国ID。デフォルトは「JP」 | H74: 1..1 | I74: v4 | J74: ● | K74: ● | N74: ☆ | P74: ヘッダ部 | Q74: UN01005700 | R74: BBIE | S74: ISO3166-1:Alpha2 | T74: ISO | U74: ID値 選択入力 | V74: デフォルト ＝JP（日本） | W74: BBIE | Y74: =_xlfn.LET(_xlpm.v,_xlfn.XLOOKUP(E74,'[1]SME09-01_LHM'!$D:$D,'[1]SME09-01_LHM'!$AL:$AL),IF(_xlpm.v=0,"",_xlpm.v)) -> IBT-040 | Z74: =_xlfn.LET(_xlpm.v,IF(ISTEXT(Y74),_xlfn.XLOOKUP(Y74,'JP-PINT'!A:A,'JP-PINT'!B:B),""),IF(ISERROR(_xlpm.v),"",_xlpm.v)) -> >> Seller country code | AA74: 1..1
A75: =IF(ISTEXT(E75),_xlfn.XLOOKUP(E75,'[1]SME09-01_LHM'!$D:$D,'[1]SME09-01_LHM'!$B:$B)) -> 97 | B75: =_xlfn.XLOOKUP(F75,'[1]SME09-01_LHM'!$I:$I,'[1]SME09-01_LHM'!$B:$B) -> 97 | C75: =ROW()-25 -> 50 | D75: 鑑ヘッダ | E75: IGR8 | F75: 受注者／国際アドレスグループ | G75: 受注者の国際アドレスグループ | H75: 0..1 | I75: v4.1 | J75: ● | K75: ● | L75: ● | P75: ヘッダ部 | Q75: UN01005765 | R75: ASBIE | W75: ASBIE | X75: ASBIE | Y75: =_xlfn.LET(_xlpm.v,_xlfn.XLOOKUP(E75,'[1]SME09-01_LHM'!$D:$D,'[1]SME09-01_LHM'!$AL:$AL),IF(_xlpm.v=0,"",_xlpm.v)) | Z75: =_xlfn.LET(_xlpm.v,IF(ISTEXT(Y75),_xlfn.XLOOKUP(Y75,'JP-PINT'!A:A,'JP-PINT'!B:B),""),IF(ISERROR(_xlpm.v),"",_xlpm.v))
A76: =IF(ISTEXT(E76),_xlfn.XLOOKUP(E76,'[1]SME09-01_LHM'!$D:$D,'[1]SME09-01_LHM'!$B:$B)) -> 99 | B76: =_xlfn.XLOOKUP(F76,'[1]SME09-01_LHM'!$I:$I,'[1]SME09-01_LHM'!$B:$B) -> 99 | C76: =ROW()-25 -> 51 | D76: 鑑ヘッダ | E76: IID41 | F76: 受注者国際アドレスID | G76: 国際アドレス登録機関が付与する受注者国際アドレス番号 | H76: 0..1 | I76: v4.3 | J76: ● | K76: ● | L76: ● | M76: ― | N76: ☆ | O76: ○ | P76: ヘッダ部 | Q76: UN01005858 | R76: BBIE | S76: ISO6523 | T76: ISO | U76: 属性コード値 選択入力 | V76: 6523'国際アドレス登録機関コード値 | W76: BBIE | X76: BBIE | Y76: =_xlfn.LET(_xlpm.v,_xlfn.XLOOKUP(E76,'[1]SME09-01_LHM'!$D:$D,'[1]SME09-01_LHM'!$AL:$AL),IF(_xlpm.v=0,"",_xlpm.v)) -> IBT-034 | Z76: =_xlfn.LET(_xlpm.v,IF(ISTEXT(Y76),_xlfn.XLOOKUP(Y76,'JP-PINT'!A:A,'JP-PINT'!B:B),""),IF(ISERROR(_xlpm.v),"",_xlpm.v)) -> > Seller electronic address | AA76: 1..1
A77: =IF(ISTEXT(E77),_xlfn.XLOOKUP(E77,'[1]SME09-01_LHM'!$D:$D,'[1]SME09-01_LHM'!$B:$B)) -> 100 | B77: =_xlfn.XLOOKUP(F77,'[1]SME09-01_LHM'!$I:$I,'[1]SME09-01_LHM'!$B:$B) -> 100 | C77: =ROW()-25 -> 52 | D77: 鑑ヘッダ | E77: IID42 | F77: 受注者国際アドレス登録機関ID | G77: ISOがコード表6523に登録した国際アドレス登録機関のID | I77: v4.3 | J77: ● | K77: ● | L77: ● | M77: ― | N77: ☆ | O77: ○ | P77: ヘッダ部 | R77: SC | W77: SC | X77: SC | Y77: =_xlfn.LET(_xlpm.v,_xlfn.XLOOKUP(E77,'[1]SME09-01_LHM'!$D:$D,'[1]SME09-01_LHM'!$AL:$AL),IF(_xlpm.v=0,"",_xlpm.v)) -> IBT-034-1 | Z77: =_xlfn.LET(_xlpm.v,IF(ISTEXT(Y77),_xlfn.XLOOKUP(Y77,'JP-PINT'!A:A,'JP-PINT'!B:B),""),IF(ISERROR(_xlpm.v),"",_xlpm.v)) -> >>Scheme identifier | AA77: 1..1
A78: =IF(ISTEXT(E78),_xlfn.XLOOKUP(E78,'[1]SME09-01_LHM'!$D:$D,'[1]SME09-01_LHM'!$B:$B)) -> 101 | B78: =_xlfn.XLOOKUP(F78,'[1]SME09-01_LHM'!$I:$I,'[1]SME09-01_LHM'!$B:$B) -> 101 | C78: =ROW()-25 -> 53 | D78: 鑑ヘッダ | E78: IGR9 | F78: インボイス文書契約／発注者グループ | G78: 発注者に関する情報からなるグループ。 | H78: 1..1 | I78: v1 | J78: ○ | K78: ○ | L78: ○ | N78: ☆ | P78: ヘッダ部 | Q78: UN01005880 | R78: ASBIE | W78: ASBIE | X78: ASBIE | Y78: =_xlfn.LET(_xlpm.v,_xlfn.XLOOKUP(E78,'[1]SME09-01_LHM'!$D:$D,'[1]SME09-01_LHM'!$AL:$AL),IF(_xlpm.v=0,"",_xlpm.v)) -> IBG-07 | Z78: =_xlfn.LET(_xlpm.v,IF(ISTEXT(Y78),_xlfn.XLOOKUP(Y78,'JP-PINT'!A:A,'JP-PINT'!B:B),""),IF(ISERROR(_xlpm.v),"",_xlpm.v)) -> BUYER | AA78: 1..1
A79: =IF(ISTEXT(E79),_xlfn.XLOOKUP(E79,'[1]SME09-01_LHM'!$D:$D,'[1]SME09-01_LHM'!$B:$B)) -> 103 | B79: =_xlfn.XLOOKUP(F79,'[1]SME09-01_LHM'!$I:$I,'[1]SME09-01_LHM'!$B:$B) -> 103 | C79: =ROW()-25 -> 54 | D79: 鑑ヘッダ | E79: IID43 | F79: 発注者ID | G79: 注文を行う企業/工場・事業所・事業部門等を表すID。デフォルトはデータなし。 | H79: 0..1 | I79: v1 | J79: ＊ | K79: ＊ | L79: ＊ | M79: ※ | N79: ★ | P79: ヘッダ部 | Q79: UN01005757 | R79: BBIE | W79: BBIE | X79: BBIE | Y79: =_xlfn.LET(_xlpm.v,_xlfn.XLOOKUP(E79,'[1]SME09-01_LHM'!$D:$D,'[1]SME09-01_LHM'!$AL:$AL),IF(_xlpm.v=0,"",_xlpm.v)) -> IBT-046 | Z79: =_xlfn.LET(_xlpm.v,IF(ISTEXT(Y79),_xlfn.XLOOKUP(Y79,'JP-PINT'!A:A,'JP-PINT'!B:B),""),IF(ISERROR(_xlpm.v),"",_xlpm.v)) -> > Buyer identifier | AA79: 0..1
A80: =IF(ISTEXT(E80),_xlfn.XLOOKUP(E80,'[1]SME09-01_LHM'!$D:$D,'[1]SME09-01_LHM'!$B:$B)) -> 104 | B80: =_xlfn.XLOOKUP(F80,'[1]SME09-01_LHM'!$I:$I,'[1]SME09-01_LHM'!$B:$B) -> 104 | C80: =ROW()-25 -> 55 | D80: 鑑ヘッダ | E80: IID44 | F80: 発注者国際企業ID | G80: 企業を表す国際企業ID。ISO6523に登録された国際企業登録機関を属性で指定する。 | H80: 0..1 | I80: v1 | J80: ＊ | K80: ＊ | L80: ＊ | N80: ★ | P80: ヘッダ部 | Q80: UN01005758 | R80: BBIE | S80: ISO6523 | T80: ISO | U80: 属性コード値 選択入力 | V80: 6523企業ID/＠ 6523企業コード発番機関コード値 | W80: BBIE | X80: BBIE | Y80: =_xlfn.LET(_xlpm.v,_xlfn.XLOOKUP(E80,'[1]SME09-01_LHM'!$D:$D,'[1]SME09-01_LHM'!$AL:$AL),IF(_xlpm.v=0,"",_xlpm.v)) -> IBT-047 | Z80: =_xlfn.LET(_xlpm.v,IF(ISTEXT(Y80),_xlfn.XLOOKUP(Y80,'JP-PINT'!A:A,'JP-PINT'!B:B),""),IF(ISERROR(_xlpm.v),"",_xlpm.v)) -> > Buyer legal registration identifier | AA80: 0..1
A81: =IF(ISTEXT(E81),_xlfn.XLOOKUP(E81,'[1]SME09-01_LHM'!$D:$D,'[1]SME09-01_LHM'!$B:$B)) -> 105 | B81: =_xlfn.XLOOKUP(F81,'[1]SME09-01_LHM'!$I:$I,'[1]SME09-01_LHM'!$B:$B) -> 105 | C81: =ROW()-25 -> 56 | D81: 鑑ヘッダ | E81: IID45 | F81: 発注者名称 | G81: 発注を行う企業/工場・事業所・事業部門等の名称 | H81: 0..1 | I81: v1 | J81: ◎ | K81: ◎ | L81: ◎ | M81: ※ | N81: ☆ | O81: ○ | P81: ヘッダ部 | Q81: UN01005759 | R81: BBIE | W81: BBIE | X81: BBIE | Y81: =_xlfn.LET(_xlpm.v,_xlfn.XLOOKUP(E81,'[1]SME09-01_LHM'!$D:$D,'[1]SME09-01_LHM'!$AL:$AL),IF(_xlpm.v=0,"",_xlpm.v)) -> IBT-044 | Z81: =_xlfn.LET(_xlpm.v,IF(ISTEXT(Y81),_xlfn.XLOOKUP(Y81,'JP-PINT'!A:A,'JP-PINT'!B:B),""),IF(ISERROR(_xlpm.v),"",_xlpm.v)) -> > Buyer name | AA81: 1..1
A82: =IF(ISTEXT(E82),_xlfn.XLOOKUP(E82,'[1]SME09-01_LHM'!$D:$D,'[1]SME09-01_LHM'!$B:$B)) -> 133.3 | B82: =_xlfn.XLOOKUP(F82,'[1]SME09-01_LHM'!$I:$I,'[1]SME09-01_LHM'!$B:$B) -> 133.3 | C82: =ROW()-25 -> 57 | D82: 鑑ヘッダ | E82: IID46 | F82: 発注者適格請求書発行事業者登録番号 | G82: 登録された発注者の適格請求書発行事業者登録番号 （免税事業者についてはなし） | H82: 0..1 | I82: v4 | J82: ＊ | K82: ＊ | L82: ＊ | N82: ★ | P82: ヘッダ部 | Q82: UN01013039 | R82: BBIE | S82: ISO6523 | T82: ISO | U82: 属性コード値 選択入力 | V82: 6523'国際アドレス登録機関コード値 | W82: BBIE | X82: BBIE | Y82: =_xlfn.LET(_xlpm.v,_xlfn.XLOOKUP(E82,'[1]SME09-01_LHM'!$D:$D,'[1]SME09-01_LHM'!$AL:$AL),IF(_xlpm.v=0,"",_xlpm.v)) -> IBT-031 | Z82: =_xlfn.LET(_xlpm.v,IF(ISTEXT(Y82),_xlfn.XLOOKUP(Y82,'JP-PINT'!A:A,'JP-PINT'!B:B),""),IF(ISERROR(_xlpm.v),"",_xlpm.v)) -> > Seller TAX identifier | AA82: 0..1
A83: =IF(ISTEXT(E83),_xlfn.XLOOKUP(E83,'[1]SME09-01_LHM'!$D:$D,'[1]SME09-01_LHM'!$B:$B)) -> #N/A | B83: =_xlfn.XLOOKUP(F83,'[1]SME09-01_LHM'!$I:$I,'[1]SME09-01_LHM'!$B:$B) -> #N/A | C83: =ROW()-25 -> 58 | D83: 鑑ヘッダ | E83: IID47 | F83: 発注者タイプコード | G83: インボイス制度対象事業者のタイプを識別するコード 正規、簡易課税、2割特例、免税 | H83: 0..1 | I83: v4 | J83: ＊ | K83: ＊ | L83: ＊ | P83: ヘッダ部 | Q83: UN01012925 | R83: BBIE | S83: JECxxxx | T83: JEC | W83: BBIE | X83: BBIE | Y83: =_xlfn.LET(_xlpm.v,_xlfn.XLOOKUP(E83,'[1]SME09-01_LHM'!$D:$D,'[1]SME09-01_LHM'!$AL:$AL),IF(_xlpm.v=0,"",_xlpm.v)) -> #N/A | Z83: =_xlfn.LET(_xlpm.v,IF(ISTEXT(Y83),_xlfn.XLOOKUP(Y83,'JP-PINT'!A:A,'JP-PINT'!B:B),""),IF(ISERROR(_xlpm.v),"",_xlpm.v))
A84: =IF(ISTEXT(E84),_xlfn.XLOOKUP(E84,'[1]SME09-01_LHM'!$D:$D,'[1]SME09-01_LHM'!$B:$B)) -> 108 | B84: =_xlfn.XLOOKUP(F84,'[1]SME09-01_LHM'!$I:$I,'[1]SME09-01_LHM'!$B:$B) -> 108 | C84: =ROW()-25 -> 59 | D84: 鑑ヘッダ | E84: IGR10 | F84: 発注者／連絡先グループ | G84: 連絡先に関する情報からなるグループ。 | H84: 0..1 | I84: v1 | J84: ＊ | K84: ＊ | L84: ＊ | N84: ★ | P84: ヘッダ部 | Q84: UN01005761 | R84: ASBIE | W84: ASBIE | X84: ASBIE | Y84: =_xlfn.LET(_xlpm.v,_xlfn.XLOOKUP(E84,'[1]SME09-01_LHM'!$D:$D,'[1]SME09-01_LHM'!$AL:$AL),IF(_xlpm.v=0,"",_xlpm.v)) -> IBG-09 | Z84: =_xlfn.LET(_xlpm.v,IF(ISTEXT(Y84),_xlfn.XLOOKUP(Y84,'JP-PINT'!A:A,'JP-PINT'!B:B),""),IF(ISERROR(_xlpm.v),"",_xlpm.v)) -> > BUYER CONTACT | AA84: 0..1
A85: =IF(ISTEXT(E85),_xlfn.XLOOKUP(E85,'[1]SME09-01_LHM'!$D:$D,'[1]SME09-01_LHM'!$B:$B)) -> 110 | B85: =_xlfn.XLOOKUP(F85,'[1]SME09-01_LHM'!$I:$I,'[1]SME09-01_LHM'!$B:$B) -> 110 | C85: =ROW()-25 -> 60 | D85: 鑑ヘッダ | E85: IID48 | F85: 発注者部門ID | G85: 発注者の発注部門を表すID。 | H85: 0..1 | I85: v1 | J85: ＊ | K85: ＊ | L85: ＊ | P85: ヘッダ部 | Q85: UN01005719 | R85: BBIE | W85: BBIE | X85: BBIE | Y85: =_xlfn.LET(_xlpm.v,_xlfn.XLOOKUP(E85,'[1]SME09-01_LHM'!$D:$D,'[1]SME09-01_LHM'!$AL:$AL),IF(_xlpm.v=0,"",_xlpm.v)) | Z85: =_xlfn.LET(_xlpm.v,IF(ISTEXT(Y85),_xlfn.XLOOKUP(Y85,'JP-PINT'!A:A,'JP-PINT'!B:B),""),IF(ISERROR(_xlpm.v),"",_xlpm.v))
A86: =IF(ISTEXT(E86),_xlfn.XLOOKUP(E86,'[1]SME09-01_LHM'!$D:$D,'[1]SME09-01_LHM'!$B:$B)) -> 111 | B86: =_xlfn.XLOOKUP(F86,'[1]SME09-01_LHM'!$I:$I,'[1]SME09-01_LHM'!$B:$B) -> 111 | C86: =ROW()-25 -> 61 | D86: 鑑ヘッダ | E86: IID49 | F86: 発注者担当名 | G86: 発注者の発注担当者の名称 | H86: 0..1 | I86: v1 | J86: ＊ | K86: ＊ | L86: ＊ | N86: （★） | P86: ヘッダ部 | Q86: UN01005720 | R86: BBIE | W86: BBIE | X86: BBIE | Y86: =_xlfn.LET(_xlpm.v,_xlfn.XLOOKUP(E86,'[1]SME09-01_LHM'!$D:$D,'[1]SME09-01_LHM'!$AL:$AL),IF(_xlpm.v=0,"",_xlpm.v)) -> IBT-056 | Z86: =_xlfn.LET(_xlpm.v,IF(ISTEXT(Y86),_xlfn.XLOOKUP(Y86,'JP-PINT'!A:A,'JP-PINT'!B:B),""),IF(ISERROR(_xlpm.v),"",_xlpm.v)) -> >> Buyer contact point | AA86: 0..1
A87: =IF(ISTEXT(E87),_xlfn.XLOOKUP(E87,'[1]SME09-01_LHM'!$D:$D,'[1]SME09-01_LHM'!$B:$B)) -> 112 | B87: =_xlfn.XLOOKUP(F87,'[1]SME09-01_LHM'!$I:$I,'[1]SME09-01_LHM'!$B:$B) -> 112 | C87: =ROW()-25 -> 62 | D87: 鑑ヘッダ | E87: IID50 | F87: 発注者部門名 | G87: 発注者の発注部門の名称。 | H87: 0..1 | I87: v1 | J87: ＊ | K87: ＊ | L87: ＊ | N87: （★） | P87: ヘッダ部 | Q87: UN01005721 | R87: BBIE | W87: BBIE | X87: BBIE | Y87: =_xlfn.LET(_xlpm.v,_xlfn.XLOOKUP(E87,'[1]SME09-01_LHM'!$D:$D,'[1]SME09-01_LHM'!$AL:$AL),IF(_xlpm.v=0,"",_xlpm.v)) -> IBT-056 | Z87: =_xlfn.LET(_xlpm.v,IF(ISTEXT(Y87),_xlfn.XLOOKUP(Y87,'JP-PINT'!A:A,'JP-PINT'!B:B),""),IF(ISERROR(_xlpm.v),"",_xlpm.v)) -> >> Buyer contact point | AA87: 0..1
A88: =IF(ISTEXT(E88),_xlfn.XLOOKUP(E88,'[1]SME09-01_LHM'!$D:$D,'[1]SME09-01_LHM'!$B:$B)) -> 113 | B88: =_xlfn.XLOOKUP(F88,'[1]SME09-01_LHM'!$I:$I,'[1]SME09-01_LHM'!$B:$B) -> 113 | C88: =ROW()-25 -> 63 | D88: 鑑ヘッダ | E88: IID51 | F88: 発注者担当ID | G88: 発注者個人を表すID | H88: 0..1 | I88: v4 | J88: ＊ | K88: ＊ | L88: ＊ | P88: ヘッダ部 | Q88: UN01005725 | R88: BBIE | W88: BBIE | X88: BBIE | Y88: =_xlfn.LET(_xlpm.v,_xlfn.XLOOKUP(E88,'[1]SME09-01_LHM'!$D:$D,'[1]SME09-01_LHM'!$AL:$AL),IF(_xlpm.v=0,"",_xlpm.v)) | Z88: =_xlfn.LET(_xlpm.v,IF(ISTEXT(Y88),_xlfn.XLOOKUP(Y88,'JP-PINT'!A:A,'JP-PINT'!B:B),""),IF(ISERROR(_xlpm.v),"",_xlpm.v))
A89: =IF(ISTEXT(E89),_xlfn.XLOOKUP(E89,'[1]SME09-01_LHM'!$D:$D,'[1]SME09-01_LHM'!$B:$B)) -> 116 | B89: =_xlfn.XLOOKUP(F89,'[1]SME09-01_LHM'!$I:$I,'[1]SME09-01_LHM'!$B:$B) -> 116 | C89: =ROW()-25 -> 64 | D89: 鑑ヘッダ | E89: IID52 | F89: 発注者電話番号 | G89: 発注者の電話番号。 | H89: 0..1 | I89: v1 | J89: ＊ | K89: ＊ | L89: ＊ | N89: ★ | P89: ヘッダ部 | Q89: UN01005860 | R89: BBIE | W89: BBIE | X89: BBIE | Y89: =_xlfn.LET(_xlpm.v,_xlfn.XLOOKUP(E89,'[1]SME09-01_LHM'!$D:$D,'[1]SME09-01_LHM'!$AL:$AL),IF(_xlpm.v=0,"",_xlpm.v)) -> IBT-057 | Z89: =_xlfn.LET(_xlpm.v,IF(ISTEXT(Y89),_xlfn.XLOOKUP(Y89,'JP-PINT'!A:A,'JP-PINT'!B:B),""),IF(ISERROR(_xlpm.v),"",_xlpm.v)) -> >> Buyer contact telephone number | AA89: 0..1
A90: =IF(ISTEXT(E90),_xlfn.XLOOKUP(E90,'[1]SME09-01_LHM'!$D:$D,'[1]SME09-01_LHM'!$B:$B)) -> 119 | B90: =_xlfn.XLOOKUP(F90,'[1]SME09-01_LHM'!$I:$I,'[1]SME09-01_LHM'!$B:$B) -> 119 | C90: =ROW()-25 -> 65 | D90: 鑑ヘッダ | E90: IID53 | F90: 発注者FAX番号 | G90: 発注者のFAX番号 | H90: 0..1 | I90: v4 | J90: ＊ | K90: ＊ | L90: ＊ | P90: ヘッダ部 | Q90: UN01005860 | R90: BBIE | W90: BBIE | X90: BBIE | Y90: =_xlfn.LET(_xlpm.v,_xlfn.XLOOKUP(E90,'[1]SME09-01_LHM'!$D:$D,'[1]SME09-01_LHM'!$AL:$AL),IF(_xlpm.v=0,"",_xlpm.v)) | Z90: =_xlfn.LET(_xlpm.v,IF(ISTEXT(Y90),_xlfn.XLOOKUP(Y90,'JP-PINT'!A:A,'JP-PINT'!B:B),""),IF(ISERROR(_xlpm.v),"",_xlpm.v))
A91: =IF(ISTEXT(E91),_xlfn.XLOOKUP(E91,'[1]SME09-01_LHM'!$D:$D,'[1]SME09-01_LHM'!$B:$B)) -> 122 | B91: =_xlfn.XLOOKUP(F91,'[1]SME09-01_LHM'!$I:$I,'[1]SME09-01_LHM'!$B:$B) -> 122 | C91: =ROW()-25 -> 66 | D91: 鑑ヘッダ | E91: IID54 | F91: 発注者メールアドレス | G91: 発注者の電子メールアドレス。 | H91: 0..1 | I91: v4 | J91: ＊ | K91: ＊ | L91: ＊ | N91: ★ | P91: ヘッダ部 | Q91: UN01005858 | R91: BBIE | W91: BBIE | X91: BBIE | Y91: =_xlfn.LET(_xlpm.v,_xlfn.XLOOKUP(E91,'[1]SME09-01_LHM'!$D:$D,'[1]SME09-01_LHM'!$AL:$AL),IF(_xlpm.v=0,"",_xlpm.v)) -> IBT-058 | Z91: =_xlfn.LET(_xlpm.v,IF(ISTEXT(Y91),_xlfn.XLOOKUP(Y91,'JP-PINT'!A:A,'JP-PINT'!B:B),""),IF(ISERROR(_xlpm.v),"",_xlpm.v)) -> >> Buyer contact email address | AA91: 0..1
A92: =IF(ISTEXT(E92),_xlfn.XLOOKUP(E92,'[1]SME09-01_LHM'!$D:$D,'[1]SME09-01_LHM'!$B:$B)) -> 123 | B92: =_xlfn.XLOOKUP(F92,'[1]SME09-01_LHM'!$I:$I,'[1]SME09-01_LHM'!$B:$B) -> 123 | C92: =ROW()-25 -> 67 | D92: 鑑ヘッダ | E92: IGR11 | F92: 発注者／住所グループ | G92: 発注者住所に関する情報からなるグループ。 | H92: 0..1 | I92: v4 | J92: ● | K92: ● | L92: ● | N92: ☆ | P92: ヘッダ部 | Q92: UN01005762 | R92: ASBIE | W92: ASBIE | X92: ASBIE | Y92: =_xlfn.LET(_xlpm.v,_xlfn.XLOOKUP(E92,'[1]SME09-01_LHM'!$D:$D,'[1]SME09-01_LHM'!$AL:$AL),IF(_xlpm.v=0,"",_xlpm.v)) -> IBG-08 | Z92: =_xlfn.LET(_xlpm.v,IF(ISTEXT(Y92),_xlfn.XLOOKUP(Y92,'JP-PINT'!A:A,'JP-PINT'!B:B),""),IF(ISERROR(_xlpm.v),"",_xlpm.v)) -> > BUYER POSTAL ADDRESS | AA92: 1..1
A93: =IF(ISTEXT(E93),_xlfn.XLOOKUP(E93,'[1]SME09-01_LHM'!$D:$D,'[1]SME09-01_LHM'!$B:$B)) -> 125 | B93: =_xlfn.XLOOKUP(F93,'[1]SME09-01_LHM'!$I:$I,'[1]SME09-01_LHM'!$B:$B) -> 125 | C93: =ROW()-25 -> 68 | D93: 鑑ヘッダ | E93: IID55 | F93: 発注者郵便番号 | G93: 発注者の郵便番号。 | H93: 0..1 | I93: v4 | J93: ＊ | K93: ＊ | L93: ＊ | N93: ★ | P93: ヘッダ部 | Q93: UN01005689 | R93: BBIE | W93: BBIE | X93: BBIE | Y93: =_xlfn.LET(_xlpm.v,_xlfn.XLOOKUP(E93,'[1]SME09-01_LHM'!$D:$D,'[1]SME09-01_LHM'!$AL:$AL),IF(_xlpm.v=0,"",_xlpm.v)) -> IBT-053 | Z93: =_xlfn.LET(_xlpm.v,IF(ISTEXT(Y93),_xlfn.XLOOKUP(Y93,'JP-PINT'!A:A,'JP-PINT'!B:B),""),IF(ISERROR(_xlpm.v),"",_xlpm.v)) -> >> Buyer post code | AA93: 0..1
A94: =IF(ISTEXT(E94),_xlfn.XLOOKUP(E94,'[1]SME09-01_LHM'!$D:$D,'[1]SME09-01_LHM'!$B:$B)) -> 126 | B94: =_xlfn.XLOOKUP(F94,'[1]SME09-01_LHM'!$I:$I,'[1]SME09-01_LHM'!$B:$B) -> 126 | C94: =ROW()-25 -> 69 | D94: 鑑ヘッダ | E94: IID56 | F94: 発注者住所1 | G94: 発注者の住所1行目。 | H94: 0..1 | I94: v4 | J94: ＊ | K94: ＊ | L94: ＊ | N94: ★ | P94: ヘッダ部 | Q94: UN01005692 | R94: BBIE | W94: BBIE | X94: BBIE | Y94: =_xlfn.LET(_xlpm.v,_xlfn.XLOOKUP(E94,'[1]SME09-01_LHM'!$D:$D,'[1]SME09-01_LHM'!$AL:$AL),IF(_xlpm.v=0,"",_xlpm.v)) -> IBT-050 | Z94: =_xlfn.LET(_xlpm.v,IF(ISTEXT(Y94),_xlfn.XLOOKUP(Y94,'JP-PINT'!A:A,'JP-PINT'!B:B),""),IF(ISERROR(_xlpm.v),"",_xlpm.v)) -> >> Buyer address line 1 | AA94: 0..1
A95: =IF(ISTEXT(E95),_xlfn.XLOOKUP(E95,'[1]SME09-01_LHM'!$D:$D,'[1]SME09-01_LHM'!$B:$B)) -> 127 | B95: =_xlfn.XLOOKUP(F95,'[1]SME09-01_LHM'!$I:$I,'[1]SME09-01_LHM'!$B:$B) -> 127 | C95: =ROW()-25 -> 70 | D95: 鑑ヘッダ | E95: IID57 | F95: 発注者住所2 | G95: 発注者の住所2行目。 | H95: 0..1 | I95: v4 | J95: ＊ | K95: ＊ | N95: ★ | P95: ヘッダ部 | Q95: UN01005693 | R95: BBIE | W95: BBIE | Y95: =_xlfn.LET(_xlpm.v,_xlfn.XLOOKUP(E95,'[1]SME09-01_LHM'!$D:$D,'[1]SME09-01_LHM'!$AL:$AL),IF(_xlpm.v=0,"",_xlpm.v)) -> IBT-051 | Z95: =_xlfn.LET(_xlpm.v,IF(ISTEXT(Y95),_xlfn.XLOOKUP(Y95,'JP-PINT'!A:A,'JP-PINT'!B:B),""),IF(ISERROR(_xlpm.v),"",_xlpm.v)) -> >> Buyer address line 2 | AA95: 0..1
A96: =IF(ISTEXT(E96),_xlfn.XLOOKUP(E96,'[1]SME09-01_LHM'!$D:$D,'[1]SME09-01_LHM'!$B:$B)) -> 128 | B96: =_xlfn.XLOOKUP(F96,'[1]SME09-01_LHM'!$I:$I,'[1]SME09-01_LHM'!$B:$B) -> 128 | C96: =ROW()-25 -> 71 | D96: 鑑ヘッダ | E96: IID58 | F96: 発注者住所3 | G96: 発注者の住所3行目。 | H96: 0..1 | I96: v4 | J96: ＊ | K96: ＊ | N96: ★ | P96: ヘッダ部 | Q96: UN01005694 | R96: BBIE | W96: BBIE | Y96: =_xlfn.LET(_xlpm.v,_xlfn.XLOOKUP(E96,'[1]SME09-01_LHM'!$D:$D,'[1]SME09-01_LHM'!$AL:$AL),IF(_xlpm.v=0,"",_xlpm.v)) -> IBT-163 | Z96: =_xlfn.LET(_xlpm.v,IF(ISTEXT(Y96),_xlfn.XLOOKUP(Y96,'JP-PINT'!A:A,'JP-PINT'!B:B),""),IF(ISERROR(_xlpm.v),"",_xlpm.v)) -> >> Buyer address line 3 | AA96: 0..1
A97: =IF(ISTEXT(E97),_xlfn.XLOOKUP(E97,'[1]SME09-01_LHM'!$D:$D,'[1]SME09-01_LHM'!$B:$B)) -> 129 | B97: =_xlfn.XLOOKUP(F97,'[1]SME09-01_LHM'!$I:$I,'[1]SME09-01_LHM'!$B:$B) -> 129 | C97: =ROW()-25 -> 72 | D97: 鑑ヘッダ | E97: IID59 | F97: 発注者国ID | G97: 発注者の国ID。デフォルトは「JP」 | H97: 1..1 | I97: v4 | J97: ● | K97: ● | N97: ☆ | P97: ヘッダ部 | Q97: UN01005700 | R97: BBIE | S97: ISO3166-1:Alpha2 | T97: ISO | U97: ID値 選択入力 | V97: デフォルト ＝JP（日本） | W97: BBIE | Y97: =_xlfn.LET(_xlpm.v,_xlfn.XLOOKUP(E97,'[1]SME09-01_LHM'!$D:$D,'[1]SME09-01_LHM'!$AL:$AL),IF(_xlpm.v=0,"",_xlpm.v)) -> IBT-055 | Z97: =_xlfn.LET(_xlpm.v,IF(ISTEXT(Y97),_xlfn.XLOOKUP(Y97,'JP-PINT'!A:A,'JP-PINT'!B:B),""),IF(ISERROR(_xlpm.v),"",_xlpm.v)) -> >> Buyer country code | AA97: 1..1
A98: =IF(ISTEXT(E98),_xlfn.XLOOKUP(E98,'[1]SME09-01_LHM'!$D:$D,'[1]SME09-01_LHM'!$B:$B)) -> 130 | B98: =_xlfn.XLOOKUP(F98,'[1]SME09-01_LHM'!$I:$I,'[1]SME09-01_LHM'!$B:$B) -> 130 | C98: =ROW()-25 -> 73 | D98: 鑑ヘッダ | E98: IGR12 | F98: 発注者／国際アドレスグループ | G98: 発注者の国際アドレスグループ | H98: 0..1 | I98: v4.1 | J98: ● | K98: ● | L98: ● | P98: ヘッダ部 | Q98: UN01005765 | R98: ASBIE | W98: ASBIE | X98: ASBIE | Y98: =_xlfn.LET(_xlpm.v,_xlfn.XLOOKUP(E98,'[1]SME09-01_LHM'!$D:$D,'[1]SME09-01_LHM'!$AL:$AL),IF(_xlpm.v=0,"",_xlpm.v)) | Z98: =_xlfn.LET(_xlpm.v,IF(ISTEXT(Y98),_xlfn.XLOOKUP(Y98,'JP-PINT'!A:A,'JP-PINT'!B:B),""),IF(ISERROR(_xlpm.v),"",_xlpm.v))
A99: =IF(ISTEXT(E99),_xlfn.XLOOKUP(E99,'[1]SME09-01_LHM'!$D:$D,'[1]SME09-01_LHM'!$B:$B)) -> 132 | B99: =_xlfn.XLOOKUP(F99,'[1]SME09-01_LHM'!$I:$I,'[1]SME09-01_LHM'!$B:$B) -> 132 | C99: =ROW()-25 -> 74 | D99: 鑑ヘッダ | E99: IID60 | F99: 発注者国際アドレスID | G99: 国際アドレス登録機関が付与する発注者国際アドレス番号 | H99: 0..1 | I99: v4.3 | J99: ● | K99: ● | L99: ● | M99: ― | N99: ☆ | O99: ○ | P99: ヘッダ部 | Q99: UN01005858 | R99: BBIE | S99: ISO6523 | T99: ISO | U99: 属性コード値 選択入力 | V99: 6523'国際アドレス登録機関コード値 | W99: BBIE | X99: BBIE | Y99: =_xlfn.LET(_xlpm.v,_xlfn.XLOOKUP(E99,'[1]SME09-01_LHM'!$D:$D,'[1]SME09-01_LHM'!$AL:$AL),IF(_xlpm.v=0,"",_xlpm.v)) -> IBT-049 | Z99: =_xlfn.LET(_xlpm.v,IF(ISTEXT(Y99),_xlfn.XLOOKUP(Y99,'JP-PINT'!A:A,'JP-PINT'!B:B),""),IF(ISERROR(_xlpm.v),"",_xlpm.v)) -> > Buyer electronic address | AA99: 1..1
A100: =IF(ISTEXT(E100),_xlfn.XLOOKUP(E100,'[1]SME09-01_LHM'!$D:$D,'[1]SME09-01_LHM'!$B:$B)) -> #N/A | B100: =_xlfn.XLOOKUP(F100,'[1]SME09-01_LHM'!$I:$I,'[1]SME09-01_LHM'!$B:$B) -> #N/A | C100: =ROW()-25 -> 75 | D100: 鑑ヘッダ | E100: IID61 | F100: 発注者国際アドレス登録機関ID | G100: ISOがコード表6523に登録した国際アドレス登録機関のID | I100: v4.3 | J100: ● | K100: ● | L100: ● | M100: ― | N100: ☆ | O100: ○ | P100: ヘッダ部 | R100: SC | W100: SC | X100: SC | Y100: =_xlfn.LET(_xlpm.v,_xlfn.XLOOKUP(E100,'[1]SME09-01_LHM'!$D:$D,'[1]SME09-01_LHM'!$AL:$AL),IF(_xlpm.v=0,"",_xlpm.v)) -> #N/A | Z100: =_xlfn.LET(_xlpm.v,IF(ISTEXT(Y100),_xlfn.XLOOKUP(Y100,'JP-PINT'!A:A,'JP-PINT'!B:B),""),IF(ISERROR(_xlpm.v),"",_xlpm.v)) | AA100: 1..1
...
