Workbook

Sheet Class
A1: seq | B1: level | C1: Property type | D1: Identifier | E1: Class | F1: Property Term | G1: BaseType | H1: Associated Class | I1: Multiplicity | J1: Documentation | K1: module
A2: 1 | B2: 1 | C2: Class | E2: Communication | I2: 0..* | J2: The exchange of messages or information between parties using a specified communication channel. | K2: bus
A3: 6 | B3: 1 | C3: Class | E3: Phone | I3: 0..* | J3: Phone number information, as a specialisation of Communication. | K3: bus
A4: 12 | B4: 1 | C4: Class | E4: Fax | I4: 0..* | J4: Fax number information. | K4: bus
A5: 18 | B5: 1 | C5: Class | E5: Email | I5: 0..* | J5: Email address information. | K5: bus
A6: 24 | B6: 1 | C6: Class | E6: Web Site | I6: 0..* | J6: Web site information. | K6: bus
A7: 30 | B7: 1 | C7: Class | E7: Address | I7: 0..* | J7: Class which contains address information. | K7: bus
A8: 43 | B8: 1 | C8: Class | E8: Document Information | I8: 1..1 | J8: Parent for descriptive information about the accountingEntries Class in which it is contained. | K8: bus
A9: 61 | B9: 1 | C9: Class | E9: Contact | I9: 0..* | J9: Information about contacts. | K9: bus
A10: 74 | B10: 1 | C10: Class | E10: Accounting Method Structure | I10: 0..* | J10: Class for identifying the methods of accounting used by the entity for different reporting purposes | K10: bus
A11: 81 | B11: 1 | C11: Class | E11: Accountant | I11: 0..* | J11: Information about the relevant external accountant | K11: bus
A12: 87 | B12: 1 | C12: Class | E12: Period | I12: 0..* | J12: A tool to collect a specific set of periods used to summarize results from transactions. | K12: bus
A13: 92 | B13: 1 | C13: Class | E13: Reporting Calendar_ Period | I13: 0..* | J13: A tool to collect a specific set of periods used to summarize results from transactions. | K13: bus
... A91: 365 | B91: 1 | C91: Class | E91: Transaction_ Detail | I91: 0.* | J91: Parent class grouping transaction detail (line) level records. | K91: btx

Sheet Property
A1: seq | B1: level | C1: Property type | D1: Identifier | E1: Class | F1: Property Term | G1: BaseType | H1: Associated Class | I1: Multiplicity | J1: Documentation | K1: module
A2: 2 | B2: 2 | C2: Attribute | E2: Communication | F2: Communication URI Identifier | G2: String | I2: 0..1 | J2: The Uniform Resource Identifier (URI), such as a web or an email address, for this communication. | K2: bus
A3: 3 | B3: 2 | C3: Attribute | E3: Communication | F3: Communication Channel Code | G3: String | I3: 0..1 | J3: A code specifying the communication channel or medium through which contact information is provided or used. This code identifies the type of communication mechanism associated with a contact point, in accordance with UN/EDIFACT Data Element 3155 – Communication means type code. It enables consistent interpretation of contact details across systems and jurisdictions. Examples (non-exhaustive): TE (Telephone) Voice or data communication via a telephone network. FX (Telefax) Transmission of documents via facsimile equipment. EM (Electronic mail) Communication using electronic mail (email). AO (Uniform Resource Location : URL) Identification of the Uniform Resource Location (URL) Synonym: World wide web address. The Channel Code is used in conjunction with the corresponding communication identifier (e.g. phone number, fax number, or email address) and supports extensibility for additional communication types as defined by applicable code lists or jurisdictional requirements. | K3: bus
A4: 4 | B4: 2 | C4: Attribute | E4: Communication | F4: Communication Complete Number | G4: String | I4: 0..1 | J4: The text string of characters that make up the complete number for this communication. | K4: bus
A5: 5 | B5: 2 | C5: Attribute | E5: Communication | F5: Communication Use Code | G5: String | I5: 0..1 | J5: The code specifying the usage or purpose of this communication, such as main, investor-relations, direct. Enumerated as: bookkeeper, controller, direct, fax, investor-relations, main, switchboard, other. | K5: bus
A6: 7 | B6: 2 | C6: Specialization | E6: Phone | H6: Communication | I6: 1 | J6: Specialisation of Communication for telephone. Communication Channel Code SHALL be 'telephone'. | K6: bus
A7: 8 | B7: 2 | C7: Attribute | E7: Phone | F7: Phone URI Identifier | G7: String | I7: 0..1 | J7: The Uniform Resource Identifier (URI), such as a web or an email address, for this communication. | K7: bus
A8: 9 | B8: 2 | C8: Attribute | E8: Phone | F8: Phone Channel Code | G8: String | I8: 0..1 | J8: A code specifying the communication channel or medium through which contact information is provided or used. This code identifies the type of communication mechanism associated with a contact point, in accordance with UN/EDIFACT Data Element 3155 – Communication means type code. It enables consistent interpretation of contact details across systems and jurisdictions. Examples (non-exhaustive): TE (Telephone) Voice or data communication via a telephone network. FX (Telefax) Transmission of documents via facsimile equipment. EM (Electronic mail) Communication using electronic mail (email). The Channel Code is used in conjunction with the corresponding communication identifier (e.g. phone number, fax number, or email address) and supports extensibility for additional communication types as defined by applicable code lists or jurisdictional requirements. | K8: bus
A9: 10 | B9: 2 | C9: Attribute | E9: Phone | F9: Phone Complete Number | G9: String | I9: 0..1 | J9: The text string of characters that make up the complete number for this communication. | K9: bus
A10: 11 | B10: 2 | C10: Attribute | E10: Phone | F10: Phone Use Code | G10: String | I10: 0..1 | J10: The code specifying the usage or purpose of this communication, such as main, investor-relations, direct. Enumerated as: bookkeeper, controller, direct, fax, investor-relations, main, switchboard, other. | K10: bus
A11: 13 | B11: 2 | C11: Specialization | E11: Fax | H11: Communication | I11: 1 | J11: Specialisation of Communication for telephone. Communication Channel Code SHALL be 'telephone'. | K11: bus
A12: 14 | B12: 2 | C12: Attribute | E12: Fax | F12: Fax URI Identifier | G12: String | I12: 0..1 | J12: The Uniform Resource Identifier (URI), such as a web or an email address, for this communication. | K12: bus
A13: 15 | B13: 2 | C13: Attribute | E13: Fax | F13: Fax Channel Code | G13: String | I13: 0..1 | J13: A code specifying the communication channel or medium through which contact information is provided or used. This code identifies the type of communication mechanism associated with a contact point, in accordance with UN/EDIFACT Data Element 3155 – Communication means type code. It enables consistent interpretation of contact details across systems and jurisdictions. Examples (non-exhaustive): TE (Telephone) Voice or data communication via a telephone network. FX (Telefax) Transmission of documents via facsimile equipment. EM (Electronic mail) Communication using electronic mail (email). The Channel Code is used in conjunction with the corresponding communication identifier (e.g. phone number, fax number, or email address) and supports extensibility for additional communication types as defined by applicable code lists or jurisdictional requirements. | K13: bus
A14: 16 | B14: 2 | C14: Attribute | E14: Fax | F14: Fax Complete Number | G14: String | I14: 0..1 | J14: The text string of characters that make up the complete number for this communication. | K14: bus
A15: 17 | B15: 2 | C15: Attribute | E15: Fax | F15: Fax Use Code | G15: String | I15: 0..1 | J15: The code specifying the usage or purpose of this communication, such as main, investor-relations, direct. Enumerated as: bookkeeper, controller, direct, fax, investor-relations, main, switchboard, other. | K15: bus
A16: 19 | B16: 2 | C16: Specialization | E16: Email | H16: Communication | I16: 1 | J16: Specialisation of Communication for telephone. Communication Channel Code SHALL be 'telephone'. | K16: bus
A17: 20 | B17: 2 | C17: Attribute | E17: Email | F17: Email URI Identifier | G17: String | I17: 0..1 | J17: The Uniform Resource Identifier (URI), such as a web or an email address, for this communication. | K17: bus
A18: 21 | B18: 2 | C18: Attribute | E18: Email | F18: Email Channel Code | G18: String | I18: 0..1 | J18: A code specifying the communication channel or medium through which contact information is provided or used. This code identifies the type of communication mechanism associated with a contact point, in accordance with UN/EDIFACT Data Element 3155 – Communication means type code. It enables consistent interpretation of contact details across systems and jurisdictions. Examples (non-exhaustive): TE (Telephone) Voice or data communication via a telephone network. FX (Telefax) Transmission of documents via facsimile equipment. EM (Electronic mail) Communication using electronic mail (email). The Channel Code is used in conjunction with the corresponding communication identifier (e.g. phone number, fax number, or email address) and supports extensibility for additional communication types as defined by applicable code lists or jurisdictional requirements. | K18: bus
A19: 22 | B19: 2 | C19: Attribute | E19: Email | F19: Email Complete Number | G19: String | I19: 0..1 | J19: The text string of characters that make up the complete number for this communication. | K19: bus
A20: 23 | B20: 2 | C20: Attribute | E20: Email | F20: Email Use Code | G20: String | I20: 0..1 | J20: The code specifying the usage or purpose of this communication, such as main, investor-relations, direct. Enumerated as: bookkeeper, controller, direct, fax, investor-relations, main, switchboard, other. | K20: bus
A21: 25 | B21: 2 | C21: Specialization | E21: Web Site | H21: Communication | I21: 1 | J21: Specialisation of Communication for telephone. Communication Channel Code SHALL be 'telephone'. | K21: bus
A22: 26 | B22: 2 | C22: Attribute | E22: Web Site | F22: Web Site URI Identifier | G22: String | I22: 0..1 | J22: The Uniform Resource Identifier (URI), such as a web or an email address, for this communication. | K22: bus
A23: 27 | B23: 2 | C23: Attribute | E23: Web Site | F23: Web Site Channel Code | G23: String | I23: 0..1 | J23: A code specifying the communication channel or medium through which contact information is provided or used. This code identifies the type of communication mechanism associated with a contact point, in accordance with UN/EDIFACT Data Element 3155 – Communication means type code. It enables consistent interpretation of contact details across systems and jurisdictions. Examples (non-exhaustive): TE (Telephone) Voice or data communication via a telephone network. FX (Telefax) Transmission of documents via facsimile equipment. EM (Electronic mail) Communication using electronic mail (email). The Channel Code is used in conjunction with the corresponding communication identifier (e.g. phone number, fax number, or email address) and supports extensibility for additional communication types as defined by applicable code lists or jurisdictional requirements. | K23: bus
A24: 28 | B24: 2 | C24: Attribute | E24: Web Site | F24: Web Site Complete Number | G24: String | I24: 0..1 | J24: The text string of characters that make up the complete number for this communication. | K24: bus
A25: 29 | B25: 2 | C25: Attribute | E25: Web Site | F25: Web Site Use Code | G25: String | I25: 0..1 | J25: The code specifying the usage or purpose of this communication, such as main, investor-relations, direct. Enumerated as: bookkeeper, controller, direct, fax, investor-relations, main, switchboard, other. | K25: bus
A26: 31 | B26: 2 | C26: Attribute | E26: Address | F26: Address Name | G26: String | I26: 0..1 | J26: Address Name | K26: bus
A27: 32 | B27: 2 | C27: Attribute | E27: Address | F27: Address Description | G27: String | I27: 0..1 | J27: Address Description | K27: bus
A28: 33 | B28: 2 | C28: Attribute | E28: Address | F28: Address Purpose | G28: String | I28: 0..1 | J28: Address Purpose | K28: bus
A29: 34 | B29: 2 | C29: Attribute | E29: Address | F29: Location ID | G29: String | I29: 0..1 | J29: A code used to identify the location and to associate it with contacts and transactions | K29: bus
A30: 35 | B30: 2 | C30: Attribute | E30: Address | F30: Building Number | G30: String | I30: 0..1 | J30: Building Number | K30: bus
A31: 36 | B31: 2 | C31: Attribute | E31: Address | F31: Street | G31: String | I31: 0..1 | J31: Street address | K31: bus
A32: 37 | B32: 2 | C32: Attribute | E32: Address | F32: Address Detail | G32: String | I32: 0..1 | J32: Address Detail | K32: bus
A33: 38 | B33: 2 | C33: Attribute | E33: Address | F33: City | G33: String | I33: 0..1 | J33: City | K33: bus
... A37: 42 | B37: 2 | C37: Attribute | E37: Address | F37: Address Active Indicator | G37: Boolean | I37: 0..1 | J37: Boolean to indicate whether the address is active (="true") or inactive (="false") | K37: bus
A38: 44 | B38: 2 | C38: Attribute | D38: PK | E38: Document Information | F38: Detail Document Number | G38: String | I38: 0..1 | J38: Unique identifier for this file. | K38: bus
A39: 45 | B39: 2 | C39: Attribute | D39: PK | E39: Document Information | F39: Detail Document Type | G39: Token | I39: 1..1 | J39: account: information to fill in a chart of accounts file. balance: the results of accumulation of a complete and validated list of entries for an account (or a list of account) in a specific period - sometimes called general ledger entries: a list of individual accounting entries, which might be posted/validated or nonposted/validated journal: a self-balancing (Dr = Cr) list of entries for a specific period including beginning balance for that period. ledger: a complete list of entries for a specific account (or list of accounts) for a specific period; note - debits do not have to equal credits. assets: a listing of open receivables, payables, inventory, fixed assets or other information that can be extracted from but are not necessarily included as part of a journal entry. trialBalance: the self-balancing (Dr = Cr) result of accumulation of a complete and validated list of entries for the entity in a complete list of accounts in a specific period. taxtables: aids automated interpretation of instances that represent tax tables; Tax table are defined by using multiple [taxes] classs to gather the population of codes, authorities and rates; through [taxTableCode] cross-references in the [taxes] class, these "master file" tax tables can be referenced. mapping: a collection of mappings between interrelated data sets, such as a local and related corporate standard chart of accounts or detail data mapped to summarized end reporting concepts. versioning: a collection of changes between two versions of the same class of information, such as updates to a master file like a chart of accounts. master_file: a collection of master files, such as the customer or inventory master file. trade_documents: a collection of trade/transactional documents, such as vendor invoices or customer orders. profile_compliant: the meaning of this collection of information can be determined by understanding an established profile and especially an XBRL GL Profile. Profiles are determined through namespace declarations, schemaRef and conventions of those profiles. other: for all other types of representations. Often sorted by date or by account, these terms have specific, and sometimes different, meanings in different areas. Common practice will drive accounting method/term matches. | K39: bus
A40: 46 | B40: 2 | C40: Attribute | E40: Document Information | F40: Document Date | G40: Date Time | I40: 0..1 | J40: Date/time file was created. | K40: bus
A41: 47 | B41: 2 | C41: Attribute | E41: Document Information | F41: Revises Audit Number | G41: String | I41: 0..1 | J41: If this batch of information revises a previous batch of information, this field identifies the previous batch that is being revised. 'uniqueID' of the previous batch goes here. Developers should consider exception reporting. | K41: bus
A42: 48 | B42: 2 | C42: Attribute | E42: Document Information | F42: Action to Take with Previous Data | G42: Token | I42: 0..1 | J42: Provides guidance on action to take with previous set of data: supersedes - old data should be considered as obsolete/overwritten; supplements - belongs with that data as if it was included with it. | K42: bus
A43: 49 | B43: 2 | C43: Attribute | E43: Document Information | F43: Language | G43: QName | I43: 0..1 | J43: Primary language of the intellectual content. Where practical, the content of this field should coincide with ISO 639-1988 language codes. | K43: bus
A44: 50 | B44: 2 | C44: Attribute | E44: Document Information | F44: Creator | G44: String | I44: 0..1 | J44: Identifies the creator of the XBRL instance. | K44: bus
A45: 51 | B45: 2 | C45: Attribute | E45: Document Information | F45: Document Comment | G45: String | I45: 0..1 | J45: Text for entire document. | K45: bus
A46: 52 | B46: 2 | C46: Attribute | E46: Document Information | F46: Period Covered Start | G46: Date Time | I46: 0..1 | J46: Start of date range for contents. Used as basis for many assumptions about data, including the date as of which open balances are open. | K46: bus
A47: 53 | B47: 2 | C47: Attribute | E47: Document Information | F47: Period Covered End | G47: Date Time | I47: 0..1 | J47: End of date range for contents. Used as basis for many assumptions about data, including the date as of which open balances are open. | K47: bus
A48: 54 | B48: 2 | C48: Attribute | E48: Document Information | F48: Period Count | G48: Decimal | I48: 0..1 | J48: Number of periods or buckets, used by postingCode. Used to interpret posting date. It may be preferable to limit entries by period covered to be by individual reporting period. | K48: bus
A49: 55 | B49: 2 | C49: Attribute | E49: Document Information | F49: Period Unit | G49: Token | I49: 0..1 | J49: Type of periods covered by periodCount. Enumerated as: daily, weekly, bi-weekly, semi-monthly, monthly, quarterly, thirdly, semiannual, annual, ad-hoc, current-period-only, other. | K49: bus
A50: 56 | B50: 2 | C50: Attribute | E50: Document Information | F50: Period Unit Description | G50: String | I50: 0..1 | J50: Free format description of the period unit | K50: bus
A51: 57 | B51: 2 | C51: Attribute | E51: Document Information | F51: Source Application | G51: String | I51: 0..1 | J51: Product or service that produced this file. Used by many systems (e.g., VAT). Version number can be included or extended. | K51: bus
... A53: 59 | B53: 2 | C53: Attribute | E53: Document Information | F53: Default Currency | G53: QName | I53: 0..1 | J53: The default currency related to the amount can be entered here instead of the XBRL instance specified way, especially important in multi-currency situations. Recommend ISO 4217 coding | K53: bus
A54: 60 | B54: 2 | C54: Composition | E54: Document Information | H54: Summary Reporting Taxonomies | I54: 0..* | J54: Identifies and provides information about one or more target reporting taxonomies to which the data represented in the document rolls up to. | K54: lnk
A55: 62 | B55: 2 | C55: Attribute | E55: Contact | F55: Contact Prefix | G55: String | I55: 0..1 | J55: Prefix (e.g. Dr., Mr., Mrs.) | K55: bus
A56: 63 | B56: 2 | C56: Attribute | E56: Contact | F56: Contact Last Name | G56: String | I56: 0..1 | J56: Last or family name | K56: bus
A57: 64 | B57: 2 | C57: Attribute | E57: Contact | F57: Contact First Name | G57: String | I57: 0..1 | J57: First or given name | K57: bus
A58: 65 | B58: 2 | C58: Attribute | E58: Contact | F58: Contact Suffix | G58: String | I58: 0..1 | J58: Suffix (e.g. MD, CPA, Jr.) | K58: bus
A59: 66 | B59: 2 | C59: Attribute | E59: Contact | F59: Contact Attention Line | G59: String | I59: 0..1 | J59: Attention Line | K59: bus
A60: 67 | B60: 2 | C60: Attribute | E60: Contact | F60: Contact Position Role | G60: String | I60: 0..1 | J60: Position or role | K60: bus
A61: 68 | B61: 2 | C61: Attribute | E61: Contact | F61: Contact Contact Type | G61: String | I61: 0..1 | J61: Role of contact. Examples include: Source Service, Sender, Recipient, Invoicer, Auditor, Accountant | K61: bus
A62: 69 | B62: 2 | C62: Attribute | E62: Contact | F62: Contact Location ID cross reference | G62: String | I62: 0..1 | J62: This code is used to associate the contact with a specific location for the Entity. Its value should be the same as that of the organizationAddressLocationIdentifier | K62: bus
A63: 70 | B63: 2 | C63: Attribute | E63: Contact | F63: Contact Active | G63: Boolean | I63: 0..1 | J63: Boolean to indicate whether the contact is active (="true") or inactive (="false") | K63: bus
A64: 71 | B64: 2 | C64: Composition | E64: Contact | F64: Contact | H64: Phone | I64: 0..* | J64: Contact Phone Number | K64: bus
A65: 72 | B65: 2 | C65: Composition | E65: Contact | F65: Contact | H65: Fax | I65: 0..* | J65: Contact Fax Number Class | K65: bus
A66: 73 | B66: 2 | C66: Composition | E66: Contact | F66: Contact | H66: Email | I66: 0..* | J66: Contact E-mail address class | K66: bus
A67: 75 | B67: 2 | C67: Attribute | E67: Accounting Method Structure | F67: Accounting Method | G67: Token | I67: 0..1 | J67: For this entity, the method of accounting represented - from: accrual, cash, modified cash, modified accrual, encumbrance, special methods, hybrid methods, other | K67: bus
A68: 76 | B68: 2 | C68: Attribute | E68: Accounting Method Structure | F68: Accounting Method Description | G68: String | I68: 0..1 | J68: Free format description of the accounting method | K68: bus
A69: 77 | B69: 2 | C69: Attribute | E69: Accounting Method Structure | F69: Accounting Method Purpose | G69: Token | I69: 0..1 | J69: For this entity, the reporting purpose represented - from book, tax, management, statutory, other | K69: bus
A70: 78 | B70: 2 | C70: Attribute | E70: Accounting Method Structure | F70: Accounting Method Purpose Description | G70: String | I70: 0..1 | J70: Free format description of the accounting method purpose | K70: bus
A71: 79 | B71: 2 | C71: Attribute | E71: Accounting Method Structure | F71: Accounting Method Start Date | G71: Date Time | I71: 0..1 | J71: Accounting Method Start Date | K71: bus
A72: 80 | B72: 2 | C72: Attribute | E72: Accounting Method Structure | F72: Accounting Method End Date | G72: Date Time | I72: 0..1 | J72: Accounting Method End Date | K72: bus
A73: 82 | B73: 2 | C73: Attribute | E73: Accountant | F73: Accountant Name | G73: String | I73: 0..1 | J73: Name of the accountant | K73: bus
A74: 83 | B74: 2 | C74: Attribute | E74: Accountant | F74: Accountant Type of Engagement | G74: Token | I74: 0..1 | J74: Type of engagement being performed by external accountant. Enumerated as: audit, review, compilation, tax, other. | K74: bus
A75: 84 | B75: 2 | C75: Attribute | E75: Accountant | F75: Accountant Type of Engagement Description | G75: String | I75: 0..1 | J75: Free format description of the type of engagement | K75: bus
A76: 85 | B76: 2 | C76: Composition | E76: Accountant | H76: Accountant_ Address | I76: 0..* | J76: Class which contains accountant address information. | K76: bus
A77: 86 | B77: 2 | C77: Composition | E77: Accountant | H77: Accountant_ Contact | I77: 0..* | J77: Accountant Contact Information Class | K77: bus
A78: 88 | B78: 2 | C78: Attribute | D78: PK | E78: Period | F78: Period ID | G78: String | I78: 0..1 | J78: An identifier for this period in this calendar | K78: bus
A79: 89 | B79: 2 | C79: Attribute | E79: Period | F79: Period Description | G79: String | I79: 0..1 | J79: A description of this specific reporting period in this calendar. | K79: bus
A80: 90 | B80: 2 | C80: Attribute | E80: Period | F80: Period Start Date | G80: Date Time | I80: 0..1 | J80: The beginning date/time of a period | K80: bus
A81: 91 | B81: 2 | C81: Attribute | E81: Period | F81: Period End Date | G81: Date Time | I81: 0..1 | J81: The ending date/time of a period | K81: bus
A82: 93 | B82: 2 | C82: Specialization | E82: Reporting Calendar_ Period | H82: Period | I82: 1 | K82: bus
A83: 94 | B83: 2 | C83: Attribute | D83: PK | E83: Reporting Calendar_ Period | F83: Reporting Calendar_ Period ID | G83: String | I83: 0..1 | J83: An identifier for this period in this calendar | K83: bus
A84: 95 | B84: 2 | C84: Attribute | E84: Reporting Calendar_ Period | F84: Reporting Calendar_ Period Description | G84: String | I84: 0..1 | J84: A description of this specific reporting period in this calendar. | K84: bus
A85: 96 | B85: 2 | C85: Attribute | E85: Reporting Calendar_ Period | F85: Reporting Calendar_ Period Start Date | G85: Date Time | I85: 0..1 | J85: The beginning date/time of a period | K85: bus
A86: 97 | B86: 2 | C86: Attribute | E86: Reporting Calendar_ Period | F86: Reporting Calendar_ Period End Date | G86: Date Time | I86: 0..1 | J86: The ending date/time of a period | K86: bus
A87: 98 | B87: 2 | C87: Attribute | E87: Reporting Calendar_ Period | F87: Reporting Calendar_ Period Closed Date | G87: Date Time | I87: 0..1 | J87: The date/time a period has been closed for activity. If this is present with a nill value (xsi:nill="true") then the period is not closed. | K87: bus
A88: 100 | B88: 2 | C88: Attribute | E88: Reporting Calendar | F88: Reporting Calendar Code | G88: String | I88: 0..1 | J88: The code used to identify this specific reporting calendar, unique across periods | K88: bus
A89: 101 | B89: 2 | C89: Attribute | E89: Reporting Calendar | F89: Reporting Calendar Description | G89: String | I89: 0..1 | J89: A description of the reporting calendar (associated with the reportingCalendarCode given) | K89: bus
A90: 102 | B90: 2 | C90: Attribute | E90: Reporting Calendar | F90: Reporting Calendar Title | G90: String | I90: 0..1 | J90: A description of the reporting period. The actual beginning and ending dates are found within the 'reportingCalendarPeriod' class | K90: bus
A91: 103 | B91: 2 | C91: Attribute | E91: Reporting Calendar | F91: Reporting Calendar Type Code | G91: Token | I91: 0..1 | J91: A code for the type of period involved. Enumerated as: monthly, quarterly, semi-annually, 4-5-4, ad-hoc, other. | K91: bus
A92: 104 | B92: 2 | C92: Attribute | E92: Reporting Calendar | F92: Reporting Calendar Description | G92: String | I92: 0..1 | J92: A description of the type of period involved. | K92: bus
A93: 105 | B93: 2 | C93: Attribute | E93: Reporting Calendar | F93: Reporting Calendar Closed Status | G93: Token | I93: 0..1 | J93: An identifier on whether the reporting calendar is still open for activity. enumerated, "open", "closed", "pending" | K93: bus
A94: 106 | B94: 2 | C94: Attribute | E94: Reporting Calendar | F94: Reporting Calendar Purpose | G94: Token | I94: 0..1 | J94: A description of the accounting set of books involved. Uses enumeration from accounting method purpose. | K94: bus
A95: 107 | B95: 2 | C95: Attribute | E95: Reporting Calendar | F95: Reporting Calendar Purpose Description | G95: String | I95: 0..1 | J95: Free format description of the reporting purpose | K95: bus
A96: 108 | B96: 2 | C96: Composition | E96: Reporting Calendar | H96: Reporting Calendar_ Period | I96: 0..* | J96: A tool to collect a specific set of periods used to summarize results from transactions. | K96: bus
A97: 110 | B97: 2 | C97: Attribute | D97: PK | E97: Authority Registered Identifier | F97: Authority Registered ID | G97: String | I97: 0..1 | J97: Identifier of the registered authority identifier record within this report, used to uniquely identify and reference the instance. | K97: cor
A98: 111 | B98: 2 | C98: Attribute | E98: Authority Registered Identifier | F98: Authority Registered Name | G98: String | I98: 0..1 | J98: Name or descriptive label of the identifier as registered with the authority. | K98: cor
A99: 112 | B99: 2 | C99: Attribute | D99: PK | E99: Authority Registered Identifier | F99: Authority Code | G99: String | I99: 0..1 | J99: Code identifying the external authority with which the identifier is registered. | K99: cor
A100: 113 | B100: 2 | C100: Attribute | E100: Authority Registered Identifier | F100: Authority Name | G100: String | I100: 0..1 | J100: Name of the external authority responsible for registering or verifying the identifier. | K100: cor
A101: 114 | B101: 2 | C101: Attribute | E101: Authority Registered Identifier | F101: Authority Verification Date | G101: Date Time | I101: 0..1 | J101: Date on which the external authority last verified or confirmed the registered identifier. | K101: cor
A102: 116 | B102: 2 | C102: Attribute | D102: PK | E102: Identifier Reference | F102: Identifier Type | G102: Token | I102: 0..1 | J102: Entity type (enumerated): C, customer, E, employee, V, vendor, O, other, I, salesperson-internal, X, salesperson-external, N, contractor. | K102: cor
A103: 117 | B103: 2 | C103: Attribute | D103: PK | E103: Identifier Reference | F103: Identifier Code | G103: String | I103: 0..1 | J103: Internal ID Number associated with identifierReference | K103: cor
A104: 118 | B104: 2 | C104: Attribute | E104: Identifier Reference | F104: Identifier Organization Type | G104: Token | I104: 0..1 | J104: Identifier Organization Type. Enumerated as: individual, organization, other. | K104: cor
...

Sheet FSM
A1: seq | B1: level | C1: Property type | D1: Identifier | E1: Class | F1: Property Term | G1: BaseType | H1: Associated Class | I1: Multiplicity | J1: Documentation | K1: module | L1: module
A2: 1 | B2: 1 | C2: Class | E2: Communication | I2: 0..* | J2: The exchange of messages or information between parties using a specified communication channel. | K2: bus | L2: =_xlfn.LET( _xlpm.c,C2,_xlpm.e,E2,_xlpm.f,F2,_xlpm.h,H2, IF( ISNUMBER(MATCH(_xlpm.c,{"Abstract Class","Class"},0)), _xlfn.XLOOKUP(_xlpm.e,Class!E:E,Class!K:K,""), IF(ISNUMBER(MATCH(_xlpm.c,{"Composition","Reference Association","Specialization"},0)), _xlfn.XLOOKUP(_xlpm.h,Class!E:E,Class!K:K,""), _xlfn.XLOOKUP(_xlpm.f,Property!F:F,Property!K:K,"") ) ) ) -> bus
A3: 2 | B3: 2 | C3: Attribute | E3: Communication | F3: Communication URI Identifier | G3: String | I3: 0..1 | J3: The Uniform Resource Identifier (URI), such as a web or an email address, for this communication. | K3: bus | L3: =_xlfn.LET( _xlpm.c,C3,_xlpm.e,E3,_xlpm.f,F3,_xlpm.h,H3, IF( ISNUMBER(MATCH(_xlpm.c,{"Abstract Class","Class"},0)), _xlfn.XLOOKUP(_xlpm.e,Class!E:E,Class!K:K,""), IF(ISNUMBER(MATCH(_xlpm.c,{"Composition","Reference Association","Specialization"},0)), _xlfn.XLOOKUP(_xlpm.h,Class!E:E,Class!K:K,""), _xlfn.XLOOKUP(_xlpm.f,Property!F:F,Property!K:K,"") ) ) ) -> bus
A4: 3 | B4: 2 | C4: Attribute | E4: Communication | F4: Communication Channel Code | G4: String | I4: 0..1 | J4: A code specifying the communication channel or medium through which contact information is provided or used. This code identifies the type of communication mechanism associated with a contact point, in accordance with UN/EDIFACT Data Element 3155 – Communication means type code. It enables consistent interpretation of contact details across systems and jurisdictions. Examples (non-exhaustive): TE (Telephone) Voice or data communication via a telephone network. FX (Telefax) Transmission of documents via facsimile equipment. EM (Electronic mail) Communication using electronic mail (email). AO (Uniform Resource Location : URL) Identification of the Uniform Resource Location (URL) Synonym: World wide web address. The Channel Code is used in conjunction with the corresponding communication identifier (e.g. phone number, fax number, or email address) and supports extensibility for additional communication types as defined by applicable code lists or jurisdictional requirements. | K4: bus | L4: =_xlfn.LET( _xlpm.c,C4,_xlpm.e,E4,_xlpm.f,F4,_xlpm.h,H4, IF( ISNUMBER(MATCH(_xlpm.c,{"Abstract Class","Class"},0)), _xlfn.XLOOKUP(_xlpm.e,Class!E:E,Class!K:K,""), IF(ISNUMBER(MATCH(_xlpm.c,{"Composition","Reference Association","Specialization"},0)), _xlfn.XLOOKUP(_xlpm.h,Class!E:E,Class!K:K,""), _xlfn.XLOOKUP(_xlpm.f,Property!F:F,Property!K:K,"") ) ) ) -> bus
A5: 4 | B5: 2 | C5: Attribute | E5: Communication | F5: Communication Complete Number | G5: String | I5: 0..1 | J5: The text string of characters that make up the complete number for this communication. | K5: bus | L5: =_xlfn.LET( _xlpm.c,C5,_xlpm.e,E5,_xlpm.f,F5,_xlpm.h,H5, IF( ISNUMBER(MATCH(_xlpm.c,{"Abstract Class","Class"},0)), _xlfn.XLOOKUP(_xlpm.e,Class!E:E,Class!K:K,""), IF(ISNUMBER(MATCH(_xlpm.c,{"Composition","Reference Association","Specialization"},0)), _xlfn.XLOOKUP(_xlpm.h,Class!E:E,Class!K:K,""), _xlfn.XLOOKUP(_xlpm.f,Property!F:F,Property!K:K,"") ) ) ) -> bus
A6: 5 | B6: 2 | C6: Attribute | E6: Communication | F6: Communication Use Code | G6: String | I6: 0..1 | J6: The code specifying the usage or purpose of this communication, such as main, investor-relations, direct. Enumerated as: bookkeeper, controller, direct, fax, investor-relations, main, switchboard, other. | K6: bus | L6: =_xlfn.LET( _xlpm.c,C6,_xlpm.e,E6,_xlpm.f,F6,_xlpm.h,H6, IF( ISNUMBER(MATCH(_xlpm.c,{"Abstract Class","Class"},0)), _xlfn.XLOOKUP(_xlpm.e,Class!E:E,Class!K:K,""), IF(ISNUMBER(MATCH(_xlpm.c,{"Composition","Reference Association","Specialization"},0)), _xlfn.XLOOKUP(_xlpm.h,Class!E:E,Class!K:K,""), _xlfn.XLOOKUP(_xlpm.f,Property!F:F,Property!K:K,"") ) ) ) -> bus
A7: 6 | B7: 1 | C7: Class | E7: Phone | I7: 0..* | J7: Phone number information, as a specialisation of Communication. | K7: bus | L7: =_xlfn.LET( _xlpm.c,C7,_xlpm.e,E7,_xlpm.f,F7,_xlpm.h,H7, IF( ISNUMBER(MATCH(_xlpm.c,{"Abstract Class","Class"},0)), _xlfn.XLOOKUP(_xlpm.e,Class!E:E,Class!K:K,""), IF(ISNUMBER(MATCH(_xlpm.c,{"Composition","Reference Association","Specialization"},0)), _xlfn.XLOOKUP(_xlpm.h,Class!E:E,Class!K:K,""), _xlfn.XLOOKUP(_xlpm.f,Property!F:F,Property!K:K,"") ) ) ) -> bus
A8: 7 | B8: 2 | C8: Specialization | E8: Phone | H8: Communication | I8: 1 | J8: Specialisation of Communication for telephone. Communication Channel Code SHALL be 'telephone'. | K8: bus | L8: =_xlfn.LET( _xlpm.c,C8,_xlpm.e,E8,_xlpm.f,F8,_xlpm.h,H8, IF( ISNUMBER(MATCH(_xlpm.c,{"Abstract Class","Class"},0)), _xlfn.XLOOKUP(_xlpm.e,Class!E:E,Class!K:K,""), IF(ISNUMBER(MATCH(_xlpm.c,{"Composition","Reference Association","Specialization"},0)), _xlfn.XLOOKUP(_xlpm.h,Class!E:E,Class!K:K,""), _xlfn.XLOOKUP(_xlpm.f,Property!F:F,Property!K:K,"") ) ) ) -> bus
A9: 8 | B9: 2 | C9: Attribute | E9: Phone | F9: Phone URI Identifier | G9: String | I9: 0..1 | J9: The Uniform Resource Identifier (URI), such as a web or an email address, for this communication. | K9: bus | L9: =_xlfn.LET( _xlpm.c,C9,_xlpm.e,E9,_xlpm.f,F9,_xlpm.h,H9, IF( ISNUMBER(MATCH(_xlpm.c,{"Abstract Class","Class"},0)), _xlfn.XLOOKUP(_xlpm.e,Class!E:E,Class!K:K,""), IF(ISNUMBER(MATCH(_xlpm.c,{"Composition","Reference Association","Specialization"},0)), _xlfn.XLOOKUP(_xlpm.h,Class!E:E,Class!K:K,""), _xlfn.XLOOKUP(_xlpm.f,Property!F:F,Property!K:K,"") ) ) ) -> bus
A10: 9 | B10: 2 | C10: Attribute | E10: Phone | F10: Phone Channel Code | G10: String | I10: 0..1 | J10: A code specifying the communication channel or medium through which contact information is provided or used. This code identifies the type of communication mechanism associated with a contact point, in accordance with UN/EDIFACT Data Element 3155 – Communication means type code. It enables consistent interpretation of contact details across systems and jurisdictions. Examples (non-exhaustive): TE (Telephone) Voice or data communication via a telephone network. FX (Telefax) Transmission of documents via facsimile equipment. EM (Electronic mail) Communication using electronic mail (email). The Channel Code is used in conjunction with the corresponding communication identifier (e.g. phone number, fax number, or email address) and supports extensibility for additional communication types as defined by applicable code lists or jurisdictional requirements. | K10: bus | L10: =_xlfn.LET( _xlpm.c,C10,_xlpm.e,E10,_xlpm.f,F10,_xlpm.h,H10, IF( ISNUMBER(MATCH(_xlpm.c,{"Abstract Class","Class"},0)), _xlfn.XLOOKUP(_xlpm.e,Class!E:E,Class!K:K,""), IF(ISNUMBER(MATCH(_xlpm.c,{"Composition","Reference Association","Specialization"},0)), _xlfn.XLOOKUP(_xlpm.h,Class!E:E,Class!K:K,""), _xlfn.XLOOKUP(_xlpm.f,Property!F:F,Property!K:K,"") ) ) ) -> bus
A11: 10 | B11: 2 | C11: Attribute | E11: Phone | F11: Phone Complete Number | G11: String | I11: 0..1 | J11: The text string of characters that make up the complete number for this communication. | K11: bus | L11: =_xlfn.LET( _xlpm.c,C11,_xlpm.e,E11,_xlpm.f,F11,_xlpm.h,H11, IF( ISNUMBER(MATCH(_xlpm.c,{"Abstract Class","Class"},0)), _xlfn.XLOOKUP(_xlpm.e,Class!E:E,Class!K:K,""), IF(ISNUMBER(MATCH(_xlpm.c,{"Composition","Reference Association","Specialization"},0)), _xlfn.XLOOKUP(_xlpm.h,Class!E:E,Class!K:K,""), _xlfn.XLOOKUP(_xlpm.f,Property!F:F,Property!K:K,"") ) ) ) -> bus
A12: 11 | B12: 2 | C12: Attribute | E12: Phone | F12: Phone Use Code | G12: String | I12: 0..1 | J12: The code specifying the usage or purpose of this communication, such as main, investor-relations, direct. Enumerated as: bookkeeper, controller, direct, fax, investor-relations, main, switchboard, other. | K12: bus | L12: =_xlfn.LET( _xlpm.c,C12,_xlpm.e,E12,_xlpm.f,F12,_xlpm.h,H12, IF( ISNUMBER(MATCH(_xlpm.c,{"Abstract Class","Class"},0)), _xlfn.XLOOKUP(_xlpm.e,Class!E:E,Class!K:K,""), IF(ISNUMBER(MATCH(_xlpm.c,{"Composition","Reference Association","Specialization"},0)), _xlfn.XLOOKUP(_xlpm.h,Class!E:E,Class!K:K,""), _xlfn.XLOOKUP(_xlpm.f,Property!F:F,Property!K:K,"") ) ) ) -> bus
A13: 12 | B13: 1 | C13: Class | E13: Fax | I13: 0..* | J13: Fax number information. | K13: bus | L13: =_xlfn.LET( _xlpm.c,C13,_xlpm.e,E13,_xlpm.f,F13,_xlpm.h,H13, IF( ISNUMBER(MATCH(_xlpm.c,{"Abstract Class","Class"},0)), _xlfn.XLOOKUP(_xlpm.e,Class!E:E,Class!K:K,""), IF(ISNUMBER(MATCH(_xlpm.c,{"Composition","Reference Association","Specialization"},0)), _xlfn.XLOOKUP(_xlpm.h,Class!E:E,Class!K:K,""), _xlfn.XLOOKUP(_xlpm.f,Property!F:F,Property!K:K,"") ) ) ) -> bus
A14: 13 | B14: 2 | C14: Specialization | E14: Fax | H14: Communication | I14: 1 | J14: Specialisation of Communication for telephone. Communication Channel Code SHALL be 'telephone'. | K14: bus | L14: =_xlfn.LET( _xlpm.c,C14,_xlpm.e,E14,_xlpm.f,F14,_xlpm.h,H14, IF( ISNUMBER(MATCH(_xlpm.c,{"Abstract Class","Class"},0)), _xlfn.XLOOKUP(_xlpm.e,Class!E:E,Class!K:K,""), IF(ISNUMBER(MATCH(_xlpm.c,{"Composition","Reference Association","Specialization"},0)), _xlfn.XLOOKUP(_xlpm.h,Class!E:E,Class!K:K,""), _xlfn.XLOOKUP(_xlpm.f,Property!F:F,Property!K:K,"") ) ) ) -> bus
A15: 14 | B15: 2 | C15: Attribute | E15: Fax | F15: Fax URI Identifier | G15: String | I15: 0..1 | J15: The Uniform Resource Identifier (URI), such as a web or an email address, for this communication. | K15: bus | L15: =_xlfn.LET( _xlpm.c,C15,_xlpm.e,E15,_xlpm.f,F15,_xlpm.h,H15, IF( ISNUMBER(MATCH(_xlpm.c,{"Abstract Class","Class"},0)), _xlfn.XLOOKUP(_xlpm.e,Class!E:E,Class!K:K,""), IF(ISNUMBER(MATCH(_xlpm.c,{"Composition","Reference Association","Specialization"},0)), _xlfn.XLOOKUP(_xlpm.h,Class!E:E,Class!K:K,""), _xlfn.XLOOKUP(_xlpm.f,Property!F:F,Property!K:K,"") ) ) ) -> bus
A16: 15 | B16: 2 | C16: Attribute | E16: Fax | F16: Fax Channel Code | G16: String | I16: 0..1 | J16: A code specifying the communication channel or medium through which contact information is provided or used. This code identifies the type of communication mechanism associated with a contact point, in accordance with UN/EDIFACT Data Element 3155 – Communication means type code. It enables consistent interpretation of contact details across systems and jurisdictions. Examples (non-exhaustive): TE (Telephone) Voice or data communication via a telephone network. FX (Telefax) Transmission of documents via facsimile equipment. EM (Electronic mail) Communication using electronic mail (email). The Channel Code is used in conjunction with the corresponding communication identifier (e.g. phone number, fax number, or email address) and supports extensibility for additional communication types as defined by applicable code lists or jurisdictional requirements. | K16: bus | L16: =_xlfn.LET( _xlpm.c,C16,_xlpm.e,E16,_xlpm.f,F16,_xlpm.h,H16, IF( ISNUMBER(MATCH(_xlpm.c,{"Abstract Class","Class"},0)), _xlfn.XLOOKUP(_xlpm.e,Class!E:E,Class!K:K,""), IF(ISNUMBER(MATCH(_xlpm.c,{"Composition","Reference Association","Specialization"},0)), _xlfn.XLOOKUP(_xlpm.h,Class!E:E,Class!K:K,""), _xlfn.XLOOKUP(_xlpm.f,Property!F:F,Property!K:K,"") ) ) ) -> bus
A17: 16 | B17: 2 | C17: Attribute | E17: Fax | F17: Fax Complete Number | G17: String | I17: 0..1 | J17: The text string of characters that make up the complete number for this communication. | K17: bus | L17: =_xlfn.LET( _xlpm.c,C17,_xlpm.e,E17,_xlpm.f,F17,_xlpm.h,H17, IF( ISNUMBER(MATCH(_xlpm.c,{"Abstract Class","Class"},0)), _xlfn.XLOOKUP(_xlpm.e,Class!E:E,Class!K:K,""), IF(ISNUMBER(MATCH(_xlpm.c,{"Composition","Reference Association","Specialization"},0)), _xlfn.XLOOKUP(_xlpm.h,Class!E:E,Class!K:K,""), _xlfn.XLOOKUP(_xlpm.f,Property!F:F,Property!K:K,"") ) ) ) -> bus
A18: 17 | B18: 2 | C18: Attribute | E18: Fax | F18: Fax Use Code | G18: String | I18: 0..1 | J18: The code specifying the usage or purpose of this communication, such as main, investor-relations, direct. Enumerated as: bookkeeper, controller, direct, fax, investor-relations, main, switchboard, other. | K18: bus | L18: =_xlfn.LET( _xlpm.c,C18,_xlpm.e,E18,_xlpm.f,F18,_xlpm.h,H18, IF( ISNUMBER(MATCH(_xlpm.c,{"Abstract Class","Class"},0)), _xlfn.XLOOKUP(_xlpm.e,Class!E:E,Class!K:K,""), IF(ISNUMBER(MATCH(_xlpm.c,{"Composition","Reference Association","Specialization"},0)), _xlfn.XLOOKUP(_xlpm.h,Class!E:E,Class!K:K,""), _xlfn.XLOOKUP(_xlpm.f,Property!F:F,Property!K:K,"") ) ) ) -> bus
A19: 18 | B19: 1 | C19: Class | E19: Email | I19: 0..* | J19: Email address information. | K19: bus | L19: =_xlfn.LET( _xlpm.c,C19,_xlpm.e,E19,_xlpm.f,F19,_xlpm.h,H19, IF( ISNUMBER(MATCH(_xlpm.c,{"Abstract Class","Class"},0)), _xlfn.XLOOKUP(_xlpm.e,Class!E:E,Class!K:K,""), IF(ISNUMBER(MATCH(_xlpm.c,{"Composition","Reference Association","Specialization"},0)), _xlfn.XLOOKUP(_xlpm.h,Class!E:E,Class!K:K,""), _xlfn.XLOOKUP(_xlpm.f,Property!F:F,Property!K:K,"") ) ) ) -> bus
A20: 19 | B20: 2 | C20: Specialization | E20: Email | H20: Communication | I20: 1 | J20: Specialisation of Communication for telephone. Communication Channel Code SHALL be 'telephone'. | K20: bus | L20: =_xlfn.LET( _xlpm.c,C20,_xlpm.e,E20,_xlpm.f,F20,_xlpm.h,H20, IF( ISNUMBER(MATCH(_xlpm.c,{"Abstract Class","Class"},0)), _xlfn.XLOOKUP(_xlpm.e,Class!E:E,Class!K:K,""), IF(ISNUMBER(MATCH(_xlpm.c,{"Composition","Reference Association","Specialization"},0)), _xlfn.XLOOKUP(_xlpm.h,Class!E:E,Class!K:K,""), _xlfn.XLOOKUP(_xlpm.f,Property!F:F,Property!K:K,"") ) ) ) -> bus
A21: 20 | B21: 2 | C21: Attribute | E21: Email | F21: Email URI Identifier | G21: String | I21: 0..1 | J21: The Uniform Resource Identifier (URI), such as a web or an email address, for this communication. | K21: bus | L21: =_xlfn.LET( _xlpm.c,C21,_xlpm.e,E21,_xlpm.f,F21,_xlpm.h,H21, IF( ISNUMBER(MATCH(_xlpm.c,{"Abstract Class","Class"},0)), _xlfn.XLOOKUP(_xlpm.e,Class!E:E,Class!K:K,""), IF(ISNUMBER(MATCH(_xlpm.c,{"Composition","Reference Association","Specialization"},0)), _xlfn.XLOOKUP(_xlpm.h,Class!E:E,Class!K:K,""), _xlfn.XLOOKUP(_xlpm.f,Property!F:F,Property!K:K,"") ) ) ) -> bus
A22: 21 | B22: 2 | C22: Attribute | E22: Email | F22: Email Channel Code | G22: String | I22: 0..1 | J22: A code specifying the communication channel or medium through which contact information is provided or used. This code identifies the type of communication mechanism associated with a contact point, in accordance with UN/EDIFACT Data Element 3155 – Communication means type code. It enables consistent interpretation of contact details across systems and jurisdictions. Examples (non-exhaustive): TE (Telephone) Voice or data communication via a telephone network. FX (Telefax) Transmission of documents via facsimile equipment. EM (Electronic mail) Communication using electronic mail (email). The Channel Code is used in conjunction with the corresponding communication identifier (e.g. phone number, fax number, or email address) and supports extensibility for additional communication types as defined by applicable code lists or jurisdictional requirements. | K22: bus | L22: =_xlfn.LET( _xlpm.c,C22,_xlpm.e,E22,_xlpm.f,F22,_xlpm.h,H22, IF( ISNUMBER(MATCH(_xlpm.c,{"Abstract Class","Class"},0)), _xlfn.XLOOKUP(_xlpm.e,Class!E:E,Class!K:K,""), IF(ISNUMBER(MATCH(_xlpm.c,{"Composition","Reference Association","Specialization"},0)), _xlfn.XLOOKUP(_xlpm.h,Class!E:E,Class!K:K,""), _xlfn.XLOOKUP(_xlpm.f,Property!F:F,Property!K:K,"") ) ) ) -> bus
A23: 22 | B23: 2 | C23: Attribute | E23: Email | F23: Email Complete Number | G23: String | I23: 0..1 | J23: The text string of characters that make up the complete number for this communication. | K23: bus | L23: =_xlfn.LET( _xlpm.c,C23,_xlpm.e,E23,_xlpm.f,F23,_xlpm.h,H23, IF( ISNUMBER(MATCH(_xlpm.c,{"Abstract Class","Class"},0)), _xlfn.XLOOKUP(_xlpm.e,Class!E:E,Class!K:K,""), IF(ISNUMBER(MATCH(_xlpm.c,{"Composition","Reference Association","Specialization"},0)), _xlfn.XLOOKUP(_xlpm.h,Class!E:E,Class!K:K,""), _xlfn.XLOOKUP(_xlpm.f,Property!F:F,Property!K:K,"") ) ) ) -> bus
A24: 23 | B24: 2 | C24: Attribute | E24: Email | F24: Email Use Code | G24: String | I24: 0..1 | J24: The code specifying the usage or purpose of this communication, such as main, investor-relations, direct. Enumerated as: bookkeeper, controller, direct, fax, investor-relations, main, switchboard, other. | K24: bus | L24: =_xlfn.LET( _xlpm.c,C24,_xlpm.e,E24,_xlpm.f,F24,_xlpm.h,H24, IF( ISNUMBER(MATCH(_xlpm.c,{"Abstract Class","Class"},0)), _xlfn.XLOOKUP(_xlpm.e,Class!E:E,Class!K:K,""), IF(ISNUMBER(MATCH(_xlpm.c,{"Composition","Reference Association","Specialization"},0)), _xlfn.XLOOKUP(_xlpm.h,Class!E:E,Class!K:K,""), _xlfn.XLOOKUP(_xlpm.f,Property!F:F,Property!K:K,"") ) ) ) -> bus
A25: 24 | B25: 1 | C25: Class | E25: Web Site | I25: 0..* | J25: Web site information. | K25: bus | L25: =_xlfn.LET( _xlpm.c,C25,_xlpm.e,E25,_xlpm.f,F25,_xlpm.h,H25, IF( ISNUMBER(MATCH(_xlpm.c,{"Abstract Class","Class"},0)), _xlfn.XLOOKUP(_xlpm.e,Class!E:E,Class!K:K,""), IF(ISNUMBER(MATCH(_xlpm.c,{"Composition","Reference Association","Specialization"},0)), _xlfn.XLOOKUP(_xlpm.h,Class!E:E,Class!K:K,""), _xlfn.XLOOKUP(_xlpm.f,Property!F:F,Property!K:K,"") ) ) ) -> bus
A26: 25 | B26: 2 | C26: Specialization | E26: Web Site | H26: Communication | I26: 1 | J26: Specialisation of Communication for telephone. Communication Channel Code SHALL be 'telephone'. | K26: bus | L26: =_xlfn.LET( _xlpm.c,C26,_xlpm.e,E26,_xlpm.f,F26,_xlpm.h,H26, IF( ISNUMBER(MATCH(_xlpm.c,{"Abstract Class","Class"},0)), _xlfn.XLOOKUP(_xlpm.e,Class!E:E,Class!K:K,""), IF(ISNUMBER(MATCH(_xlpm.c,{"Composition","Reference Association","Specialization"},0)), _xlfn.XLOOKUP(_xlpm.h,Class!E:E,Class!K:K,""), _xlfn.XLOOKUP(_xlpm.f,Property!F:F,Property!K:K,"") ) ) ) -> bus
A27: 26 | B27: 2 | C27: Attribute | E27: Web Site | F27: Web Site URI Identifier | G27: String | I27: 0..1 | J27: The Uniform Resource Identifier (URI), such as a web or an email address, for this communication. | K27: bus | L27: =_xlfn.LET( _xlpm.c,C27,_xlpm.e,E27,_xlpm.f,F27,_xlpm.h,H27, IF( ISNUMBER(MATCH(_xlpm.c,{"Abstract Class","Class"},0)), _xlfn.XLOOKUP(_xlpm.e,Class!E:E,Class!K:K,""), IF(ISNUMBER(MATCH(_xlpm.c,{"Composition","Reference Association","Specialization"},0)), _xlfn.XLOOKUP(_xlpm.h,Class!E:E,Class!K:K,""), _xlfn.XLOOKUP(_xlpm.f,Property!F:F,Property!K:K,"") ) ) ) -> bus
A28: 27 | B28: 2 | C28: Attribute | E28: Web Site | F28: Web Site Channel Code | G28: String | I28: 0..1 | J28: A code specifying the communication channel or medium through which contact information is provided or used. This code identifies the type of communication mechanism associated with a contact point, in accordance with UN/EDIFACT Data Element 3155 – Communication means type code. It enables consistent interpretation of contact details across systems and jurisdictions. Examples (non-exhaustive): TE (Telephone) Voice or data communication via a telephone network. FX (Telefax) Transmission of documents via facsimile equipment. EM (Electronic mail) Communication using electronic mail (email). The Channel Code is used in conjunction with the corresponding communication identifier (e.g. phone number, fax number, or email address) and supports extensibility for additional communication types as defined by applicable code lists or jurisdictional requirements. | K28: bus | L28: =_xlfn.LET( _xlpm.c,C28,_xlpm.e,E28,_xlpm.f,F28,_xlpm.h,H28, IF( ISNUMBER(MATCH(_xlpm.c,{"Abstract Class","Class"},0)), _xlfn.XLOOKUP(_xlpm.e,Class!E:E,Class!K:K,""), IF(ISNUMBER(MATCH(_xlpm.c,{"Composition","Reference Association","Specialization"},0)), _xlfn.XLOOKUP(_xlpm.h,Class!E:E,Class!K:K,""), _xlfn.XLOOKUP(_xlpm.f,Property!F:F,Property!K:K,"") ) ) ) -> bus
A29: 28 | B29: 2 | C29: Attribute | E29: Web Site | F29: Web Site Complete Number | G29: String | I29: 0..1 | J29: The text string of characters that make up the complete number for this communication. | K29: bus | L29: =_xlfn.LET( _xlpm.c,C29,_xlpm.e,E29,_xlpm.f,F29,_xlpm.h,H29, IF( ISNUMBER(MATCH(_xlpm.c,{"Abstract Class","Class"},0)), _xlfn.XLOOKUP(_xlpm.e,Class!E:E,Class!K:K,""), IF(ISNUMBER(MATCH(_xlpm.c,{"Composition","Reference Association","Specialization"},0)), _xlfn.XLOOKUP(_xlpm.h,Class!E:E,Class!K:K,""), _xlfn.XLOOKUP(_xlpm.f,Property!F:F,Property!K:K,"") ) ) ) -> bus
A30: 29 | B30: 2 | C30: Attribute | E30: Web Site | F30: Web Site Use Code | G30: String | I30: 0..1 | J30: The code specifying the usage or purpose of this communication, such as main, investor-relations, direct. Enumerated as: bookkeeper, controller, direct, fax, investor-relations, main, switchboard, other. | K30: bus | L30: =_xlfn.LET( _xlpm.c,C30,_xlpm.e,E30,_xlpm.f,F30,_xlpm.h,H30, IF( ISNUMBER(MATCH(_xlpm.c,{"Abstract Class","Class"},0)), _xlfn.XLOOKUP(_xlpm.e,Class!E:E,Class!K:K,""), IF(ISNUMBER(MATCH(_xlpm.c,{"Composition","Reference Association","Specialization"},0)), _xlfn.XLOOKUP(_xlpm.h,Class!E:E,Class!K:K,""), _xlfn.XLOOKUP(_xlpm.f,Property!F:F,Property!K:K,"") ) ) ) -> bus
A31: 30 | B31: 1 | C31: Class | E31: Address | I31: 0..* | J31: Class which contains address information. | K31: bus | L31: =_xlfn.LET( _xlpm.c,C31,_xlpm.e,E31,_xlpm.f,F31,_xlpm.h,H31, IF( ISNUMBER(MATCH(_xlpm.c,{"Abstract Class","Class"},0)), _xlfn.XLOOKUP(_xlpm.e,Class!E:E,Class!K:K,""), IF(ISNUMBER(MATCH(_xlpm.c,{"Composition","Reference Association","Specialization"},0)), _xlfn.XLOOKUP(_xlpm.h,Class!E:E,Class!K:K,""), _xlfn.XLOOKUP(_xlpm.f,Property!F:F,Property!K:K,"") ) ) ) -> bus
A32: 31 | B32: 2 | C32: Attribute | E32: Address | F32: Address Name | G32: String | I32: 0..1 | J32: Address Name | K32: bus | L32: =_xlfn.LET( _xlpm.c,C32,_xlpm.e,E32,_xlpm.f,F32,_xlpm.h,H32, IF( ISNUMBER(MATCH(_xlpm.c,{"Abstract Class","Class"},0)), _xlfn.XLOOKUP(_xlpm.e,Class!E:E,Class!K:K,""), IF(ISNUMBER(MATCH(_xlpm.c,{"Composition","Reference Association","Specialization"},0)), _xlfn.XLOOKUP(_xlpm.h,Class!E:E,Class!K:K,""), _xlfn.XLOOKUP(_xlpm.f,Property!F:F,Property!K:K,"") ) ) ) -> bus
A33: 32 | B33: 2 | C33: Attribute | E33: Address | F33: Address Description | G33: String | I33: 0..1 | J33: Address Description | K33: bus | L33: =_xlfn.LET( _xlpm.c,C33,_xlpm.e,E33,_xlpm.f,F33,_xlpm.h,H33, IF( ISNUMBER(MATCH(_xlpm.c,{"Abstract Class","Class"},0)), _xlfn.XLOOKUP(_xlpm.e,Class!E:E,Class!K:K,""), IF(ISNUMBER(MATCH(_xlpm.c,{"Composition","Reference Association","Specialization"},0)), _xlfn.XLOOKUP(_xlpm.h,Class!E:E,Class!K:K,""), _xlfn.XLOOKUP(_xlpm.f,Property!F:F,Property!K:K,"") ) ) ) -> bus
A34: 33 | B34: 2 | C34: Attribute | E34: Address | F34: Address Purpose | G34: String | I34: 0..1 | J34: Address Purpose | K34: bus | L34: =_xlfn.LET( _xlpm.c,C34,_xlpm.e,E34,_xlpm.f,F34,_xlpm.h,H34, IF( ISNUMBER(MATCH(_xlpm.c,{"Abstract Class","Class"},0)), _xlfn.XLOOKUP(_xlpm.e,Class!E:E,Class!K:K,""), IF(ISNUMBER(MATCH(_xlpm.c,{"Composition","Reference Association","Specialization"},0)), _xlfn.XLOOKUP(_xlpm.h,Class!E:E,Class!K:K,""), _xlfn.XLOOKUP(_xlpm.f,Property!F:F,Property!K:K,"") ) ) ) -> bus
A35: 34 | B35: 2 | C35: Attribute | E35: Address | F35: Location ID | G35: String | I35: 0..1 | J35: A code used to identify the location and to associate it with contacts and transactions | K35: bus | L35: =_xlfn.LET( _xlpm.c,C35,_xlpm.e,E35,_xlpm.f,F35,_xlpm.h,H35, IF( ISNUMBER(MATCH(_xlpm.c,{"Abstract Class","Class"},0)), _xlfn.XLOOKUP(_xlpm.e,Class!E:E,Class!K:K,""), IF(ISNUMBER(MATCH(_xlpm.c,{"Composition","Reference Association","Specialization"},0)), _xlfn.XLOOKUP(_xlpm.h,Class!E:E,Class!K:K,""), _xlfn.XLOOKUP(_xlpm.f,Property!F:F,Property!K:K,"") ) ) ) -> bus
A36: 35 | B36: 2 | C36: Attribute | E36: Address | F36: Building Number | G36: String | I36: 0..1 | J36: Building Number | K36: bus | L36: =_xlfn.LET( _xlpm.c,C36,_xlpm.e,E36,_xlpm.f,F36,_xlpm.h,H36, IF( ISNUMBER(MATCH(_xlpm.c,{"Abstract Class","Class"},0)), _xlfn.XLOOKUP(_xlpm.e,Class!E:E,Class!K:K,""), IF(ISNUMBER(MATCH(_xlpm.c,{"Composition","Reference Association","Specialization"},0)), _xlfn.XLOOKUP(_xlpm.h,Class!E:E,Class!K:K,""), _xlfn.XLOOKUP(_xlpm.f,Property!F:F,Property!K:K,"") ) ) ) -> bus
A37: 36 | B37: 2 | C37: Attribute | E37: Address | F37: Street | G37: String | I37: 0..1 | J37: Street address | K37: bus | L37: =_xlfn.LET( _xlpm.c,C37,_xlpm.e,E37,_xlpm.f,F37,_xlpm.h,H37, IF( ISNUMBER(MATCH(_xlpm.c,{"Abstract Class","Class"},0)), _xlfn.XLOOKUP(_xlpm.e,Class!E:E,Class!K:K,""), IF(ISNUMBER(MATCH(_xlpm.c,{"Composition","Reference Association","Specialization"},0)), _xlfn.XLOOKUP(_xlpm.h,Class!E:E,Class!K:K,""), _xlfn.XLOOKUP(_xlpm.f,Property!F:F,Property!K:K,"") ) ) ) -> bus
A38: 37 | B38: 2 | C38: Attribute | E38: Address | F38: Address Detail | G38: String | I38: 0..1 | J38: Address Detail | K38: bus | L38: =_xlfn.LET( _xlpm.c,C38,_xlpm.e,E38,_xlpm.f,F38,_xlpm.h,H38, IF( ISNUMBER(MATCH(_xlpm.c,{"Abstract Class","Class"},0)), _xlfn.XLOOKUP(_xlpm.e,Class!E:E,Class!K:K,""), IF(ISNUMBER(MATCH(_xlpm.c,{"Composition","Reference Association","Specialization"},0)), _xlfn.XLOOKUP(_xlpm.h,Class!E:E,Class!K:K,""), _xlfn.XLOOKUP(_xlpm.f,Property!F:F,Property!K:K,"") ) ) ) -> bus
A39: 38 | B39: 2 | C39: Attribute | E39: Address | F39: City | G39: String | I39: 0..1 | J39: City | K39: bus | L39: =_xlfn.LET( _xlpm.c,C39,_xlpm.e,E39,_xlpm.f,F39,_xlpm.h,H39, IF( ISNUMBER(MATCH(_xlpm.c,{"Abstract Class","Class"},0)), _xlfn.XLOOKUP(_xlpm.e,Class!E:E,Class!K:K,""), IF(ISNUMBER(MATCH(_xlpm.c,{"Composition","Reference Association","Specialization"},0)), _xlfn.XLOOKUP(_xlpm.h,Class!E:E,Class!K:K,""), _xlfn.XLOOKUP(_xlpm.f,Property!F:F,Property!K:K,"") ) ) ) -> bus
A40: 39 | B40: 2 | C40: Attribute | E40: Address | F40: State or Province | G40: String | I40: 0..1 | J40: State, province or region | K40: bus | L40: =_xlfn.LET( _xlpm.c,C40,_xlpm.e,E40,_xlpm.f,F40,_xlpm.h,H40, IF( ISNUMBER(MATCH(_xlpm.c,{"Abstract Class","Class"},0)), _xlfn.XLOOKUP(_xlpm.e,Class!E:E,Class!K:K,""), IF(ISNUMBER(MATCH(_xlpm.c,{"Composition","Reference Association","Specialization"},0)), _xlfn.XLOOKUP(_xlpm.h,Class!E:E,Class!K:K,""), _xlfn.XLOOKUP(_xlpm.f,Property!F:F,Property!K:K,"") ) ) ) -> bus
A41: 40 | B41: 2 | C41: Attribute | E41: Address | F41: Country | G41: String | I41: 0..1 | J41: Country | K41: bus | L41: =_xlfn.LET( _xlpm.c,C41,_xlpm.e,E41,_xlpm.f,F41,_xlpm.h,H41, IF( ISNUMBER(MATCH(_xlpm.c,{"Abstract Class","Class"},0)), _xlfn.XLOOKUP(_xlpm.e,Class!E:E,Class!K:K,""), IF(ISNUMBER(MATCH(_xlpm.c,{"Composition","Reference Association","Specialization"},0)), _xlfn.XLOOKUP(_xlpm.h,Class!E:E,Class!K:K,""), _xlfn.XLOOKUP(_xlpm.f,Property!F:F,Property!K:K,"") ) ) ) -> bus
A42: 41 | B42: 2 | C42: Attribute | E42: Address | F42: Zip or Postal Code | G42: String | I42: 0..1 | J42: Zip or other postal code | K42: bus | L42: =_xlfn.LET( _xlpm.c,C42,_xlpm.e,E42,_xlpm.f,F42,_xlpm.h,H42, IF( ISNUMBER(MATCH(_xlpm.c,{"Abstract Class","Class"},0)), _xlfn.XLOOKUP(_xlpm.e,Class!E:E,Class!K:K,""), IF(ISNUMBER(MATCH(_xlpm.c,{"Composition","Reference Association","Specialization"},0)), _xlfn.XLOOKUP(_xlpm.h,Class!E:E,Class!K:K,""), _xlfn.XLOOKUP(_xlpm.f,Property!F:F,Property!K:K,"") ) ) ) -> bus
A43: 42 | B43: 2 | C43: Attribute | E43: Address | F43: Address Active Indicator | G43: Boolean | I43: 0..1 | J43: Boolean to indicate whether the address is active (="true") or inactive (="false") | K43: bus | L43: =_xlfn.LET( _xlpm.c,C43,_xlpm.e,E43,_xlpm.f,F43,_xlpm.h,H43, IF( ISNUMBER(MATCH(_xlpm.c,{"Abstract Class","Class"},0)), _xlfn.XLOOKUP(_xlpm.e,Class!E:E,Class!K:K,""), IF(ISNUMBER(MATCH(_xlpm.c,{"Composition","Reference Association","Specialization"},0)), _xlfn.XLOOKUP(_xlpm.h,Class!E:E,Class!K:K,""), _xlfn.XLOOKUP(_xlpm.f,Property!F:F,Property!K:K,"") ) ) ) -> bus
A44: 43 | B44: 1 | C44: Class | E44: Document Information | I44: 1..1 | J44: Parent for descriptive information about the accountingEntries Class in which it is contained. | K44: bus | L44: =_xlfn.LET( _xlpm.c,C44,_xlpm.e,E44,_xlpm.f,F44,_xlpm.h,H44, IF( ISNUMBER(MATCH(_xlpm.c,{"Abstract Class","Class"},0)), _xlfn.XLOOKUP(_xlpm.e,Class!E:E,Class!K:K,""), IF(ISNUMBER(MATCH(_xlpm.c,{"Composition","Reference Association","Specialization"},0)), _xlfn.XLOOKUP(_xlpm.h,Class!E:E,Class!K:K,""), _xlfn.XLOOKUP(_xlpm.f,Property!F:F,Property!K:K,"") ) ) ) -> bus
A45: 44 | B45: 2 | C45: Attribute | D45: PK | E45: Document Information | F45: Detail Document Number | G45: String | I45: 0..1 | J45: Unique identifier for this file. | K45: bus | L45: =_xlfn.LET( _xlpm.c,C45,_xlpm.e,E45,_xlpm.f,F45,_xlpm.h,H45, IF( ISNUMBER(MATCH(_xlpm.c,{"Abstract Class","Class"},0)), _xlfn.XLOOKUP(_xlpm.e,Class!E:E,Class!K:K,""), IF(ISNUMBER(MATCH(_xlpm.c,{"Composition","Reference Association","Specialization"},0)), _xlfn.XLOOKUP(_xlpm.h,Class!E:E,Class!K:K,""), _xlfn.XLOOKUP(_xlpm.f,Property!F:F,Property!K:K,"") ) ) ) -> bus
A46: 45 | B46: 2 | C46: Attribute | D46: PK | E46: Document Information | F46: Detail Document Type | G46: Token | I46: 1..1 | J46: account: information to fill in a chart of accounts file. balance: the results of accumulation of a complete and validated list of entries for an account (or a list of account) in a specific period - sometimes called general ledger entries: a list of individual accounting entries, which might be posted/validated or nonposted/validated journal: a self-balancing (Dr = Cr) list of entries for a specific period including beginning balance for that period. ledger: a complete list of entries for a specific account (or list of accounts) for a specific period; note - debits do not have to equal credits. assets: a listing of open receivables, payables, inventory, fixed assets or other information that can be extracted from but are not necessarily included as part of a journal entry. trialBalance: the self-balancing (Dr = Cr) result of accumulation of a complete and validated list of entries for the entity in a complete list of accounts in a specific period. taxtables: aids automated interpretation of instances that represent tax tables; Tax table are defined by using multiple [taxes] classs to gather the population of codes, authorities and rates; through [taxTableCode] cross-references in the [taxes] class, these "master file" tax tables can be referenced. mapping: a collection of mappings between interrelated data sets, such as a local and related corporate standard chart of accounts or detail data mapped to summarized end reporting concepts. versioning: a collection of changes between two versions of the same class of information, such as updates to a master file like a chart of accounts. master_file: a collection of master files, such as the customer or inventory master file. trade_documents: a collection of trade/transactional documents, such as vendor invoices or customer orders. profile_compliant: the meaning of this collection of information can be determined by understanding an established profile and especially an XBRL GL Profile. Profiles are determined through namespace declarations, schemaRef and conventions of those profiles. other: for all other types of representations. Often sorted by date or by account, these terms have specific, and sometimes different, meanings in different areas. Common practice will drive accounting method/term matches. | K46: bus | L46: =_xlfn.LET( _xlpm.c,C46,_xlpm.e,E46,_xlpm.f,F46,_xlpm.h,H46, IF( ISNUMBER(MATCH(_xlpm.c,{"Abstract Class","Class"},0)), _xlfn.XLOOKUP(_xlpm.e,Class!E:E,Class!K:K,""), IF(ISNUMBER(MATCH(_xlpm.c,{"Composition","Reference Association","Specialization"},0)), _xlfn.XLOOKUP(_xlpm.h,Class!E:E,Class!K:K,""), _xlfn.XLOOKUP(_xlpm.f,Property!F:F,Property!K:K,"") ) ) ) -> bus
A47: 46 | B47: 2 | C47: Attribute | E47: Document Information | F47: Document Date | G47: Date Time | I47: 0..1 | J47: Date/time file was created. | K47: bus | L47: =_xlfn.LET( _xlpm.c,C47,_xlpm.e,E47,_xlpm.f,F47,_xlpm.h,H47, IF( ISNUMBER(MATCH(_xlpm.c,{"Abstract Class","Class"},0)), _xlfn.XLOOKUP(_xlpm.e,Class!E:E,Class!K:K,""), IF(ISNUMBER(MATCH(_xlpm.c,{"Composition","Reference Association","Specialization"},0)), _xlfn.XLOOKUP(_xlpm.h,Class!E:E,Class!K:K,""), _xlfn.XLOOKUP(_xlpm.f,Property!F:F,Property!K:K,"") ) ) ) -> bus
A48: 47 | B48: 2 | C48: Attribute | E48: Document Information | F48: Revises Audit Number | G48: String | I48: 0..1 | J48: If this batch of information revises a previous batch of information, this field identifies the previous batch that is being revised. 'uniqueID' of the previous batch goes here. Developers should consider exception reporting. | K48: bus | L48: =_xlfn.LET( _xlpm.c,C48,_xlpm.e,E48,_xlpm.f,F48,_xlpm.h,H48, IF( ISNUMBER(MATCH(_xlpm.c,{"Abstract Class","Class"},0)), _xlfn.XLOOKUP(_xlpm.e,Class!E:E,Class!K:K,""), IF(ISNUMBER(MATCH(_xlpm.c,{"Composition","Reference Association","Specialization"},0)), _xlfn.XLOOKUP(_xlpm.h,Class!E:E,Class!K:K,""), _xlfn.XLOOKUP(_xlpm.f,Property!F:F,Property!K:K,"") ) ) ) -> bus
A49: 48 | B49: 2 | C49: Attribute | E49: Document Information | F49: Action to Take with Previous Data | G49: Token | I49: 0..1 | J49: Provides guidance on action to take with previous set of data: supersedes - old data should be considered as obsolete/overwritten; supplements - belongs with that data as if it was included with it. | K49: bus | L49: =_xlfn.LET( _xlpm.c,C49,_xlpm.e,E49,_xlpm.f,F49,_xlpm.h,H49, IF( ISNUMBER(MATCH(_xlpm.c,{"Abstract Class","Class"},0)), _xlfn.XLOOKUP(_xlpm.e,Class!E:E,Class!K:K,""), IF(ISNUMBER(MATCH(_xlpm.c,{"Composition","Reference Association","Specialization"},0)), _xlfn.XLOOKUP(_xlpm.h,Class!E:E,Class!K:K,""), _xlfn.XLOOKUP(_xlpm.f,Property!F:F,Property!K:K,"") ) ) ) -> bus
A50: 49 | B50: 2 | C50: Attribute | E50: Document Information | F50: Language | G50: QName | I50: 0..1 | J50: Primary language of the intellectual content. Where practical, the content of this field should coincide with ISO 639-1988 language codes. | K50: bus | L50: =_xlfn.LET( _xlpm.c,C50,_xlpm.e,E50,_xlpm.f,F50,_xlpm.h,H50, IF( ISNUMBER(MATCH(_xlpm.c,{"Abstract Class","Class"},0)), _xlfn.XLOOKUP(_xlpm.e,Class!E:E,Class!K:K,""), IF(ISNUMBER(MATCH(_xlpm.c,{"Composition","Reference Association","Specialization"},0)), _xlfn.XLOOKUP(_xlpm.h,Class!E:E,Class!K:K,""), _xlfn.XLOOKUP(_xlpm.f,Property!F:F,Property!K:K,"") ) ) ) -> bus
A51: 50 | B51: 2 | C51: Attribute | E51: Document Information | F51: Creator | G51: String | I51: 0..1 | J51: Identifies the creator of the XBRL instance. | K51: bus | L51: =_xlfn.LET( _xlpm.c,C51,_xlpm.e,E51,_xlpm.f,F51,_xlpm.h,H51, IF( ISNUMBER(MATCH(_xlpm.c,{"Abstract Class","Class"},0)), _xlfn.XLOOKUP(_xlpm.e,Class!E:E,Class!K:K,""), IF(ISNUMBER(MATCH(_xlpm.c,{"Composition","Reference Association","Specialization"},0)), _xlfn.XLOOKUP(_xlpm.h,Class!E:E,Class!K:K,""), _xlfn.XLOOKUP(_xlpm.f,Property!F:F,Property!K:K,"") ) ) ) -> bus
A52: 51 | B52: 2 | C52: Attribute | E52: Document Information | F52: Document Comment | G52: String | I52: 0..1 | J52: Text for entire document. | K52: bus | L52: =_xlfn.LET( _xlpm.c,C52,_xlpm.e,E52,_xlpm.f,F52,_xlpm.h,H52, IF( ISNUMBER(MATCH(_xlpm.c,{"Abstract Class","Class"},0)), _xlfn.XLOOKUP(_xlpm.e,Class!E:E,Class!K:K,""), IF(ISNUMBER(MATCH(_xlpm.c,{"Composition","Reference Association","Specialization"},0)), _xlfn.XLOOKUP(_xlpm.h,Class!E:E,Class!K:K,""), _xlfn.XLOOKUP(_xlpm.f,Property!F:F,Property!K:K,"") ) ) ) -> bus
A53: 52 | B53: 2 | C53: Attribute | E53: Document Information | F53: Period Covered Start | G53: Date Time | I53: 0..1 | J53: Start of date range for contents. Used as basis for many assumptions about data, including the date as of which open balances are open. | K53: bus | L53: =_xlfn.LET( _xlpm.c,C53,_xlpm.e,E53,_xlpm.f,F53,_xlpm.h,H53, IF( ISNUMBER(MATCH(_xlpm.c,{"Abstract Class","Class"},0)), _xlfn.XLOOKUP(_xlpm.e,Class!E:E,Class!K:K,""), IF(ISNUMBER(MATCH(_xlpm.c,{"Composition","Reference Association","Specialization"},0)), _xlfn.XLOOKUP(_xlpm.h,Class!E:E,Class!K:K,""), _xlfn.XLOOKUP(_xlpm.f,Property!F:F,Property!K:K,"") ) ) ) -> bus
A54: 53 | B54: 2 | C54: Attribute | E54: Document Information | F54: Period Covered End | G54: Date Time | I54: 0..1 | J54: End of date range for contents. Used as basis for many assumptions about data, including the date as of which open balances are open. | K54: bus | L54: =_xlfn.LET( _xlpm.c,C54,_xlpm.e,E54,_xlpm.f,F54,_xlpm.h,H54, IF( ISNUMBER(MATCH(_xlpm.c,{"Abstract Class","Class"},0)), _xlfn.XLOOKUP(_xlpm.e,Class!E:E,Class!K:K,""), IF(ISNUMBER(MATCH(_xlpm.c,{"Composition","Reference Association","Specialization"},0)), _xlfn.XLOOKUP(_xlpm.h,Class!E:E,Class!K:K,""), _xlfn.XLOOKUP(_xlpm.f,Property!F:F,Property!K:K,"") ) ) ) -> bus
A55: 54 | B55: 2 | C55: Attribute | E55: Document Information | F55: Period Count | G55: Decimal | I55: 0..1 | J55: Number of periods or buckets, used by postingCode. Used to interpret posting date. It may be preferable to limit entries by period covered to be by individual reporting period. | K55: bus | L55: =_xlfn.LET( _xlpm.c,C55,_xlpm.e,E55,_xlpm.f,F55,_xlpm.h,H55, IF( ISNUMBER(MATCH(_xlpm.c,{"Abstract Class","Class"},0)), _xlfn.XLOOKUP(_xlpm.e,Class!E:E,Class!K:K,""), IF(ISNUMBER(MATCH(_xlpm.c,{"Composition","Reference Association","Specialization"},0)), _xlfn.XLOOKUP(_xlpm.h,Class!E:E,Class!K:K,""), _xlfn.XLOOKUP(_xlpm.f,Property!F:F,Property!K:K,"") ) ) ) -> bus
A56: 55 | B56: 2 | C56: Attribute | E56: Document Information | F56: Period Unit | G56: Token | I56: 0..1 | J56: Type of periods covered by periodCount. Enumerated as: daily, weekly, bi-weekly, semi-monthly, monthly, quarterly, thirdly, semiannual, annual, ad-hoc, current-period-only, other. | K56: bus | L56: =_xlfn.LET( _xlpm.c,C56,_xlpm.e,E56,_xlpm.f,F56,_xlpm.h,H56, IF( ISNUMBER(MATCH(_xlpm.c,{"Abstract Class","Class"},0)), _xlfn.XLOOKUP(_xlpm.e,Class!E:E,Class!K:K,""), IF(ISNUMBER(MATCH(_xlpm.c,{"Composition","Reference Association","Specialization"},0)), _xlfn.XLOOKUP(_xlpm.h,Class!E:E,Class!K:K,""), _xlfn.XLOOKUP(_xlpm.f,Property!F:F,Property!K:K,"") ) ) ) -> bus
A57: 56 | B57: 2 | C57: Attribute | E57: Document Information | F57: Period Unit Description | G57: String | I57: 0..1 | J57: Free format description of the period unit | K57: bus | L57: =_xlfn.LET( _xlpm.c,C57,_xlpm.e,E57,_xlpm.f,F57,_xlpm.h,H57, IF( ISNUMBER(MATCH(_xlpm.c,{"Abstract Class","Class"},0)), _xlfn.XLOOKUP(_xlpm.e,Class!E:E,Class!K:K,""), IF(ISNUMBER(MATCH(_xlpm.c,{"Composition","Reference Association","Specialization"},0)), _xlfn.XLOOKUP(_xlpm.h,Class!E:E,Class!K:K,""), _xlfn.XLOOKUP(_xlpm.f,Property!F:F,Property!K:K,"") ) ) ) -> bus
A58: 57 | B58: 2 | C58: Attribute | E58: Document Information | F58: Source Application | G58: String | I58: 0..1 | J58: Product or service that produced this file. Used by many systems (e.g., VAT). Version number can be included or extended. | K58: bus | L58: =_xlfn.LET( _xlpm.c,C58,_xlpm.e,E58,_xlpm.f,F58,_xlpm.h,H58, IF( ISNUMBER(MATCH(_xlpm.c,{"Abstract Class","Class"},0)), _xlfn.XLOOKUP(_xlpm.e,Class!E:E,Class!K:K,""), IF(ISNUMBER(MATCH(_xlpm.c,{"Composition","Reference Association","Specialization"},0)), _xlfn.XLOOKUP(_xlpm.h,Class!E:E,Class!K:K,""), _xlfn.XLOOKUP(_xlpm.f,Property!F:F,Property!K:K,"") ) ) ) -> bus
... A60: 59 | B60: 2 | C60: Attribute | E60: Document Information | F60: Default Currency | G60: QName | I60: 0..1 | J60: The default currency related to the amount can be entered here instead of the XBRL instance specified way, especially important in multi-currency situations. Recommend ISO 4217 coding | K60: bus | L60: =_xlfn.LET( _xlpm.c,C60,_xlpm.e,E60,_xlpm.f,F60,_xlpm.h,H60, IF( ISNUMBER(MATCH(_xlpm.c,{"Abstract Class","Class"},0)), _xlfn.XLOOKUP(_xlpm.e,Class!E:E,Class!K:K,""), IF(ISNUMBER(MATCH(_xlpm.c,{"Composition","Reference Association","Specialization"},0)), _xlfn.XLOOKUP(_xlpm.h,Class!E:E,Class!K:K,""), _xlfn.XLOOKUP(_xlpm.f,Property!F:F,Property!K:K,"") ) ) ) -> bus
A61: 60 | B61: 2 | C61: Composition | E61: Document Information | H61: Summary Reporting Taxonomies | I61: 0..* | J61: Identifies and provides information about one or more target reporting taxonomies to which the data represented in the document rolls up to. | K61: lnk | L61: =_xlfn.LET( _xlpm.c,C61,_xlpm.e,E61,_xlpm.f,F61,_xlpm.h,H61, IF( ISNUMBER(MATCH(_xlpm.c,{"Abstract Class","Class"},0)), _xlfn.XLOOKUP(_xlpm.e,Class!E:E,Class!K:K,""), IF(ISNUMBER(MATCH(_xlpm.c,{"Composition","Reference Association","Specialization"},0)), _xlfn.XLOOKUP(_xlpm.h,Class!E:E,Class!K:K,""), _xlfn.XLOOKUP(_xlpm.f,Property!F:F,Property!K:K,"") ) ) ) -> lnk
A62: 61 | B62: 1 | C62: Class | E62: Contact | I62: 0..* | J62: Information about contacts. | K62: bus | L62: =_xlfn.LET( _xlpm.c,C62,_xlpm.e,E62,_xlpm.f,F62,_xlpm.h,H62, IF( ISNUMBER(MATCH(_xlpm.c,{"Abstract Class","Class"},0)), _xlfn.XLOOKUP(_xlpm.e,Class!E:E,Class!K:K,""), IF(ISNUMBER(MATCH(_xlpm.c,{"Composition","Reference Association","Specialization"},0)), _xlfn.XLOOKUP(_xlpm.h,Class!E:E,Class!K:K,""), _xlfn.XLOOKUP(_xlpm.f,Property!F:F,Property!K:K,"") ) ) ) -> bus
A63: 62 | B63: 2 | C63: Attribute | E63: Contact | F63: Contact Prefix | G63: String | I63: 0..1 | J63: Prefix (e.g. Dr., Mr., Mrs.) | K63: bus | L63: =_xlfn.LET( _xlpm.c,C63,_xlpm.e,E63,_xlpm.f,F63,_xlpm.h,H63, IF( ISNUMBER(MATCH(_xlpm.c,{"Abstract Class","Class"},0)), _xlfn.XLOOKUP(_xlpm.e,Class!E:E,Class!K:K,""), IF(ISNUMBER(MATCH(_xlpm.c,{"Composition","Reference Association","Specialization"},0)), _xlfn.XLOOKUP(_xlpm.h,Class!E:E,Class!K:K,""), _xlfn.XLOOKUP(_xlpm.f,Property!F:F,Property!K:K,"") ) ) ) -> bus
A64: 63 | B64: 2 | C64: Attribute | E64: Contact | F64: Contact Last Name | G64: String | I64: 0..1 | J64: Last or family name | K64: bus | L64: =_xlfn.LET( _xlpm.c,C64,_xlpm.e,E64,_xlpm.f,F64,_xlpm.h,H64, IF( ISNUMBER(MATCH(_xlpm.c,{"Abstract Class","Class"},0)), _xlfn.XLOOKUP(_xlpm.e,Class!E:E,Class!K:K,""), IF(ISNUMBER(MATCH(_xlpm.c,{"Composition","Reference Association","Specialization"},0)), _xlfn.XLOOKUP(_xlpm.h,Class!E:E,Class!K:K,""), _xlfn.XLOOKUP(_xlpm.f,Property!F:F,Property!K:K,"") ) ) ) -> bus
A65: 64 | B65: 2 | C65: Attribute | E65: Contact | F65: Contact First Name | G65: String | I65: 0..1 | J65: First or given name | K65: bus | L65: =_xlfn.LET( _xlpm.c,C65,_xlpm.e,E65,_xlpm.f,F65,_xlpm.h,H65, IF( ISNUMBER(MATCH(_xlpm.c,{"Abstract Class","Class"},0)), _xlfn.XLOOKUP(_xlpm.e,Class!E:E,Class!K:K,""), IF(ISNUMBER(MATCH(_xlpm.c,{"Composition","Reference Association","Specialization"},0)), _xlfn.XLOOKUP(_xlpm.h,Class!E:E,Class!K:K,""), _xlfn.XLOOKUP(_xlpm.f,Property!F:F,Property!K:K,"") ) ) ) -> bus
A66: 65 | B66: 2 | C66: Attribute | E66: Contact | F66: Contact Suffix | G66: String | I66: 0..1 | J66: Suffix (e.g. MD, CPA, Jr.) | K66: bus | L66: =_xlfn.LET( _xlpm.c,C66,_xlpm.e,E66,_xlpm.f,F66,_xlpm.h,H66, IF( ISNUMBER(MATCH(_xlpm.c,{"Abstract Class","Class"},0)), _xlfn.XLOOKUP(_xlpm.e,Class!E:E,Class!K:K,""), IF(ISNUMBER(MATCH(_xlpm.c,{"Composition","Reference Association","Specialization"},0)), _xlfn.XLOOKUP(_xlpm.h,Class!E:E,Class!K:K,""), _xlfn.XLOOKUP(_xlpm.f,Property!F:F,Property!K:K,"") ) ) ) -> bus
A67: 66 | B67: 2 | C67: Attribute | E67: Contact | F67: Contact Attention Line | G67: String | I67: 0..1 | J67: Attention Line | K67: bus | L67: =_xlfn.LET( _xlpm.c,C67,_xlpm.e,E67,_xlpm.f,F67,_xlpm.h,H67, IF( ISNUMBER(MATCH(_xlpm.c,{"Abstract Class","Class"},0)), _xlfn.XLOOKUP(_xlpm.e,Class!E:E,Class!K:K,""), IF(ISNUMBER(MATCH(_xlpm.c,{"Composition","Reference Association","Specialization"},0)), _xlfn.XLOOKUP(_xlpm.h,Class!E:E,Class!K:K,""), _xlfn.XLOOKUP(_xlpm.f,Property!F:F,Property!K:K,"") ) ) ) -> bus
A68: 67 | B68: 2 | C68: Attribute | E68: Contact | F68: Contact Position Role | G68: String | I68: 0..1 | J68: Position or role | K68: bus | L68: =_xlfn.LET( _xlpm.c,C68,_xlpm.e,E68,_xlpm.f,F68,_xlpm.h,H68, IF( ISNUMBER(MATCH(_xlpm.c,{"Abstract Class","Class"},0)), _xlfn.XLOOKUP(_xlpm.e,Class!E:E,Class!K:K,""), IF(ISNUMBER(MATCH(_xlpm.c,{"Composition","Reference Association","Specialization"},0)), _xlfn.XLOOKUP(_xlpm.h,Class!E:E,Class!K:K,""), _xlfn.XLOOKUP(_xlpm.f,Property!F:F,Property!K:K,"") ) ) ) -> bus
A69: 68 | B69: 2 | C69: Attribute | E69: Contact | F69: Contact Contact Type | G69: String | I69: 0..1 | J69: Role of contact. Examples include: Source Service, Sender, Recipient, Invoicer, Auditor, Accountant | K69: bus | L69: =_xlfn.LET( _xlpm.c,C69,_xlpm.e,E69,_xlpm.f,F69,_xlpm.h,H69, IF( ISNUMBER(MATCH(_xlpm.c,{"Abstract Class","Class"},0)), _xlfn.XLOOKUP(_xlpm.e,Class!E:E,Class!K:K,""), IF(ISNUMBER(MATCH(_xlpm.c,{"Composition","Reference Association","Specialization"},0)), _xlfn.XLOOKUP(_xlpm.h,Class!E:E,Class!K:K,""), _xlfn.XLOOKUP(_xlpm.f,Property!F:F,Property!K:K,"") ) ) ) -> bus
A70: 69 | B70: 2 | C70: Attribute | E70: Contact | F70: Contact Location ID cross reference | G70: String | I70: 0..1 | J70: This code is used to associate the contact with a specific location for the Entity. Its value should be the same as that of the organizationAddressLocationIdentifier | K70: bus | L70: =_xlfn.LET( _xlpm.c,C70,_xlpm.e,E70,_xlpm.f,F70,_xlpm.h,H70, IF( ISNUMBER(MATCH(_xlpm.c,{"Abstract Class","Class"},0)), _xlfn.XLOOKUP(_xlpm.e,Class!E:E,Class!K:K,""), IF(ISNUMBER(MATCH(_xlpm.c,{"Composition","Reference Association","Specialization"},0)), _xlfn.XLOOKUP(_xlpm.h,Class!E:E,Class!K:K,""), _xlfn.XLOOKUP(_xlpm.f,Property!F:F,Property!K:K,"") ) ) ) -> bus
A71: 70 | B71: 2 | C71: Attribute | E71: Contact | F71: Contact Active | G71: Boolean | I71: 0..1 | J71: Boolean to indicate whether the contact is active (="true") or inactive (="false") | K71: bus | L71: =_xlfn.LET( _xlpm.c,C71,_xlpm.e,E71,_xlpm.f,F71,_xlpm.h,H71, IF( ISNUMBER(MATCH(_xlpm.c,{"Abstract Class","Class"},0)), _xlfn.XLOOKUP(_xlpm.e,Class!E:E,Class!K:K,""), IF(ISNUMBER(MATCH(_xlpm.c,{"Composition","Reference Association","Specialization"},0)), _xlfn.XLOOKUP(_xlpm.h,Class!E:E,Class!K:K,""), _xlfn.XLOOKUP(_xlpm.f,Property!F:F,Property!K:K,"") ) ) ) -> bus
A72: 71 | B72: 2 | C72: Composition | E72: Contact | F72: Contact | H72: Phone | I72: 0..* | J72: Contact Phone Number | K72: bus | L72: =_xlfn.LET( _xlpm.c,C72,_xlpm.e,E72,_xlpm.f,F72,_xlpm.h,H72, IF( ISNUMBER(MATCH(_xlpm.c,{"Abstract Class","Class"},0)), _xlfn.XLOOKUP(_xlpm.e,Class!E:E,Class!K:K,""), IF(ISNUMBER(MATCH(_xlpm.c,{"Composition","Reference Association","Specialization"},0)), _xlfn.XLOOKUP(_xlpm.h,Class!E:E,Class!K:K,""), _xlfn.XLOOKUP(_xlpm.f,Property!F:F,Property!K:K,"") ) ) ) -> bus
A73: 72 | B73: 2 | C73: Composition | E73: Contact | F73: Contact | H73: Fax | I73: 0..* | J73: Contact Fax Number Class | K73: bus | L73: =_xlfn.LET( _xlpm.c,C73,_xlpm.e,E73,_xlpm.f,F73,_xlpm.h,H73, IF( ISNUMBER(MATCH(_xlpm.c,{"Abstract Class","Class"},0)), _xlfn.XLOOKUP(_xlpm.e,Class!E:E,Class!K:K,""), IF(ISNUMBER(MATCH(_xlpm.c,{"Composition","Reference Association","Specialization"},0)), _xlfn.XLOOKUP(_xlpm.h,Class!E:E,Class!K:K,""), _xlfn.XLOOKUP(_xlpm.f,Property!F:F,Property!K:K,"") ) ) ) -> bus
A74: 73 | B74: 2 | C74: Composition | E74: Contact | F74: Contact | H74: Email | I74: 0..* | J74: Contact E-mail address class | K74: bus | L74: =_xlfn.LET( _xlpm.c,C74,_xlpm.e,E74,_xlpm.f,F74,_xlpm.h,H74, IF( ISNUMBER(MATCH(_xlpm.c,{"Abstract Class","Class"},0)), _xlfn.XLOOKUP(_xlpm.e,Class!E:E,Class!K:K,""), IF(ISNUMBER(MATCH(_xlpm.c,{"Composition","Reference Association","Specialization"},0)), _xlfn.XLOOKUP(_xlpm.h,Class!E:E,Class!K:K,""), _xlfn.XLOOKUP(_xlpm.f,Property!F:F,Property!K:K,"") ) ) ) -> bus
A75: 74 | B75: 1 | C75: Class | E75: Accounting Method Structure | I75: 0..* | J75: Class for identifying the methods of accounting used by the entity for different reporting purposes | K75: bus | L75: =_xlfn.LET( _xlpm.c,C75,_xlpm.e,E75,_xlpm.f,F75,_xlpm.h,H75, IF( ISNUMBER(MATCH(_xlpm.c,{"Abstract Class","Class"},0)), _xlfn.XLOOKUP(_xlpm.e,Class!E:E,Class!K:K,""), IF(ISNUMBER(MATCH(_xlpm.c,{"Composition","Reference Association","Specialization"},0)), _xlfn.XLOOKUP(_xlpm.h,Class!E:E,Class!K:K,""), _xlfn.XLOOKUP(_xlpm.f,Property!F:F,Property!K:K,"") ) ) ) -> bus
A76: 75 | B76: 2 | C76: Attribute | E76: Accounting Method Structure | F76: Accounting Method | G76: Token | I76: 0..1 | J76: For this entity, the method of accounting represented - from: accrual, cash, modified cash, modified accrual, encumbrance, special methods, hybrid methods, other | K76: bus | L76: =_xlfn.LET( _xlpm.c,C76,_xlpm.e,E76,_xlpm.f,F76,_xlpm.h,H76, IF( ISNUMBER(MATCH(_xlpm.c,{"Abstract Class","Class"},0)), _xlfn.XLOOKUP(_xlpm.e,Class!E:E,Class!K:K,""), IF(ISNUMBER(MATCH(_xlpm.c,{"Composition","Reference Association","Specialization"},0)), _xlfn.XLOOKUP(_xlpm.h,Class!E:E,Class!K:K,""), _xlfn.XLOOKUP(_xlpm.f,Property!F:F,Property!K:K,"") ) ) ) -> bus
A77: 76 | B77: 2 | C77: Attribute | E77: Accounting Method Structure | F77: Accounting Method Description | G77: String | I77: 0..1 | J77: Free format description of the accounting method | K77: bus | L77: =_xlfn.LET( _xlpm.c,C77,_xlpm.e,E77,_xlpm.f,F77,_xlpm.h,H77, IF( ISNUMBER(MATCH(_xlpm.c,{"Abstract Class","Class"},0)), _xlfn.XLOOKUP(_xlpm.e,Class!E:E,Class!K:K,""), IF(ISNUMBER(MATCH(_xlpm.c,{"Composition","Reference Association","Specialization"},0)), _xlfn.XLOOKUP(_xlpm.h,Class!E:E,Class!K:K,""), _xlfn.XLOOKUP(_xlpm.f,Property!F:F,Property!K:K,"") ) ) ) -> bus
A78: 77 | B78: 2 | C78: Attribute | E78: Accounting Method Structure | F78: Accounting Method Purpose | G78: Token | I78: 0..1 | J78: For this entity, the reporting purpose represented - from book, tax, management, statutory, other | K78: bus | L78: =_xlfn.LET( _xlpm.c,C78,_xlpm.e,E78,_xlpm.f,F78,_xlpm.h,H78, IF( ISNUMBER(MATCH(_xlpm.c,{"Abstract Class","Class"},0)), _xlfn.XLOOKUP(_xlpm.e,Class!E:E,Class!K:K,""), IF(ISNUMBER(MATCH(_xlpm.c,{"Composition","Reference Association","Specialization"},0)), _xlfn.XLOOKUP(_xlpm.h,Class!E:E,Class!K:K,""), _xlfn.XLOOKUP(_xlpm.f,Property!F:F,Property!K:K,"") ) ) ) -> bus
A79: 78 | B79: 2 | C79: Attribute | E79: Accounting Method Structure | F79: Accounting Method Purpose Description | G79: String | I79: 0..1 | J79: Free format description of the accounting method purpose | K79: bus | L79: =_xlfn.LET( _xlpm.c,C79,_xlpm.e,E79,_xlpm.f,F79,_xlpm.h,H79, IF( ISNUMBER(MATCH(_xlpm.c,{"Abstract Class","Class"},0)), _xlfn.XLOOKUP(_xlpm.e,Class!E:E,Class!K:K,""), IF(ISNUMBER(MATCH(_xlpm.c,{"Composition","Reference Association","Specialization"},0)), _xlfn.XLOOKUP(_xlpm.h,Class!E:E,Class!K:K,""), _xlfn.XLOOKUP(_xlpm.f,Property!F:F,Property!K:K,"") ) ) ) -> bus
A80: 79 | B80: 2 | C80: Attribute | E80: Accounting Method Structure | F80: Accounting Method Start Date | G80: Date Time | I80: 0..1 | J80: Accounting Method Start Date | K80: bus | L80: =_xlfn.LET( _xlpm.c,C80,_xlpm.e,E80,_xlpm.f,F80,_xlpm.h,H80, IF( ISNUMBER(MATCH(_xlpm.c,{"Abstract Class","Class"},0)), _xlfn.XLOOKUP(_xlpm.e,Class!E:E,Class!K:K,""), IF(ISNUMBER(MATCH(_xlpm.c,{"Composition","Reference Association","Specialization"},0)), _xlfn.XLOOKUP(_xlpm.h,Class!E:E,Class!K:K,""), _xlfn.XLOOKUP(_xlpm.f,Property!F:F,Property!K:K,"") ) ) ) -> bus
A81: 80 | B81: 2 | C81: Attribute | E81: Accounting Method Structure | F81: Accounting Method End Date | G81: Date Time | I81: 0..1 | J81: Accounting Method End Date | K81: bus | L81: =_xlfn.LET( _xlpm.c,C81,_xlpm.e,E81,_xlpm.f,F81,_xlpm.h,H81, IF( ISNUMBER(MATCH(_xlpm.c,{"Abstract Class","Class"},0)), _xlfn.XLOOKUP(_xlpm.e,Class!E:E,Class!K:K,""), IF(ISNUMBER(MATCH(_xlpm.c,{"Composition","Reference Association","Specialization"},0)), _xlfn.XLOOKUP(_xlpm.h,Class!E:E,Class!K:K,""), _xlfn.XLOOKUP(_xlpm.f,Property!F:F,Property!K:K,"") ) ) ) -> bus
A82: 81 | B82: 1 | C82: Class | E82: Accountant | I82: 0..* | J82: Information about the relevant external accountant | K82: bus | L82: =_xlfn.LET( _xlpm.c,C82,_xlpm.e,E82,_xlpm.f,F82,_xlpm.h,H82, IF( ISNUMBER(MATCH(_xlpm.c,{"Abstract Class","Class"},0)), _xlfn.XLOOKUP(_xlpm.e,Class!E:E,Class!K:K,""), IF(ISNUMBER(MATCH(_xlpm.c,{"Composition","Reference Association","Specialization"},0)), _xlfn.XLOOKUP(_xlpm.h,Class!E:E,Class!K:K,""), _xlfn.XLOOKUP(_xlpm.f,Property!F:F,Property!K:K,"") ) ) ) -> bus
A83: 82 | B83: 2 | C83: Attribute | E83: Accountant | F83: Accountant Name | G83: String | I83: 0..1 | J83: Name of the accountant | K83: bus | L83: =_xlfn.LET( _xlpm.c,C83,_xlpm.e,E83,_xlpm.f,F83,_xlpm.h,H83, IF( ISNUMBER(MATCH(_xlpm.c,{"Abstract Class","Class"},0)), _xlfn.XLOOKUP(_xlpm.e,Class!E:E,Class!K:K,""), IF(ISNUMBER(MATCH(_xlpm.c,{"Composition","Reference Association","Specialization"},0)), _xlfn.XLOOKUP(_xlpm.h,Class!E:E,Class!K:K,""), _xlfn.XLOOKUP(_xlpm.f,Property!F:F,Property!K:K,"") ) ) ) -> bus
A84: 83 | B84: 2 | C84: Attribute | E84: Accountant | F84: Accountant Type of Engagement | G84: Token | I84: 0..1 | J84: Type of engagement being performed by external accountant. Enumerated as: audit, review, compilation, tax, other. | K84: bus | L84: =_xlfn.LET( _xlpm.c,C84,_xlpm.e,E84,_xlpm.f,F84,_xlpm.h,H84, IF( ISNUMBER(MATCH(_xlpm.c,{"Abstract Class","Class"},0)), _xlfn.XLOOKUP(_xlpm.e,Class!E:E,Class!K:K,""), IF(ISNUMBER(MATCH(_xlpm.c,{"Composition","Reference Association","Specialization"},0)), _xlfn.XLOOKUP(_xlpm.h,Class!E:E,Class!K:K,""), _xlfn.XLOOKUP(_xlpm.f,Property!F:F,Property!K:K,"") ) ) ) -> bus
A85: 84 | B85: 2 | C85: Attribute | E85: Accountant | F85: Accountant Type of Engagement Description | G85: String | I85: 0..1 | J85: Free format description of the type of engagement | K85: bus | L85: =_xlfn.LET( _xlpm.c,C85,_xlpm.e,E85,_xlpm.f,F85,_xlpm.h,H85, IF( ISNUMBER(MATCH(_xlpm.c,{"Abstract Class","Class"},0)), _xlfn.XLOOKUP(_xlpm.e,Class!E:E,Class!K:K,""), IF(ISNUMBER(MATCH(_xlpm.c,{"Composition","Reference Association","Specialization"},0)), _xlfn.XLOOKUP(_xlpm.h,Class!E:E,Class!K:K,""), _xlfn.XLOOKUP(_xlpm.f,Property!F:F,Property!K:K,"") ) ) ) -> bus
A86: 85 | B86: 2 | C86: Composition | E86: Accountant | F86: Accountant | H86: Address | I86: 0..* | J86: Class which contains accountant address information. | K86: bus | L86: =_xlfn.LET( _xlpm.c,C86,_xlpm.e,E86,_xlpm.f,F86,_xlpm.h,H86, IF( ISNUMBER(MATCH(_xlpm.c,{"Abstract Class","Class"},0)), _xlfn.XLOOKUP(_xlpm.e,Class!E:E,Class!K:K,""), IF(ISNUMBER(MATCH(_xlpm.c,{"Composition","Reference Association","Specialization"},0)), _xlfn.XLOOKUP(_xlpm.h,Class!E:E,Class!K:K,""), _xlfn.XLOOKUP(_xlpm.f,Property!F:F,Property!K:K,"") ) ) ) -> bus
A87: 86 | B87: 2 | C87: Composition | E87: Accountant | F87: Accountant | H87: Contact | I87: 0..* | J87: Accountant Contact Information Class | K87: bus | L87: =_xlfn.LET( _xlpm.c,C87,_xlpm.e,E87,_xlpm.f,F87,_xlpm.h,H87, IF( ISNUMBER(MATCH(_xlpm.c,{"Abstract Class","Class"},0)), _xlfn.XLOOKUP(_xlpm.e,Class!E:E,Class!K:K,""), IF(ISNUMBER(MATCH(_xlpm.c,{"Composition","Reference Association","Specialization"},0)), _xlfn.XLOOKUP(_xlpm.h,Class!E:E,Class!K:K,""), _xlfn.XLOOKUP(_xlpm.f,Property!F:F,Property!K:K,"") ) ) ) -> bus
A88: 87 | B88: 1 | C88: Class | E88: Period | I88: 0..* | J88: A tool to collect a specific set of periods used to summarize results from transactions. | K88: bus | L88: =_xlfn.LET( _xlpm.c,C88,_xlpm.e,E88,_xlpm.f,F88,_xlpm.h,H88, IF( ISNUMBER(MATCH(_xlpm.c,{"Abstract Class","Class"},0)), _xlfn.XLOOKUP(_xlpm.e,Class!E:E,Class!K:K,""), IF(ISNUMBER(MATCH(_xlpm.c,{"Composition","Reference Association","Specialization"},0)), _xlfn.XLOOKUP(_xlpm.h,Class!E:E,Class!K:K,""), _xlfn.XLOOKUP(_xlpm.f,Property!F:F,Property!K:K,"") ) ) ) -> bus
A89: 88 | B89: 2 | C89: Attribute | D89: PK | E89: Period | F89: Period ID | G89: String | I89: 0..1 | J89: An identifier for this period in this calendar | K89: bus | L89: =_xlfn.LET( _xlpm.c,C89,_xlpm.e,E89,_xlpm.f,F89,_xlpm.h,H89, IF( ISNUMBER(MATCH(_xlpm.c,{"Abstract Class","Class"},0)), _xlfn.XLOOKUP(_xlpm.e,Class!E:E,Class!K:K,""), IF(ISNUMBER(MATCH(_xlpm.c,{"Composition","Reference Association","Specialization"},0)), _xlfn.XLOOKUP(_xlpm.h,Class!E:E,Class!K:K,""), _xlfn.XLOOKUP(_xlpm.f,Property!F:F,Property!K:K,"") ) ) ) -> bus
A90: 89 | B90: 2 | C90: Attribute | E90: Period | F90: Period Description | G90: String | I90: 0..1 | J90: A description of this specific reporting period in this calendar. | K90: bus | L90: =_xlfn.LET( _xlpm.c,C90,_xlpm.e,E90,_xlpm.f,F90,_xlpm.h,H90, IF( ISNUMBER(MATCH(_xlpm.c,{"Abstract Class","Class"},0)), _xlfn.XLOOKUP(_xlpm.e,Class!E:E,Class!K:K,""), IF(ISNUMBER(MATCH(_xlpm.c,{"Composition","Reference Association","Specialization"},0)), _xlfn.XLOOKUP(_xlpm.h,Class!E:E,Class!K:K,""), _xlfn.XLOOKUP(_xlpm.f,Property!F:F,Property!K:K,"") ) ) ) -> bus
A91: 90 | B91: 2 | C91: Attribute | E91: Period | F91: Period Start Date | G91: Date Time | I91: 0..1 | J91: The beginning date/time of a period | K91: bus | L91: =_xlfn.LET( _xlpm.c,C91,_xlpm.e,E91,_xlpm.f,F91,_xlpm.h,H91, IF( ISNUMBER(MATCH(_xlpm.c,{"Abstract Class","Class"},0)), _xlfn.XLOOKUP(_xlpm.e,Class!E:E,Class!K:K,""), IF(ISNUMBER(MATCH(_xlpm.c,{"Composition","Reference Association","Specialization"},0)), _xlfn.XLOOKUP(_xlpm.h,Class!E:E,Class!K:K,""), _xlfn.XLOOKUP(_xlpm.f,Property!F:F,Property!K:K,"") ) ) ) -> bus
A92: 91 | B92: 2 | C92: Attribute | E92: Period | F92: Period End Date | G92: Date Time | I92: 0..1 | J92: The ending date/time of a period | K92: bus | L92: =_xlfn.LET( _xlpm.c,C92,_xlpm.e,E92,_xlpm.f,F92,_xlpm.h,H92, IF( ISNUMBER(MATCH(_xlpm.c,{"Abstract Class","Class"},0)), _xlfn.XLOOKUP(_xlpm.e,Class!E:E,Class!K:K,""), IF(ISNUMBER(MATCH(_xlpm.c,{"Composition","Reference Association","Specialization"},0)), _xlfn.XLOOKUP(_xlpm.h,Class!E:E,Class!K:K,""), _xlfn.XLOOKUP(_xlpm.f,Property!F:F,Property!K:K,"") ) ) ) -> bus
A93: 92 | B93: 1 | C93: Class | E93: Reporting Calendar_ Period | I93: 0..* | J93: A tool to collect a specific set of periods used to summarize results from transactions. | K93: bus | L93: =_xlfn.LET( _xlpm.c,C93,_xlpm.e,E93,_xlpm.f,F93,_xlpm.h,H93, IF( ISNUMBER(MATCH(_xlpm.c,{"Abstract Class","Class"},0)), _xlfn.XLOOKUP(_xlpm.e,Class!E:E,Class!K:K,""), IF(ISNUMBER(MATCH(_xlpm.c,{"Composition","Reference Association","Specialization"},0)), _xlfn.XLOOKUP(_xlpm.h,Class!E:E,Class!K:K,""), _xlfn.XLOOKUP(_xlpm.f,Property!F:F,Property!K:K,"") ) ) ) -> bus
A94: 93 | B94: 2 | C94: Specialization | E94: Reporting Calendar_ Period | H94: Period | I94: 1 | K94: bus | L94: =_xlfn.LET( _xlpm.c,C94,_xlpm.e,E94,_xlpm.f,F94,_xlpm.h,H94, IF( ISNUMBER(MATCH(_xlpm.c,{"Abstract Class","Class"},0)), _xlfn.XLOOKUP(_xlpm.e,Class!E:E,Class!K:K,""), IF(ISNUMBER(MATCH(_xlpm.c,{"Composition","Reference Association","Specialization"},0)), _xlfn.XLOOKUP(_xlpm.h,Class!E:E,Class!K:K,""), _xlfn.XLOOKUP(_xlpm.f,Property!F:F,Property!K:K,"") ) ) ) -> bus
A95: 94 | B95: 2 | C95: Attribute | D95: PK | E95: Reporting Calendar_ Period | F95: Reporting Calendar_ Period ID | G95: String | I95: 0..1 | J95: An identifier for this period in this calendar | K95: bus | L95: =_xlfn.LET( _xlpm.c,C95,_xlpm.e,E95,_xlpm.f,F95,_xlpm.h,H95, IF( ISNUMBER(MATCH(_xlpm.c,{"Abstract Class","Class"},0)), _xlfn.XLOOKUP(_xlpm.e,Class!E:E,Class!K:K,""), IF(ISNUMBER(MATCH(_xlpm.c,{"Composition","Reference Association","Specialization"},0)), _xlfn.XLOOKUP(_xlpm.h,Class!E:E,Class!K:K,""), _xlfn.XLOOKUP(_xlpm.f,Property!F:F,Property!K:K,"") ) ) ) -> bus
A96: 95 | B96: 2 | C96: Attribute | E96: Reporting Calendar_ Period | F96: Reporting Calendar_ Period Description | G96: String | I96: 0..1 | J96: A description of this specific reporting period in this calendar. | K96: bus | L96: =_xlfn.LET( _xlpm.c,C96,_xlpm.e,E96,_xlpm.f,F96,_xlpm.h,H96, IF( ISNUMBER(MATCH(_xlpm.c,{"Abstract Class","Class"},0)), _xlfn.XLOOKUP(_xlpm.e,Class!E:E,Class!K:K,""), IF(ISNUMBER(MATCH(_xlpm.c,{"Composition","Reference Association","Specialization"},0)), _xlfn.XLOOKUP(_xlpm.h,Class!E:E,Class!K:K,""), _xlfn.XLOOKUP(_xlpm.f,Property!F:F,Property!K:K,"") ) ) ) -> bus
A97: 96 | B97: 2 | C97: Attribute | E97: Reporting Calendar_ Period | F97: Reporting Calendar_ Period Start Date | G97: Date Time | I97: 0..1 | J97: The beginning date/time of a period | K97: bus | L97: =_xlfn.LET( _xlpm.c,C97,_xlpm.e,E97,_xlpm.f,F97,_xlpm.h,H97, IF( ISNUMBER(MATCH(_xlpm.c,{"Abstract Class","Class"},0)), _xlfn.XLOOKUP(_xlpm.e,Class!E:E,Class!K:K,""), IF(ISNUMBER(MATCH(_xlpm.c,{"Composition","Reference Association","Specialization"},0)), _xlfn.XLOOKUP(_xlpm.h,Class!E:E,Class!K:K,""), _xlfn.XLOOKUP(_xlpm.f,Property!F:F,Property!K:K,"") ) ) ) -> bus
A98: 97 | B98: 2 | C98: Attribute | E98: Reporting Calendar_ Period | F98: Reporting Calendar_ Period End Date | G98: Date Time | I98: 0..1 | J98: The ending date/time of a period | K98: bus | L98: =_xlfn.LET( _xlpm.c,C98,_xlpm.e,E98,_xlpm.f,F98,_xlpm.h,H98, IF( ISNUMBER(MATCH(_xlpm.c,{"Abstract Class","Class"},0)), _xlfn.XLOOKUP(_xlpm.e,Class!E:E,Class!K:K,""), IF(ISNUMBER(MATCH(_xlpm.c,{"Composition","Reference Association","Specialization"},0)), _xlfn.XLOOKUP(_xlpm.h,Class!E:E,Class!K:K,""), _xlfn.XLOOKUP(_xlpm.f,Property!F:F,Property!K:K,"") ) ) ) -> bus
A99: 98 | B99: 2 | C99: Attribute | E99: Reporting Calendar_ Period | F99: Reporting Calendar_ Period Closed Date | G99: Date Time | I99: 0..1 | J99: The date/time a period has been closed for activity. If this is present with a nill value (xsi:nill="true") then the period is not closed. | K99: bus | L99: =_xlfn.LET( _xlpm.c,C99,_xlpm.e,E99,_xlpm.f,F99,_xlpm.h,H99, IF( ISNUMBER(MATCH(_xlpm.c,{"Abstract Class","Class"},0)), _xlfn.XLOOKUP(_xlpm.e,Class!E:E,Class!K:K,""), IF(ISNUMBER(MATCH(_xlpm.c,{"Composition","Reference Association","Specialization"},0)), _xlfn.XLOOKUP(_xlpm.h,Class!E:E,Class!K:K,""), _xlfn.XLOOKUP(_xlpm.f,Property!F:F,Property!K:K,"") ) ) ) -> bus
A100: 99 | B100: 1 | C100: Class | E100: Reporting Calendar | I100: 0..* | J100: A tool to collect the periods used to summarise results from transactions. | K100: bus | L100: =_xlfn.LET( _xlpm.c,C100,_xlpm.e,E100,_xlpm.f,F100,_xlpm.h,H100, IF( ISNUMBER(MATCH(_xlpm.c,{"Abstract Class","Class"},0)), _xlfn.XLOOKUP(_xlpm.e,Class!E:E,Class!K:K,""), IF(ISNUMBER(MATCH(_xlpm.c,{"Composition","Reference Association","Specialization"},0)), _xlfn.XLOOKUP(_xlpm.h,Class!E:E,Class!K:K,""), _xlfn.XLOOKUP(_xlpm.f,Property!F:F,Property!K:K,"") ) ) ) -> bus
A101: 100 | B101: 2 | C101: Attribute | E101: Reporting Calendar | F101: Reporting Calendar Code | G101: String | I101: 0..1 | J101: The code used to identify this specific reporting calendar, unique across periods | K101: bus | L101: =_xlfn.LET( _xlpm.c,C101,_xlpm.e,E101,_xlpm.f,F101,_xlpm.h,H101, IF( ISNUMBER(MATCH(_xlpm.c,{"Abstract Class","Class"},0)), _xlfn.XLOOKUP(_xlpm.e,Class!E:E,Class!K:K,""), IF(ISNUMBER(MATCH(_xlpm.c,{"Composition","Reference Association","Specialization"},0)), _xlfn.XLOOKUP(_xlpm.h,Class!E:E,Class!K:K,""), _xlfn.XLOOKUP(_xlpm.f,Property!F:F,Property!K:K,"") ) ) ) -> bus
...

Sheet FSM_btx
A1: seq | B1: level | C1: Property type | D1: Identifier | E1: Class | F1: Property Term | G1: BaseType | H1: Associated Class | I1: Multiplicity | J1: Definition
A2: 1 | B2: 1 | C2: Class | E2: Amount Structure | I2: 0..* | J2: Structure combining a monetary amount with its currency and currency role information. | K2: btx | L2: =_xlfn.LET( _xlpm.c,C2,_xlpm.e,E2,_xlpm.f,F2,_xlpm.h,H2, IF( ISNUMBER(MATCH(_xlpm.c,{"Abstract Class","Class"},0)), _xlfn.XLOOKUP(_xlpm.e,Class!E:E,Class!K:K,""), IF(ISNUMBER(MATCH(_xlpm.c,{"Composition","Reference Association","Specialization"},0)), _xlfn.XLOOKUP(_xlpm.h,Class!E:E,Class!K:K,""), _xlfn.XLOOKUP(_xlpm.f,Property!F:F,Property!K:K,"") ) ) ) -> btx
A3: 2 | B3: 2 | C3: Attribute | E3: Amount Structure | F3: Amount | G3: Monetary | I3: 1 | J3: Numeric value of the monetary amount expressed in the specified currency. | K3: btx | L3: =_xlfn.LET( _xlpm.c,C3,_xlpm.e,E3,_xlpm.f,F3,_xlpm.h,H3, IF( ISNUMBER(MATCH(_xlpm.c,{"Abstract Class","Class"},0)), _xlfn.XLOOKUP(_xlpm.e,Class!E:E,Class!K:K,""), IF(ISNUMBER(MATCH(_xlpm.c,{"Composition","Reference Association","Specialization"},0)), _xlfn.XLOOKUP(_xlpm.h,Class!E:E,Class!K:K,""), _xlfn.XLOOKUP(_xlpm.f,Property!F:F,Property!K:K,"") ) ) ) -> btx
A4: 3 | B4: 2 | C4: Attribute | E4: Amount Structure | F4: Amount Type | G4: Token | I4: 0..1 | J4: Code or text specifying the type or role of the amount, such as tax amount, tax base amount, allowance amount, or charge amount. | K4: btx | L4: =_xlfn.LET( _xlpm.c,C4,_xlpm.e,E4,_xlpm.f,F4,_xlpm.h,H4, IF( ISNUMBER(MATCH(_xlpm.c,{"Abstract Class","Class"},0)), _xlfn.XLOOKUP(_xlpm.e,Class!E:E,Class!K:K,""), IF(ISNUMBER(MATCH(_xlpm.c,{"Composition","Reference Association","Specialization"},0)), _xlfn.XLOOKUP(_xlpm.h,Class!E:E,Class!K:K,""), _xlfn.XLOOKUP(_xlpm.f,Property!F:F,Property!K:K,"") ) ) ) -> btx
A5: 4 | B5: 2 | C5: Attribute | E5: Amount Structure | F5: Currency Code | G5: Token | I5: 0..1 | J5: Code specifying the currency in which the amount is expressed, typically an ISO 4217 currency code. | K5: btx | L5: =_xlfn.LET( _xlpm.c,C5,_xlpm.e,E5,_xlpm.f,F5,_xlpm.h,H5, IF( ISNUMBER(MATCH(_xlpm.c,{"Abstract Class","Class"},0)), _xlfn.XLOOKUP(_xlpm.e,Class!E:E,Class!K:K,""), IF(ISNUMBER(MATCH(_xlpm.c,{"Composition","Reference Association","Specialization"},0)), _xlfn.XLOOKUP(_xlpm.h,Class!E:E,Class!K:K,""), _xlfn.XLOOKUP(_xlpm.f,Property!F:F,Property!K:K,"") ) ) ) -> btx
A6: 5 | B6: 2 | C6: Attribute | E6: Amount Structure | F6: Currency Code Type | G6: Token | I6: 0..1 | J6: Code specifying the role of the currency used for the amount, such as functional currency, local currency, reporting currency, or transaction currency. | K6: btx | L6: =_xlfn.LET( _xlpm.c,C6,_xlpm.e,E6,_xlpm.f,F6,_xlpm.h,H6, IF( ISNUMBER(MATCH(_xlpm.c,{"Abstract Class","Class"},0)), _xlfn.XLOOKUP(_xlpm.e,Class!E:E,Class!K:K,""), IF(ISNUMBER(MATCH(_xlpm.c,{"Composition","Reference Association","Specialization"},0)), _xlfn.XLOOKUP(_xlpm.h,Class!E:E,Class!K:K,""), _xlfn.XLOOKUP(_xlpm.f,Property!F:F,Property!K:K,"") ) ) ) -> btx
A7: 6 | B7: 1 | C7: Class | E7: Header_ Amount Structure | I7: 0..* | J7: Structure representing monetary amounts and currency information applicable to the document as a whole, such as document-level totals or aggregated tax amounts. | K7: btx | L7: =_xlfn.LET( _xlpm.c,C7,_xlpm.e,E7,_xlpm.f,F7,_xlpm.h,H7, IF( ISNUMBER(MATCH(_xlpm.c,{"Abstract Class","Class"},0)), _xlfn.XLOOKUP(_xlpm.e,Class!E:E,Class!K:K,""), IF(ISNUMBER(MATCH(_xlpm.c,{"Composition","Reference Association","Specialization"},0)), _xlfn.XLOOKUP(_xlpm.h,Class!E:E,Class!K:K,""), _xlfn.XLOOKUP(_xlpm.f,Property!F:F,Property!K:K,"") ) ) ) -> btx
A8: 7 | B8: 2 | C8: Specialization | E8: Header_ Amount Structure | H8: Amount Structure | I8: 1 | K8: btx | L8: =_xlfn.LET( _xlpm.c,C8,_xlpm.e,E8,_xlpm.f,F8,_xlpm.h,H8, IF( ISNUMBER(MATCH(_xlpm.c,{"Abstract Class","Class"},0)), _xlfn.XLOOKUP(_xlpm.e,Class!E:E,Class!K:K,""), IF(ISNUMBER(MATCH(_xlpm.c,{"Composition","Reference Association","Specialization"},0)), _xlfn.XLOOKUP(_xlpm.h,Class!E:E,Class!K:K,""), _xlfn.XLOOKUP(_xlpm.f,Property!F:F,Property!K:K,"") ) ) ) -> btx
A9: 8 | B9: 2 | C9: Attribute | E9: Header_ Amount Structure | F9: Header_ Amount | G9: Monetary | I9: 1 | J9: Numeric value of the monetary amount expressed in the specified currency. | K9: btx | L9: =_xlfn.LET( _xlpm.c,C9,_xlpm.e,E9,_xlpm.f,F9,_xlpm.h,H9, IF( ISNUMBER(MATCH(_xlpm.c,{"Abstract Class","Class"},0)), _xlfn.XLOOKUP(_xlpm.e,Class!E:E,Class!K:K,""), IF(ISNUMBER(MATCH(_xlpm.c,{"Composition","Reference Association","Specialization"},0)), _xlfn.XLOOKUP(_xlpm.h,Class!E:E,Class!K:K,""), _xlfn.XLOOKUP(_xlpm.f,Property!F:F,Property!K:K,"") ) ) ) -> btx
A10: 9 | B10: 2 | C10: Attribute | E10: Header_ Amount Structure | F10: Header_ Amount Type | G10: String | I10: 0..1 | J10: Code or text specifying the type or role of the amount, such as tax amount, tax base amount, allowance amount, or charge amount. | K10: btx | L10: =_xlfn.LET( _xlpm.c,C10,_xlpm.e,E10,_xlpm.f,F10,_xlpm.h,H10, IF( ISNUMBER(MATCH(_xlpm.c,{"Abstract Class","Class"},0)), _xlfn.XLOOKUP(_xlpm.e,Class!E:E,Class!K:K,""), IF(ISNUMBER(MATCH(_xlpm.c,{"Composition","Reference Association","Specialization"},0)), _xlfn.XLOOKUP(_xlpm.h,Class!E:E,Class!K:K,""), _xlfn.XLOOKUP(_xlpm.f,Property!F:F,Property!K:K,"") ) ) ) -> btx
A11: 10 | B11: 2 | C11: Attribute | E11: Header_ Amount Structure | F11: Header_ Currency Code | G11: Token | I11: 0..1 | J11: Code specifying the currency in which the amount is expressed, typically an ISO 4217 currency code. | K11: btx | L11: =_xlfn.LET( _xlpm.c,C11,_xlpm.e,E11,_xlpm.f,F11,_xlpm.h,H11, IF( ISNUMBER(MATCH(_xlpm.c,{"Abstract Class","Class"},0)), _xlfn.XLOOKUP(_xlpm.e,Class!E:E,Class!K:K,""), IF(ISNUMBER(MATCH(_xlpm.c,{"Composition","Reference Association","Specialization"},0)), _xlfn.XLOOKUP(_xlpm.h,Class!E:E,Class!K:K,""), _xlfn.XLOOKUP(_xlpm.f,Property!F:F,Property!K:K,"") ) ) ) -> btx
A12: 11 | B12: 2 | C12: Attribute | E12: Header_ Amount Structure | F12: Header_ Currency Code Type | G12: Token | I12: 0..1 | J12: Code specifying the role of the currency used for the amount, such as functional currency, local currency, reporting currency, or transaction currency. | K12: btx | L12: =_xlfn.LET( _xlpm.c,C12,_xlpm.e,E12,_xlpm.f,F12,_xlpm.h,H12, IF( ISNUMBER(MATCH(_xlpm.c,{"Abstract Class","Class"},0)), _xlfn.XLOOKUP(_xlpm.e,Class!E:E,Class!K:K,""), IF(ISNUMBER(MATCH(_xlpm.c,{"Composition","Reference Association","Specialization"},0)), _xlfn.XLOOKUP(_xlpm.h,Class!E:E,Class!K:K,""), _xlfn.XLOOKUP(_xlpm.f,Property!F:F,Property!K:K,"") ) ) ) -> btx
A13: 12 | B13: 1 | C13: Class | E13: Detail_ Amount Structure | I13: 0..* | J13: Structure representing monetary amounts and currency information applicable to an individual line, such as line-level net amounts, tax calculation bases, allowances, or charges. | K13: btx | L13: =_xlfn.LET( _xlpm.c,C13,_xlpm.e,E13,_xlpm.f,F13,_xlpm.h,H13, IF( ISNUMBER(MATCH(_xlpm.c,{"Abstract Class","Class"},0)), _xlfn.XLOOKUP(_xlpm.e,Class!E:E,Class!K:K,""), IF(ISNUMBER(MATCH(_xlpm.c,{"Composition","Reference Association","Specialization"},0)), _xlfn.XLOOKUP(_xlpm.h,Class!E:E,Class!K:K,""), _xlfn.XLOOKUP(_xlpm.f,Property!F:F,Property!K:K,"") ) ) ) -> btx
A14: 13 | B14: 2 | C14: Specialization | E14: Detail_ Amount Structure | H14: Amount Structure | I14: 1 | K14: btx | L14: =_xlfn.LET( _xlpm.c,C14,_xlpm.e,E14,_xlpm.f,F14,_xlpm.h,H14, IF( ISNUMBER(MATCH(_xlpm.c,{"Abstract Class","Class"},0)), _xlfn.XLOOKUP(_xlpm.e,Class!E:E,Class!K:K,""), IF(ISNUMBER(MATCH(_xlpm.c,{"Composition","Reference Association","Specialization"},0)), _xlfn.XLOOKUP(_xlpm.h,Class!E:E,Class!K:K,""), _xlfn.XLOOKUP(_xlpm.f,Property!F:F,Property!K:K,"") ) ) ) -> btx
A15: 14 | B15: 2 | C15: Attribute | E15: Detail_ Amount Structure | F15: Detail_ Amount | G15: Monetary | I15: 1 | J15: Numeric value of the monetary amount expressed in the specified currency. | K15: btx | L15: =_xlfn.LET( _xlpm.c,C15,_xlpm.e,E15,_xlpm.f,F15,_xlpm.h,H15, IF( ISNUMBER(MATCH(_xlpm.c,{"Abstract Class","Class"},0)), _xlfn.XLOOKUP(_xlpm.e,Class!E:E,Class!K:K,""), IF(ISNUMBER(MATCH(_xlpm.c,{"Composition","Reference Association","Specialization"},0)), _xlfn.XLOOKUP(_xlpm.h,Class!E:E,Class!K:K,""), _xlfn.XLOOKUP(_xlpm.f,Property!F:F,Property!K:K,"") ) ) ) -> btx
A16: 15 | B16: 2 | C16: Attribute | E16: Detail_ Amount Structure | F16: Detail_ Amount Type | G16: String | I16: 0..1 | J16: Code or text specifying the type or role of the amount, such as tax amount, tax base amount, allowance amount, or charge amount. | K16: btx | L16: =_xlfn.LET( _xlpm.c,C16,_xlpm.e,E16,_xlpm.f,F16,_xlpm.h,H16, IF( ISNUMBER(MATCH(_xlpm.c,{"Abstract Class","Class"},0)), _xlfn.XLOOKUP(_xlpm.e,Class!E:E,Class!K:K,""), IF(ISNUMBER(MATCH(_xlpm.c,{"Composition","Reference Association","Specialization"},0)), _xlfn.XLOOKUP(_xlpm.h,Class!E:E,Class!K:K,""), _xlfn.XLOOKUP(_xlpm.f,Property!F:F,Property!K:K,"") ) ) ) -> btx
A17: 16 | B17: 2 | C17: Attribute | E17: Detail_ Amount Structure | F17: Detail_ Currency Code | G17: Token | I17: 0..1 | J17: Code specifying the currency in which the amount is expressed, typically an ISO 4217 currency code. | K17: btx | L17: =_xlfn.LET( _xlpm.c,C17,_xlpm.e,E17,_xlpm.f,F17,_xlpm.h,H17, IF( ISNUMBER(MATCH(_xlpm.c,{"Abstract Class","Class"},0)), _xlfn.XLOOKUP(_xlpm.e,Class!E:E,Class!K:K,""), IF(ISNUMBER(MATCH(_xlpm.c,{"Composition","Reference Association","Specialization"},0)), _xlfn.XLOOKUP(_xlpm.h,Class!E:E,Class!K:K,""), _xlfn.XLOOKUP(_xlpm.f,Property!F:F,Property!K:K,"") ) ) ) -> btx
A18: 17 | B18: 2 | C18: Attribute | E18: Detail_ Amount Structure | F18: Detail_ Currency Code Type | G18: Token | I18: 0..1 | J18: Code specifying the role of the currency used for the amount, such as functional currency, local currency, reporting currency, or transaction currency. | K18: btx | L18: =_xlfn.LET( _xlpm.c,C18,_xlpm.e,E18,_xlpm.f,F18,_xlpm.h,H18, IF( ISNUMBER(MATCH(_xlpm.c,{"Abstract Class","Class"},0)), _xlfn.XLOOKUP(_xlpm.e,Class!E:E,Class!K:K,""), IF(ISNUMBER(MATCH(_xlpm.c,{"Composition","Reference Association","Specialization"},0)), _xlfn.XLOOKUP(_xlpm.h,Class!E:E,Class!K:K,""), _xlfn.XLOOKUP(_xlpm.f,Property!F:F,Property!K:K,"") ) ) ) -> btx
A19: 18 | B19: 2 | C19: Attribute | E19: Detail_ Amount Structure | F19: Detail Adjustment Reason Description Code | G19: Code | I19: 0..1 | J19: UNTDED 4465 Adjustment reason description code. Code specifying the reason for an adjustment. | K19: btx | L19: =_xlfn.LET( _xlpm.c,C19,_xlpm.e,E19,_xlpm.f,F19,_xlpm.h,H19, IF( ISNUMBER(MATCH(_xlpm.c,{"Abstract Class","Class"},0)), _xlfn.XLOOKUP(_xlpm.e,Class!E:E,Class!K:K,""), IF(ISNUMBER(MATCH(_xlpm.c,{"Composition","Reference Association","Specialization"},0)), _xlfn.XLOOKUP(_xlpm.h,Class!E:E,Class!K:K,""), _xlfn.XLOOKUP(_xlpm.f,Property!F:F,Property!K:K,"") ) ) ) -> btx
A20: 19 | B20: 1 | C20: Class | E20: Detail_ Multicurrency | I20: 0..* | J20: Class to provide additional information related to home currencies that differ from original currencies applied at the transaction detail (line) level and related exchange rates - typically this will be used to record exchange rates and amounts in currencies and/or on dates other than those of the original transaction. This class allows recording of exchange rates using a third currency as a triangulation currency. This is often EUR but is not restricted to being so. This class may be repeated as many times as necessary to record amounts in foreign currencies on the same or different dates. | K20: muc | L20: =_xlfn.LET( _xlpm.c,C20,_xlpm.e,E20,_xlpm.f,F20,_xlpm.h,H20, IF( ISNUMBER(MATCH(_xlpm.c,{"Abstract Class","Class"},0)), _xlfn.XLOOKUP(_xlpm.e,Class!E:E,Class!K:K,""), IF(ISNUMBER(MATCH(_xlpm.c,{"Composition","Reference Association","Specialization"},0)), _xlfn.XLOOKUP(_xlpm.h,Class!E:E,Class!K:K,""), _xlfn.XLOOKUP(_xlpm.f,Property!F:F,Property!K:K,"") ) ) ) -> muc
A21: 20 | B21: 2 | C21: Specialization | E21: Detail_ Multicurrency | H21: Multicurrency | I21: 1 | K21: muc | L21: =_xlfn.LET( _xlpm.c,C21,_xlpm.e,E21,_xlpm.f,F21,_xlpm.h,H21, IF( ISNUMBER(MATCH(_xlpm.c,{"Abstract Class","Class"},0)), _xlfn.XLOOKUP(_xlpm.e,Class!E:E,Class!K:K,""), IF(ISNUMBER(MATCH(_xlpm.c,{"Composition","Reference Association","Specialization"},0)), _xlfn.XLOOKUP(_xlpm.h,Class!E:E,Class!K:K,""), _xlfn.XLOOKUP(_xlpm.f,Property!F:F,Property!K:K,"") ) ) ) -> muc
A22: 21 | B22: 2 | C22: Attribute | E22: Detail_ Multicurrency | F22: Detail_ Multicurrency Exchange Rate Date | G22: Date Time | I22: 0..1 | J22: Date of exchange rate (other than original transaction date) on which amount is expressed as amountRestatedAmount or amountTriangulationAmount | K22: muc | L22: =_xlfn.LET( _xlpm.c,C22,_xlpm.e,E22,_xlpm.f,F22,_xlpm.h,H22, IF( ISNUMBER(MATCH(_xlpm.c,{"Abstract Class","Class"},0)), _xlfn.XLOOKUP(_xlpm.e,Class!E:E,Class!K:K,""), IF(ISNUMBER(MATCH(_xlpm.c,{"Composition","Reference Association","Specialization"},0)), _xlfn.XLOOKUP(_xlpm.h,Class!E:E,Class!K:K,""), _xlfn.XLOOKUP(_xlpm.f,Property!F:F,Property!K:K,"") ) ) ) -> muc
A23: 22 | B23: 2 | C23: Attribute | E23: Detail_ Multicurrency | F23: Detail_ Multicurrency Foreign Currency Amount | G23: Monetary | I23: 0..1 | J23: The amount in the foreign currency identified by amountRestatedCurrency as of multicurrencyDetailExchangeRateDate. | K23: muc | L23: =_xlfn.LET( _xlpm.c,C23,_xlpm.e,E23,_xlpm.f,F23,_xlpm.h,H23, IF( ISNUMBER(MATCH(_xlpm.c,{"Abstract Class","Class"},0)), _xlfn.XLOOKUP(_xlpm.e,Class!E:E,Class!K:K,""), IF(ISNUMBER(MATCH(_xlpm.c,{"Composition","Reference Association","Specialization"},0)), _xlfn.XLOOKUP(_xlpm.h,Class!E:E,Class!K:K,""), _xlfn.XLOOKUP(_xlpm.f,Property!F:F,Property!K:K,"") ) ) ) -> muc
A24: 23 | B24: 2 | C24: Attribute | E24: Detail_ Multicurrency | F24: Detail_ Multicurrency Foreign Currency | G24: QName | I24: 0..1 | J24: The currency in which amountRestatedAmount is expressed. Recommended ISO 4217 coding. | K24: muc | L24: =_xlfn.LET( _xlpm.c,C24,_xlpm.e,E24,_xlpm.f,F24,_xlpm.h,H24, IF( ISNUMBER(MATCH(_xlpm.c,{"Abstract Class","Class"},0)), _xlfn.XLOOKUP(_xlpm.e,Class!E:E,Class!K:K,""), IF(ISNUMBER(MATCH(_xlpm.c,{"Composition","Reference Association","Specialization"},0)), _xlfn.XLOOKUP(_xlpm.h,Class!E:E,Class!K:K,""), _xlfn.XLOOKUP(_xlpm.f,Property!F:F,Property!K:K,"") ) ) ) -> muc
A25: 24 | B25: 2 | C25: Attribute | E25: Detail_ Multicurrency | F25: Detail_ Multicurrency Exchange Rate | G25: Pure | I25: 0..1 | J25: Exchange rate used to convert amountRestatedAmount as of multicurrencyDetailExchangeRateDate (expressed as national currency divided by foreign currency) | K25: muc | L25: =_xlfn.LET( _xlpm.c,C25,_xlpm.e,E25,_xlpm.f,F25,_xlpm.h,H25, IF( ISNUMBER(MATCH(_xlpm.c,{"Abstract Class","Class"},0)), _xlfn.XLOOKUP(_xlpm.e,Class!E:E,Class!K:K,""), IF(ISNUMBER(MATCH(_xlpm.c,{"Composition","Reference Association","Specialization"},0)), _xlfn.XLOOKUP(_xlpm.h,Class!E:E,Class!K:K,""), _xlfn.XLOOKUP(_xlpm.f,Property!F:F,Property!K:K,"") ) ) ) -> muc
A26: 25 | B26: 2 | C26: Attribute | E26: Detail_ Multicurrency | F26: Detail_ Multicurrency Exchange Rate Source | G26: String | I26: 0..1 | J26: Source of Exchange Rate for restated amount - for example, Reuters, Bloomberg | K26: muc | L26: =_xlfn.LET( _xlpm.c,C26,_xlpm.e,E26,_xlpm.f,F26,_xlpm.h,H26, IF( ISNUMBER(MATCH(_xlpm.c,{"Abstract Class","Class"},0)), _xlfn.XLOOKUP(_xlpm.e,Class!E:E,Class!K:K,""), IF(ISNUMBER(MATCH(_xlpm.c,{"Composition","Reference Association","Specialization"},0)), _xlfn.XLOOKUP(_xlpm.h,Class!E:E,Class!K:K,""), _xlfn.XLOOKUP(_xlpm.f,Property!F:F,Property!K:K,"") ) ) ) -> muc
A27: 26 | B27: 2 | C27: Attribute | E27: Detail_ Multicurrency | F27: Detail_ Multicurrency Exchange Rate Type | G27: String | I27: 0..1 | J27: Type of Exchange Rate for restated amount - for example, spot rate, forward contract etc. | K27: muc | L27: =_xlfn.LET( _xlpm.c,C27,_xlpm.e,E27,_xlpm.f,F27,_xlpm.h,H27, IF( ISNUMBER(MATCH(_xlpm.c,{"Abstract Class","Class"},0)), _xlfn.XLOOKUP(_xlpm.e,Class!E:E,Class!K:K,""), IF(ISNUMBER(MATCH(_xlpm.c,{"Composition","Reference Association","Specialization"},0)), _xlfn.XLOOKUP(_xlpm.h,Class!E:E,Class!K:K,""), _xlfn.XLOOKUP(_xlpm.f,Property!F:F,Property!K:K,"") ) ) ) -> muc
A28: 27 | B28: 2 | C28: Attribute | E28: Detail_ Multicurrency | F28: Detail_ Multicurrency Comment | G28: String | I28: 0..1 | J28: Comment describing the enclosing multicurrencyDetail class's contents. May include reason for recording additional exchange rates other than that used at the time of the original transaction. | K28: muc | L28: =_xlfn.LET( _xlpm.c,C28,_xlpm.e,E28,_xlpm.f,F28,_xlpm.h,H28, IF( ISNUMBER(MATCH(_xlpm.c,{"Abstract Class","Class"},0)), _xlfn.XLOOKUP(_xlpm.e,Class!E:E,Class!K:K,""), IF(ISNUMBER(MATCH(_xlpm.c,{"Composition","Reference Association","Specialization"},0)), _xlfn.XLOOKUP(_xlpm.h,Class!E:E,Class!K:K,""), _xlfn.XLOOKUP(_xlpm.f,Property!F:F,Property!K:K,"") ) ) ) -> muc
A29: 28 | B29: 1 | C29: Class | E29: Header_ Multicurrency | I29: 0..* | J29: Class to provide additional information related to home currencies that differ from original currencies applicable to the document as a whole and related exchange rates - typically this will be used to record exchange rates and amounts in currencies and/or on dates other than those of the original transaction. This class allows recording of exchange rates using a third currency as a triangulation currency. This is often EUR but is not restricted to being so. This class may be repeated as many times as necessary to record amounts in foreign currencies on the same or different dates. | K29: btx | L29: =_xlfn.LET( _xlpm.c,C29,_xlpm.e,E29,_xlpm.f,F29,_xlpm.h,H29, IF( ISNUMBER(MATCH(_xlpm.c,{"Abstract Class","Class"},0)), _xlfn.XLOOKUP(_xlpm.e,Class!E:E,Class!K:K,""), IF(ISNUMBER(MATCH(_xlpm.c,{"Composition","Reference Association","Specialization"},0)), _xlfn.XLOOKUP(_xlpm.h,Class!E:E,Class!K:K,""), _xlfn.XLOOKUP(_xlpm.f,Property!F:F,Property!K:K,"") ) ) ) -> btx
A30: 29 | B30: 2 | C30: Specialization | E30: Header_ Multicurrency | H30: Multicurrency | I30: 1 | K30: muc | L30: =_xlfn.LET( _xlpm.c,C30,_xlpm.e,E30,_xlpm.f,F30,_xlpm.h,H30, IF( ISNUMBER(MATCH(_xlpm.c,{"Abstract Class","Class"},0)), _xlfn.XLOOKUP(_xlpm.e,Class!E:E,Class!K:K,""), IF(ISNUMBER(MATCH(_xlpm.c,{"Composition","Reference Association","Specialization"},0)), _xlfn.XLOOKUP(_xlpm.h,Class!E:E,Class!K:K,""), _xlfn.XLOOKUP(_xlpm.f,Property!F:F,Property!K:K,"") ) ) ) -> muc
A31: 30 | B31: 2 | C31: Attribute | E31: Header_ Multicurrency | F31: Header_ Multicurrency Exchange Rate Date | G31: Date Time | I31: 0..1 | J31: Date of exchange rate (other than original transaction date) on which amount is expressed as amountRestatedAmount or amountTriangulationAmount | K31: btx | L31: =_xlfn.LET( _xlpm.c,C31,_xlpm.e,E31,_xlpm.f,F31,_xlpm.h,H31, IF( ISNUMBER(MATCH(_xlpm.c,{"Abstract Class","Class"},0)), _xlfn.XLOOKUP(_xlpm.e,Class!E:E,Class!K:K,""), IF(ISNUMBER(MATCH(_xlpm.c,{"Composition","Reference Association","Specialization"},0)), _xlfn.XLOOKUP(_xlpm.h,Class!E:E,Class!K:K,""), _xlfn.XLOOKUP(_xlpm.f,Property!F:F,Property!K:K,"") ) ) ) -> btx
A32: 31 | B32: 2 | C32: Attribute | E32: Header_ Multicurrency | F32: Header_ Multicurrency Foreign Currency Amount | G32: Monetary | I32: 0..1 | J32: The amount in the foreign currency identified by amountRestatedCurrency as of multicurrencyDetailExchangeRateDate. | K32: btx | L32: =_xlfn.LET( _xlpm.c,C32,_xlpm.e,E32,_xlpm.f,F32,_xlpm.h,H32, IF( ISNUMBER(MATCH(_xlpm.c,{"Abstract Class","Class"},0)), _xlfn.XLOOKUP(_xlpm.e,Class!E:E,Class!K:K,""), IF(ISNUMBER(MATCH(_xlpm.c,{"Composition","Reference Association","Specialization"},0)), _xlfn.XLOOKUP(_xlpm.h,Class!E:E,Class!K:K,""), _xlfn.XLOOKUP(_xlpm.f,Property!F:F,Property!K:K,"") ) ) ) -> btx
A33: 32 | B33: 2 | C33: Attribute | E33: Header_ Multicurrency | F33: Header_ Multicurrency Foreign Currency | G33: QName | I33: 0..1 | J33: The currency in which amountRestatedAmount is expressed. Recommended ISO 4217 coding. | K33: btx | L33: =_xlfn.LET( _xlpm.c,C33,_xlpm.e,E33,_xlpm.f,F33,_xlpm.h,H33, IF( ISNUMBER(MATCH(_xlpm.c,{"Abstract Class","Class"},0)), _xlfn.XLOOKUP(_xlpm.e,Class!E:E,Class!K:K,""), IF(ISNUMBER(MATCH(_xlpm.c,{"Composition","Reference Association","Specialization"},0)), _xlfn.XLOOKUP(_xlpm.h,Class!E:E,Class!K:K,""), _xlfn.XLOOKUP(_xlpm.f,Property!F:F,Property!K:K,"") ) ) ) -> btx
A34: 33 | B34: 2 | C34: Attribute | E34: Header_ Multicurrency | F34: Header_ Multicurrency Exchange Rate | G34: Pure | I34: 0..1 | J34: Exchange rate used to convert amountRestatedAmount as of multicurrencyDetailExchangeRateDate (expressed as national currency divided by foreign currency) | K34: btx | L34: =_xlfn.LET( _xlpm.c,C34,_xlpm.e,E34,_xlpm.f,F34,_xlpm.h,H34, IF( ISNUMBER(MATCH(_xlpm.c,{"Abstract Class","Class"},0)), _xlfn.XLOOKUP(_xlpm.e,Class!E:E,Class!K:K,""), IF(ISNUMBER(MATCH(_xlpm.c,{"Composition","Reference Association","Specialization"},0)), _xlfn.XLOOKUP(_xlpm.h,Class!E:E,Class!K:K,""), _xlfn.XLOOKUP(_xlpm.f,Property!F:F,Property!K:K,"") ) ) ) -> btx
A35: 34 | B35: 2 | C35: Attribute | E35: Header_ Multicurrency | F35: Header_ Multicurrency Exchange Rate Source | G35: String | I35: 0..1 | J35: Source of Exchange Rate for restated amount - for example, Reuters, Bloomberg | K35: btx | L35: =_xlfn.LET( _xlpm.c,C35,_xlpm.e,E35,_xlpm.f,F35,_xlpm.h,H35, IF( ISNUMBER(MATCH(_xlpm.c,{"Abstract Class","Class"},0)), _xlfn.XLOOKUP(_xlpm.e,Class!E:E,Class!K:K,""), IF(ISNUMBER(MATCH(_xlpm.c,{"Composition","Reference Association","Specialization"},0)), _xlfn.XLOOKUP(_xlpm.h,Class!E:E,Class!K:K,""), _xlfn.XLOOKUP(_xlpm.f,Property!F:F,Property!K:K,"") ) ) ) -> btx
A36: 35 | B36: 2 | C36: Attribute | E36: Header_ Multicurrency | F36: Header_ Multicurrency Exchange Rate Type | G36: String | I36: 0..1 | J36: Type of Exchange Rate for restated amount - for example, spot rate, forward contract etc. | K36: btx | L36: =_xlfn.LET( _xlpm.c,C36,_xlpm.e,E36,_xlpm.f,F36,_xlpm.h,H36, IF( ISNUMBER(MATCH(_xlpm.c,{"Abstract Class","Class"},0)), _xlfn.XLOOKUP(_xlpm.e,Class!E:E,Class!K:K,""), IF(ISNUMBER(MATCH(_xlpm.c,{"Composition","Reference Association","Specialization"},0)), _xlfn.XLOOKUP(_xlpm.h,Class!E:E,Class!K:K,""), _xlfn.XLOOKUP(_xlpm.f,Property!F:F,Property!K:K,"") ) ) ) -> btx
A37: 36 | B37: 2 | C37: Attribute | E37: Header_ Multicurrency | F37: Header_ Multicurrency Comment | G37: String | I37: 0..1 | J37: Comment describing the enclosing multicurrencyDetail class's contents. May include reason for recording additional exchange rates other than that used at the time of the original transaction. | K37: btx | L37: =_xlfn.LET( _xlpm.c,C37,_xlpm.e,E37,_xlpm.f,F37,_xlpm.h,H37, IF( ISNUMBER(MATCH(_xlpm.c,{"Abstract Class","Class"},0)), _xlfn.XLOOKUP(_xlpm.e,Class!E:E,Class!K:K,""), IF(ISNUMBER(MATCH(_xlpm.c,{"Composition","Reference Association","Specialization"},0)), _xlfn.XLOOKUP(_xlpm.h,Class!E:E,Class!K:K,""), _xlfn.XLOOKUP(_xlpm.f,Property!F:F,Property!K:K,"") ) ) ) -> btx
A38: 37 | B38: 1 | C38: Class | E38: Header_ Account Identifier | I38: 0..* | J38: Class: parent container for account numbers and identifiers applied at the document level. No entry is made here, but each detail line may have multiple accounts assigned to it for reporting in different GAAPs, offsetting accounts in Japan, passing along information to consolidation systems about local versus consolidating accounts, etc. For example, the account 4783HG-QOWI-192837-1000 may be expressed so: /account/accountMainID 1000 /account/accountMainDescription Cash /account/accountSub/accountSubID 4783HG /account/accountSub/accountSubDescription Department /account/accountSub/accountSubID QOWI /account/accountSub/accountSubDescription Branch /account/accountSub/accountSubID 192837 /account/accountSub/accountSubDescription Division | K38: btx | L38: =_xlfn.LET( _xlpm.c,C38,_xlpm.e,E38,_xlpm.f,F38,_xlpm.h,H38, IF( ISNUMBER(MATCH(_xlpm.c,{"Abstract Class","Class"},0)), _xlfn.XLOOKUP(_xlpm.e,Class!E:E,Class!K:K,""), IF(ISNUMBER(MATCH(_xlpm.c,{"Composition","Reference Association","Specialization"},0)), _xlfn.XLOOKUP(_xlpm.h,Class!E:E,Class!K:K,""), _xlfn.XLOOKUP(_xlpm.f,Property!F:F,Property!K:K,"") ) ) ) -> btx
A39: 38 | B39: 2 | C39: Specialization | E39: Header_ Account Identifier | H39: Account Identifier | I39: 1 | K39: cor | L39: =_xlfn.LET( _xlpm.c,C39,_xlpm.e,E39,_xlpm.f,F39,_xlpm.h,H39, IF( ISNUMBER(MATCH(_xlpm.c,{"Abstract Class","Class"},0)), _xlfn.XLOOKUP(_xlpm.e,Class!E:E,Class!K:K,""), IF(ISNUMBER(MATCH(_xlpm.c,{"Composition","Reference Association","Specialization"},0)), _xlfn.XLOOKUP(_xlpm.h,Class!E:E,Class!K:K,""), _xlfn.XLOOKUP(_xlpm.f,Property!F:F,Property!K:K,"") ) ) ) -> cor
A40: 39 | B40: 2 | C40: Attribute | D40: PK | E40: Header_ Account Identifier | F40: Header_ Account Number | G40: String | I40: 0..1 | J40: Main account - the code used to identify the accounting bucket the entry has been assigned to. Examples might be 1000 for Cash, 567GAAZ for Sales Expense or Z for tax payments. Identifiers such as department, branch, division, manager, or other modifiers are noted in the Subaccount area. Before needing to post, account is not necessary. Posting to the general ledger almost always requires an entry here. | K40: btx | L40: =_xlfn.LET( _xlpm.c,C40,_xlpm.e,E40,_xlpm.f,F40,_xlpm.h,H40, IF( ISNUMBER(MATCH(_xlpm.c,{"Abstract Class","Class"},0)), _xlfn.XLOOKUP(_xlpm.e,Class!E:E,Class!K:K,""), IF(ISNUMBER(MATCH(_xlpm.c,{"Composition","Reference Association","Specialization"},0)), _xlfn.XLOOKUP(_xlpm.h,Class!E:E,Class!K:K,""), _xlfn.XLOOKUP(_xlpm.f,Property!F:F,Property!K:K,"") ) ) ) -> btx
A41: 40 | B41: 2 | C41: Attribute | E41: Header_ Account Identifier | F41: Header_ Account Description | G41: String | I41: 0..1 | J41: Description of accountMainID - the human readable describer that accompanies the code used in accountMainID | K41: btx | L41: =_xlfn.LET( _xlpm.c,C41,_xlpm.e,E41,_xlpm.f,F41,_xlpm.h,H41, IF( ISNUMBER(MATCH(_xlpm.c,{"Abstract Class","Class"},0)), _xlfn.XLOOKUP(_xlpm.e,Class!E:E,Class!K:K,""), IF(ISNUMBER(MATCH(_xlpm.c,{"Composition","Reference Association","Specialization"},0)), _xlfn.XLOOKUP(_xlpm.h,Class!E:E,Class!K:K,""), _xlfn.XLOOKUP(_xlpm.f,Property!F:F,Property!K:K,"") ) ) ) -> btx
A42: 41 | B42: 2 | C42: Attribute | E42: Header_ Account Identifier | F42: Header_ Account Classification | G42: Token | I42: 0..1 | J42: Account type - FASB Concepts 6 and similar international designs. When xbrlInfo is used to associated other XBRL reporting items, this field is more suited to representing existing systems (audit) than data interchange. Enumerated as: asset, liability, equity, income, gain, expense, loss, contr-to-equity, distr-from-equity, comprehensive-income, other. | K42: btx | L42: =_xlfn.LET( _xlpm.c,C42,_xlpm.e,E42,_xlpm.f,F42,_xlpm.h,H42, IF( ISNUMBER(MATCH(_xlpm.c,{"Abstract Class","Class"},0)), _xlfn.XLOOKUP(_xlpm.e,Class!E:E,Class!K:K,""), IF(ISNUMBER(MATCH(_xlpm.c,{"Composition","Reference Association","Specialization"},0)), _xlfn.XLOOKUP(_xlpm.h,Class!E:E,Class!K:K,""), _xlfn.XLOOKUP(_xlpm.f,Property!F:F,Property!K:K,"") ) ) ) -> btx
A43: 42 | B43: 2 | C43: Attribute | E43: Header_ Account Identifier | F43: Header_ Account Classification Description | G43: String | I43: 0..1 | J43: Free format description of the account classification | K43: btx | L43: =_xlfn.LET( _xlpm.c,C43,_xlpm.e,E43,_xlpm.f,F43,_xlpm.h,H43, IF( ISNUMBER(MATCH(_xlpm.c,{"Abstract Class","Class"},0)), _xlfn.XLOOKUP(_xlpm.e,Class!E:E,Class!K:K,""), IF(ISNUMBER(MATCH(_xlpm.c,{"Composition","Reference Association","Specialization"},0)), _xlfn.XLOOKUP(_xlpm.h,Class!E:E,Class!K:K,""), _xlfn.XLOOKUP(_xlpm.f,Property!F:F,Property!K:K,"") ) ) ) -> btx
A44: 43 | B44: 2 | C44: Attribute | E44: Header_ Account Identifier | F44: Header_ Parent Account Number | G44: String | I44: 0..1 | J44: Roll up item from child natural account to parent natural account. | K44: btx | L44: =_xlfn.LET( _xlpm.c,C44,_xlpm.e,E44,_xlpm.f,F44,_xlpm.h,H44, IF( ISNUMBER(MATCH(_xlpm.c,{"Abstract Class","Class"},0)), _xlfn.XLOOKUP(_xlpm.e,Class!E:E,Class!K:K,""), IF(ISNUMBER(MATCH(_xlpm.c,{"Composition","Reference Association","Specialization"},0)), _xlfn.XLOOKUP(_xlpm.h,Class!E:E,Class!K:K,""), _xlfn.XLOOKUP(_xlpm.f,Property!F:F,Property!K:K,"") ) ) ) -> btx
A45: 44 | B45: 2 | C45: Attribute | E45: Header_ Account Identifier | F45: Header_ Purpose of Account | G45: Token | I45: 0..1 | J45: Code related to usage for account aggregate - Consolidating, European, IFRS, Offsetting, Primary, Tax, USGAAP, Japanese, Other. Japanese companies will use this for the tax required offsetting entry. If left blank, assumes default accounting method for company. | K45: btx | L45: =_xlfn.LET( _xlpm.c,C45,_xlpm.e,E45,_xlpm.f,F45,_xlpm.h,H45, IF( ISNUMBER(MATCH(_xlpm.c,{"Abstract Class","Class"},0)), _xlfn.XLOOKUP(_xlpm.e,Class!E:E,Class!K:K,""), IF(ISNUMBER(MATCH(_xlpm.c,{"Composition","Reference Association","Specialization"},0)), _xlfn.XLOOKUP(_xlpm.h,Class!E:E,Class!K:K,""), _xlfn.XLOOKUP(_xlpm.f,Property!F:F,Property!K:K,"") ) ) ) -> btx
A46: 45 | B46: 2 | C46: Attribute | E46: Header_ Account Identifier | F46: Header_ Purpose of Account Description | G46: String | I46: 0..1 | J46: Description of usage for aggregate account | K46: btx | L46: =_xlfn.LET( _xlpm.c,C46,_xlpm.e,E46,_xlpm.f,F46,_xlpm.h,H46, IF( ISNUMBER(MATCH(_xlpm.c,{"Abstract Class","Class"},0)), _xlfn.XLOOKUP(_xlpm.e,Class!E:E,Class!K:K,""), IF(ISNUMBER(MATCH(_xlpm.c,{"Composition","Reference Association","Specialization"},0)), _xlfn.XLOOKUP(_xlpm.h,Class!E:E,Class!K:K,""), _xlfn.XLOOKUP(_xlpm.f,Property!F:F,Property!K:K,"") ) ) ) -> btx
A47: 46 | B47: 2 | C47: Attribute | E47: Header_ Account Identifier | F47: Header_ Account Type | G47: Token | I47: 0..1 | J47: Type of account. Enumerated as: account, bank, employee, customer, job, vendor, measurable, statistical, other. | K47: btx | L47: =_xlfn.LET( _xlpm.c,C47,_xlpm.e,E47,_xlpm.f,F47,_xlpm.h,H47, IF( ISNUMBER(MATCH(_xlpm.c,{"Abstract Class","Class"},0)), _xlfn.XLOOKUP(_xlpm.e,Class!E:E,Class!K:K,""), IF(ISNUMBER(MATCH(_xlpm.c,{"Composition","Reference Association","Specialization"},0)), _xlfn.XLOOKUP(_xlpm.h,Class!E:E,Class!K:K,""), _xlfn.XLOOKUP(_xlpm.f,Property!F:F,Property!K:K,"") ) ) ) -> btx
A48: 47 | B48: 2 | C48: Attribute | E48: Header_ Account Identifier | F48: Header_ Account Type Description | G48: String | I48: 0..1 | J48: Free format description of the account type | K48: btx | L48: =_xlfn.LET( _xlpm.c,C48,_xlpm.e,E48,_xlpm.f,F48,_xlpm.h,H48, IF( ISNUMBER(MATCH(_xlpm.c,{"Abstract Class","Class"},0)), _xlfn.XLOOKUP(_xlpm.e,Class!E:E,Class!K:K,""), IF(ISNUMBER(MATCH(_xlpm.c,{"Composition","Reference Association","Specialization"},0)), _xlfn.XLOOKUP(_xlpm.h,Class!E:E,Class!K:K,""), _xlfn.XLOOKUP(_xlpm.f,Property!F:F,Property!K:K,"") ) ) ) -> btx
A49: 48 | B49: 2 | C49: Attribute | E49: Header_ Account Identifier | F49: Header_ Accounting Method | G49: Token | I49: 0..1 | J49: For this entry, the method of accounting represented - from: accrual, cash, modified cash, modified accrual, encumbrance, special methods, hybrid methods, other | K49: btx | L49: =_xlfn.LET( _xlpm.c,C49,_xlpm.e,E49,_xlpm.f,F49,_xlpm.h,H49, IF( ISNUMBER(MATCH(_xlpm.c,{"Abstract Class","Class"},0)), _xlfn.XLOOKUP(_xlpm.e,Class!E:E,Class!K:K,""), IF(ISNUMBER(MATCH(_xlpm.c,{"Composition","Reference Association","Specialization"},0)), _xlfn.XLOOKUP(_xlpm.h,Class!E:E,Class!K:K,""), _xlfn.XLOOKUP(_xlpm.f,Property!F:F,Property!K:K,"") ) ) ) -> btx
A50: 49 | B50: 2 | C50: Attribute | E50: Header_ Account Identifier | F50: Header_ Accounting Method Description | G50: String | I50: 0..1 | J50: Free format description of the entry accounting method | K50: btx | L50: =_xlfn.LET( _xlpm.c,C50,_xlpm.e,E50,_xlpm.f,F50,_xlpm.h,H50, IF( ISNUMBER(MATCH(_xlpm.c,{"Abstract Class","Class"},0)), _xlfn.XLOOKUP(_xlpm.e,Class!E:E,Class!K:K,""), IF(ISNUMBER(MATCH(_xlpm.c,{"Composition","Reference Association","Specialization"},0)), _xlfn.XLOOKUP(_xlpm.h,Class!E:E,Class!K:K,""), _xlfn.XLOOKUP(_xlpm.f,Property!F:F,Property!K:K,"") ) ) ) -> btx
A51: 50 | B51: 2 | C51: Attribute | E51: Header_ Account Identifier | F51: Header_ Accounting Method Purpose | G51: Token | I51: 0..1 | J51: For this entry, the reporting purpose represented - from book, tax, management, statutory, other | K51: btx | L51: =_xlfn.LET( _xlpm.c,C51,_xlpm.e,E51,_xlpm.f,F51,_xlpm.h,H51, IF( ISNUMBER(MATCH(_xlpm.c,{"Abstract Class","Class"},0)), _xlfn.XLOOKUP(_xlpm.e,Class!E:E,Class!K:K,""), IF(ISNUMBER(MATCH(_xlpm.c,{"Composition","Reference Association","Specialization"},0)), _xlfn.XLOOKUP(_xlpm.h,Class!E:E,Class!K:K,""), _xlfn.XLOOKUP(_xlpm.f,Property!F:F,Property!K:K,"") ) ) ) -> btx
A52: 51 | B52: 2 | C52: Attribute | E52: Header_ Account Identifier | F52: Header_ Accounting Method Purpose Description | G52: String | I52: 0..1 | J52: Free format description of the entry accounting method purpose | K52: btx | L52: =_xlfn.LET( _xlpm.c,C52,_xlpm.e,E52,_xlpm.f,F52,_xlpm.h,H52, IF( ISNUMBER(MATCH(_xlpm.c,{"Abstract Class","Class"},0)), _xlfn.XLOOKUP(_xlpm.e,Class!E:E,Class!K:K,""), IF(ISNUMBER(MATCH(_xlpm.c,{"Composition","Reference Association","Specialization"},0)), _xlfn.XLOOKUP(_xlpm.h,Class!E:E,Class!K:K,""), _xlfn.XLOOKUP(_xlpm.f,Property!F:F,Property!K:K,"") ) ) ) -> btx
A53: 52 | B53: 2 | C53: Attribute | E53: Header_ Account Identifier | F53: Header_ Account Active | G53: Boolean | I53: 0..1 | J53: Boolean to indicate whether the account is active (="true") or inactive (="false") | K53: btx | L53: =_xlfn.LET( _xlpm.c,C53,_xlpm.e,E53,_xlpm.f,F53,_xlpm.h,H53, IF( ISNUMBER(MATCH(_xlpm.c,{"Abstract Class","Class"},0)), _xlfn.XLOOKUP(_xlpm.e,Class!E:E,Class!K:K,""), IF(ISNUMBER(MATCH(_xlpm.c,{"Composition","Reference Association","Specialization"},0)), _xlfn.XLOOKUP(_xlpm.h,Class!E:E,Class!K:K,""), _xlfn.XLOOKUP(_xlpm.f,Property!F:F,Property!K:K,"") ) ) ) -> btx
A54: 53 | B54: 2 | C54: Reference Association | E54: Header_ Account Identifier | F54: Header | H54: Subaccount | I54: 0..* | J54: Class to hold multiple accountSubIDs and Descriptions | K54: cor | L54: =_xlfn.LET( _xlpm.c,C54,_xlpm.e,E54,_xlpm.f,F54,_xlpm.h,H54, IF( ISNUMBER(MATCH(_xlpm.c,{"Abstract Class","Class"},0)), _xlfn.XLOOKUP(_xlpm.e,Class!E:E,Class!K:K,""), IF(ISNUMBER(MATCH(_xlpm.c,{"Composition","Reference Association","Specialization"},0)), _xlfn.XLOOKUP(_xlpm.h,Class!E:E,Class!K:K,""), _xlfn.XLOOKUP(_xlpm.f,Property!F:F,Property!K:K,"") ) ) ) -> cor
A55: 54 | B55: 1 | C55: Abstract Class | E55: Allowance Charge | I55: 0..* | J55: Abstract class representing an allowance or a charge applied to an amount, used to model reductions (allowances) or additions (charges) to a base amount, together with their calculation basis, rate, reason, and tax-related attributes. | K55: btx | L55: =_xlfn.LET( _xlpm.c,C55,_xlpm.e,E55,_xlpm.f,F55,_xlpm.h,H55, IF( ISNUMBER(MATCH(_xlpm.c,{"Abstract Class","Class"},0)), _xlfn.XLOOKUP(_xlpm.e,Class!E:E,Class!K:K,""), IF(ISNUMBER(MATCH(_xlpm.c,{"Composition","Reference Association","Specialization"},0)), _xlfn.XLOOKUP(_xlpm.h,Class!E:E,Class!K:K,""), _xlfn.XLOOKUP(_xlpm.f,Property!F:F,Property!K:K,"") ) ) ) -> btx
A56: 55 | B56: 2 | C56: Attribute | E56: Allowance Charge | F56: Charge Indicator | G56: Boolean | I56: 1 | J56: Indicator specifying whether the allowance charge represents a charge (true) or an allowance (false). | K56: btx | L56: =_xlfn.LET( _xlpm.c,C56,_xlpm.e,E56,_xlpm.f,F56,_xlpm.h,H56, IF( ISNUMBER(MATCH(_xlpm.c,{"Abstract Class","Class"},0)), _xlfn.XLOOKUP(_xlpm.e,Class!E:E,Class!K:K,""), IF(ISNUMBER(MATCH(_xlpm.c,{"Composition","Reference Association","Specialization"},0)), _xlfn.XLOOKUP(_xlpm.h,Class!E:E,Class!K:K,""), _xlfn.XLOOKUP(_xlpm.f,Property!F:F,Property!K:K,"") ) ) ) -> btx
A57: 56 | B57: 2 | C57: Attribute | E57: Allowance Charge | F57: Allowance Charge Amount | G57: Monetary | I57: 1 | J57: The monetary amount of the allowance or charge applied. | K57: btx | L57: =_xlfn.LET( _xlpm.c,C57,_xlpm.e,E57,_xlpm.f,F57,_xlpm.h,H57, IF( ISNUMBER(MATCH(_xlpm.c,{"Abstract Class","Class"},0)), _xlfn.XLOOKUP(_xlpm.e,Class!E:E,Class!K:K,""), IF(ISNUMBER(MATCH(_xlpm.c,{"Composition","Reference Association","Specialization"},0)), _xlfn.XLOOKUP(_xlpm.h,Class!E:E,Class!K:K,""), _xlfn.XLOOKUP(_xlpm.f,Property!F:F,Property!K:K,"") ) ) ) -> btx
A58: 57 | B58: 2 | C58: Attribute | E58: Allowance Charge | F58: Allowance Charge Base Amount | G58: Monetary | I58: 0..1 | J58: The base monetary amount to which the allowance or charge is applied. | K58: btx | L58: =_xlfn.LET( _xlpm.c,C58,_xlpm.e,E58,_xlpm.f,F58,_xlpm.h,H58, IF( ISNUMBER(MATCH(_xlpm.c,{"Abstract Class","Class"},0)), _xlfn.XLOOKUP(_xlpm.e,Class!E:E,Class!K:K,""), IF(ISNUMBER(MATCH(_xlpm.c,{"Composition","Reference Association","Specialization"},0)), _xlfn.XLOOKUP(_xlpm.h,Class!E:E,Class!K:K,""), _xlfn.XLOOKUP(_xlpm.f,Property!F:F,Property!K:K,"") ) ) ) -> btx
A59: 58 | B59: 2 | C59: Attribute | E59: Allowance Charge | F59: Allowance Charge Percentage | G59: Pure | I59: 0..1 | J59: The percentage rate used to calculate the allowance or charge based on the base amount. | K59: btx | L59: =_xlfn.LET( _xlpm.c,C59,_xlpm.e,E59,_xlpm.f,F59,_xlpm.h,H59, IF( ISNUMBER(MATCH(_xlpm.c,{"Abstract Class","Class"},0)), _xlfn.XLOOKUP(_xlpm.e,Class!E:E,Class!K:K,""), IF(ISNUMBER(MATCH(_xlpm.c,{"Composition","Reference Association","Specialization"},0)), _xlfn.XLOOKUP(_xlpm.h,Class!E:E,Class!K:K,""), _xlfn.XLOOKUP(_xlpm.f,Property!F:F,Property!K:K,"") ) ) ) -> btx
A60: 59 | B60: 2 | C60: Attribute | E60: Allowance Charge | F60: Allowance Charge Reason Code | G60: Code | I60: 0..1 | J60: A code specifying the reason for applying the allowance or charge. | K60: btx | L60: =_xlfn.LET( _xlpm.c,C60,_xlpm.e,E60,_xlpm.f,F60,_xlpm.h,H60, IF( ISNUMBER(MATCH(_xlpm.c,{"Abstract Class","Class"},0)), _xlfn.XLOOKUP(_xlpm.e,Class!E:E,Class!K:K,""), IF(ISNUMBER(MATCH(_xlpm.c,{"Composition","Reference Association","Specialization"},0)), _xlfn.XLOOKUP(_xlpm.h,Class!E:E,Class!K:K,""), _xlfn.XLOOKUP(_xlpm.f,Property!F:F,Property!K:K,"") ) ) ) -> btx
A61: 60 | B61: 2 | C61: Attribute | E61: Allowance Charge | F61: Allowance Charge Tax Category Code | G61: Code | I61: 0..1 | J61: A code identifying the tax category applicable to the allowance or charge. | K61: btx | L61: =_xlfn.LET( _xlpm.c,C61,_xlpm.e,E61,_xlpm.f,F61,_xlpm.h,H61, IF( ISNUMBER(MATCH(_xlpm.c,{"Abstract Class","Class"},0)), _xlfn.XLOOKUP(_xlpm.e,Class!E:E,Class!K:K,""), IF(ISNUMBER(MATCH(_xlpm.c,{"Composition","Reference Association","Specialization"},0)), _xlfn.XLOOKUP(_xlpm.h,Class!E:E,Class!K:K,""), _xlfn.XLOOKUP(_xlpm.f,Property!F:F,Property!K:K,"") ) ) ) -> btx
A62: 61 | B62: 2 | C62: Attribute | E62: Allowance Charge | F62: Allowance Charge Tax Ratio | G62: Pure | I62: 0..1 | J62: The tax ratio or rate applicable to the allowance or charge amount. | K62: btx | L62: =_xlfn.LET( _xlpm.c,C62,_xlpm.e,E62,_xlpm.f,F62,_xlpm.h,H62, IF( ISNUMBER(MATCH(_xlpm.c,{"Abstract Class","Class"},0)), _xlfn.XLOOKUP(_xlpm.e,Class!E:E,Class!K:K,""), IF(ISNUMBER(MATCH(_xlpm.c,{"Composition","Reference Association","Specialization"},0)), _xlfn.XLOOKUP(_xlpm.h,Class!E:E,Class!K:K,""), _xlfn.XLOOKUP(_xlpm.f,Property!F:F,Property!K:K,"") ) ) ) -> btx
A63: 62 | B63: 1 | C63: Class | E63: Header_ Allowance Charge | I63: 0..* | J63: Class representing an allowance or a charge applied at the document or transaction header level. It is used to model header-level reductions or additions that apply to the entire document or transaction, including their amount, calculation basis, percentage, reason, and applicable tax attributes. | K63: btx | L63: =_xlfn.LET( _xlpm.c,C63,_xlpm.e,E63,_xlpm.f,F63,_xlpm.h,H63, IF( ISNUMBER(MATCH(_xlpm.c,{"Abstract Class","Class"},0)), _xlfn.XLOOKUP(_xlpm.e,Class!E:E,Class!K:K,""), IF(ISNUMBER(MATCH(_xlpm.c,{"Composition","Reference Association","Specialization"},0)), _xlfn.XLOOKUP(_xlpm.h,Class!E:E,Class!K:K,""), _xlfn.XLOOKUP(_xlpm.f,Property!F:F,Property!K:K,"") ) ) ) -> btx
A64: 63 | B64: 2 | C64: Specialization | E64: Header_ Allowance Charge | H64: Allowance Charge | I64: 1 | K64: btx | L64: =_xlfn.LET( _xlpm.c,C64,_xlpm.e,E64,_xlpm.f,F64,_xlpm.h,H64, IF( ISNUMBER(MATCH(_xlpm.c,{"Abstract Class","Class"},0)), _xlfn.XLOOKUP(_xlpm.e,Class!E:E,Class!K:K,""), IF(ISNUMBER(MATCH(_xlpm.c,{"Composition","Reference Association","Specialization"},0)), _xlfn.XLOOKUP(_xlpm.h,Class!E:E,Class!K:K,""), _xlfn.XLOOKUP(_xlpm.f,Property!F:F,Property!K:K,"") ) ) ) -> btx
A65: 64 | B65: 2 | C65: Attribute | E65: Header_ Allowance Charge | F65: Header_ Charge Indicator | G65: Boolean | I65: 1 | J65: Indicator specifying whether the allowance charge represents a charge (true) or an allowance (false). | K65: btx | L65: =_xlfn.LET( _xlpm.c,C65,_xlpm.e,E65,_xlpm.f,F65,_xlpm.h,H65, IF( ISNUMBER(MATCH(_xlpm.c,{"Abstract Class","Class"},0)), _xlfn.XLOOKUP(_xlpm.e,Class!E:E,Class!K:K,""), IF(ISNUMBER(MATCH(_xlpm.c,{"Composition","Reference Association","Specialization"},0)), _xlfn.XLOOKUP(_xlpm.h,Class!E:E,Class!K:K,""), _xlfn.XLOOKUP(_xlpm.f,Property!F:F,Property!K:K,"") ) ) ) -> btx
A66: 65 | B66: 2 | C66: Attribute | E66: Header_ Allowance Charge | F66: Header_ Allowance Charge Amount | G66: Monetary | I66: 1 | J66: The monetary amount of the allowance or charge applied. | K66: btx | L66: =_xlfn.LET( _xlpm.c,C66,_xlpm.e,E66,_xlpm.f,F66,_xlpm.h,H66, IF( ISNUMBER(MATCH(_xlpm.c,{"Abstract Class","Class"},0)), _xlfn.XLOOKUP(_xlpm.e,Class!E:E,Class!K:K,""), IF(ISNUMBER(MATCH(_xlpm.c,{"Composition","Reference Association","Specialization"},0)), _xlfn.XLOOKUP(_xlpm.h,Class!E:E,Class!K:K,""), _xlfn.XLOOKUP(_xlpm.f,Property!F:F,Property!K:K,"") ) ) ) -> btx
A67: 66 | B67: 2 | C67: Attribute | E67: Header_ Allowance Charge | F67: Header_ Allowance Charge Base Amount | G67: Monetary | I67: 0..1 | J67: The base monetary amount to which the allowance or charge is applied. | K67: btx | L67: =_xlfn.LET( _xlpm.c,C67,_xlpm.e,E67,_xlpm.f,F67,_xlpm.h,H67, IF( ISNUMBER(MATCH(_xlpm.c,{"Abstract Class","Class"},0)), _xlfn.XLOOKUP(_xlpm.e,Class!E:E,Class!K:K,""), IF(ISNUMBER(MATCH(_xlpm.c,{"Composition","Reference Association","Specialization"},0)), _xlfn.XLOOKUP(_xlpm.h,Class!E:E,Class!K:K,""), _xlfn.XLOOKUP(_xlpm.f,Property!F:F,Property!K:K,"") ) ) ) -> btx
A68: 67 | B68: 2 | C68: Attribute | E68: Header_ Allowance Charge | F68: Header_ Allowance Charge Percentage | G68: Pure | I68: 0..1 | J68: The percentage rate used to calculate the allowance or charge based on the base amount. | K68: btx | L68: =_xlfn.LET( _xlpm.c,C68,_xlpm.e,E68,_xlpm.f,F68,_xlpm.h,H68, IF( ISNUMBER(MATCH(_xlpm.c,{"Abstract Class","Class"},0)), _xlfn.XLOOKUP(_xlpm.e,Class!E:E,Class!K:K,""), IF(ISNUMBER(MATCH(_xlpm.c,{"Composition","Reference Association","Specialization"},0)), _xlfn.XLOOKUP(_xlpm.h,Class!E:E,Class!K:K,""), _xlfn.XLOOKUP(_xlpm.f,Property!F:F,Property!K:K,"") ) ) ) -> btx
A69: 68 | B69: 2 | C69: Attribute | E69: Header_ Allowance Charge | F69: Header_ Allowance Charge Reason Code | G69: Code | I69: 0..1 | J69: A code specifying the reason for applying the allowance or charge. | K69: btx | L69: =_xlfn.LET( _xlpm.c,C69,_xlpm.e,E69,_xlpm.f,F69,_xlpm.h,H69, IF( ISNUMBER(MATCH(_xlpm.c,{"Abstract Class","Class"},0)), _xlfn.XLOOKUP(_xlpm.e,Class!E:E,Class!K:K,""), IF(ISNUMBER(MATCH(_xlpm.c,{"Composition","Reference Association","Specialization"},0)), _xlfn.XLOOKUP(_xlpm.h,Class!E:E,Class!K:K,""), _xlfn.XLOOKUP(_xlpm.f,Property!F:F,Property!K:K,"") ) ) ) -> btx
A70: 69 | B70: 2 | C70: Attribute | E70: Header_ Allowance Charge | F70: Header_ Allowance Charge Tax Category Code | G70: Code | I70: 0..1 | J70: A code identifying the tax category applicable to the allowance or charge. | K70: btx | L70: =_xlfn.LET( _xlpm.c,C70,_xlpm.e,E70,_xlpm.f,F70,_xlpm.h,H70, IF( ISNUMBER(MATCH(_xlpm.c,{"Abstract Class","Class"},0)), _xlfn.XLOOKUP(_xlpm.e,Class!E:E,Class!K:K,""), IF(ISNUMBER(MATCH(_xlpm.c,{"Composition","Reference Association","Specialization"},0)), _xlfn.XLOOKUP(_xlpm.h,Class!E:E,Class!K:K,""), _xlfn.XLOOKUP(_xlpm.f,Property!F:F,Property!K:K,"") ) ) ) -> btx
A71: 70 | B71: 2 | C71: Attribute | E71: Header_ Allowance Charge | F71: Header_ Allowance Charge Tax Ratio | G71: Pure | I71: 0..1 | J71: The tax ratio or rate applicable to the allowance or charge amount. | K71: btx | L71: =_xlfn.LET( _xlpm.c,C71,_xlpm.e,E71,_xlpm.f,F71,_xlpm.h,H71, IF( ISNUMBER(MATCH(_xlpm.c,{"Abstract Class","Class"},0)), _xlfn.XLOOKUP(_xlpm.e,Class!E:E,Class!K:K,""), IF(ISNUMBER(MATCH(_xlpm.c,{"Composition","Reference Association","Specialization"},0)), _xlfn.XLOOKUP(_xlpm.h,Class!E:E,Class!K:K,""), _xlfn.XLOOKUP(_xlpm.f,Property!F:F,Property!K:K,"") ) ) ) -> btx
A72: 71 | B72: 1 | C72: Class | E72: Detail_ Allowance Charge | I72: 0..* | J72: Class representing an allowance or a charge applied at the transaction detail (line) level. It is used to model line-level reductions or additions, including their amount, calculation basis, percentage, reason, and applicable tax attributes. | K72: btx | L72: =_xlfn.LET( _xlpm.c,C72,_xlpm.e,E72,_xlpm.f,F72,_xlpm.h,H72, IF( ISNUMBER(MATCH(_xlpm.c,{"Abstract Class","Class"},0)), _xlfn.XLOOKUP(_xlpm.e,Class!E:E,Class!K:K,""), IF(ISNUMBER(MATCH(_xlpm.c,{"Composition","Reference Association","Specialization"},0)), _xlfn.XLOOKUP(_xlpm.h,Class!E:E,Class!K:K,""), _xlfn.XLOOKUP(_xlpm.f,Property!F:F,Property!K:K,"") ) ) ) -> btx
A73: 72 | B73: 2 | C73: Specialization | E73: Detail_ Allowance Charge | H73: Allowance Charge | I73: 1 | K73: btx | L73: =_xlfn.LET( _xlpm.c,C73,_xlpm.e,E73,_xlpm.f,F73,_xlpm.h,H73, IF( ISNUMBER(MATCH(_xlpm.c,{"Abstract Class","Class"},0)), _xlfn.XLOOKUP(_xlpm.e,Class!E:E,Class!K:K,""), IF(ISNUMBER(MATCH(_xlpm.c,{"Composition","Reference Association","Specialization"},0)), _xlfn.XLOOKUP(_xlpm.h,Class!E:E,Class!K:K,""), _xlfn.XLOOKUP(_xlpm.f,Property!F:F,Property!K:K,"") ) ) ) -> btx
A74: 73 | B74: 2 | C74: Attribute | E74: Detail_ Allowance Charge | F74: Detail_ Charge Indicator | G74: Boolean | I74: 1 | J74: Indicator specifying whether the allowance charge represents a charge (true) or an allowance (false). | K74: btx | L74: =_xlfn.LET( _xlpm.c,C74,_xlpm.e,E74,_xlpm.f,F74,_xlpm.h,H74, IF( ISNUMBER(MATCH(_xlpm.c,{"Abstract Class","Class"},0)), _xlfn.XLOOKUP(_xlpm.e,Class!E:E,Class!K:K,""), IF(ISNUMBER(MATCH(_xlpm.c,{"Composition","Reference Association","Specialization"},0)), _xlfn.XLOOKUP(_xlpm.h,Class!E:E,Class!K:K,""), _xlfn.XLOOKUP(_xlpm.f,Property!F:F,Property!K:K,"") ) ) ) -> btx
A75: 74 | B75: 2 | C75: Attribute | E75: Detail_ Allowance Charge | F75: Detail_ Allowance Charge Amount | G75: Monetary | I75: 1 | J75: The monetary amount of the allowance or charge applied. | K75: btx | L75: =_xlfn.LET( _xlpm.c,C75,_xlpm.e,E75,_xlpm.f,F75,_xlpm.h,H75, IF( ISNUMBER(MATCH(_xlpm.c,{"Abstract Class","Class"},0)), _xlfn.XLOOKUP(_xlpm.e,Class!E:E,Class!K:K,""), IF(ISNUMBER(MATCH(_xlpm.c,{"Composition","Reference Association","Specialization"},0)), _xlfn.XLOOKUP(_xlpm.h,Class!E:E,Class!K:K,""), _xlfn.XLOOKUP(_xlpm.f,Property!F:F,Property!K:K,"") ) ) ) -> btx
A76: 75 | B76: 2 | C76: Attribute | E76: Detail_ Allowance Charge | F76: Detail_ Allowance Charge Base Amount | G76: Monetary | I76: 0..1 | J76: The base monetary amount to which the allowance or charge is applied. | K76: btx | L76: =_xlfn.LET( _xlpm.c,C76,_xlpm.e,E76,_xlpm.f,F76,_xlpm.h,H76, IF( ISNUMBER(MATCH(_xlpm.c,{"Abstract Class","Class"},0)), _xlfn.XLOOKUP(_xlpm.e,Class!E:E,Class!K:K,""), IF(ISNUMBER(MATCH(_xlpm.c,{"Composition","Reference Association","Specialization"},0)), _xlfn.XLOOKUP(_xlpm.h,Class!E:E,Class!K:K,""), _xlfn.XLOOKUP(_xlpm.f,Property!F:F,Property!K:K,"") ) ) ) -> btx
A77: 76 | B77: 2 | C77: Attribute | E77: Detail_ Allowance Charge | F77: Detail_ Allowance Charge Percentage | G77: Pure | I77: 0..1 | J77: The percentage rate used to calculate the allowance or charge based on the base amount. | K77: btx | L77: =_xlfn.LET( _xlpm.c,C77,_xlpm.e,E77,_xlpm.f,F77,_xlpm.h,H77, IF( ISNUMBER(MATCH(_xlpm.c,{"Abstract Class","Class"},0)), _xlfn.XLOOKUP(_xlpm.e,Class!E:E,Class!K:K,""), IF(ISNUMBER(MATCH(_xlpm.c,{"Composition","Reference Association","Specialization"},0)), _xlfn.XLOOKUP(_xlpm.h,Class!E:E,Class!K:K,""), _xlfn.XLOOKUP(_xlpm.f,Property!F:F,Property!K:K,"") ) ) ) -> btx
A78: 77 | B78: 2 | C78: Attribute | E78: Detail_ Allowance Charge | F78: Detail_ Allowance Charge Reason Code | G78: Code | I78: 0..1 | J78: A code specifying the reason for applying the allowance or charge. | K78: btx | L78: =_xlfn.LET( _xlpm.c,C78,_xlpm.e,E78,_xlpm.f,F78,_xlpm.h,H78, IF( ISNUMBER(MATCH(_xlpm.c,{"Abstract Class","Class"},0)), _xlfn.XLOOKUP(_xlpm.e,Class!E:E,Class!K:K,""), IF(ISNUMBER(MATCH(_xlpm.c,{"Composition","Reference Association","Specialization"},0)), _xlfn.XLOOKUP(_xlpm.h,Class!E:E,Class!K:K,""), _xlfn.XLOOKUP(_xlpm.f,Property!F:F,Property!K:K,"") ) ) ) -> btx
A79: 78 | B79: 2 | C79: Attribute | E79: Detail_ Allowance Charge | F79: Detail_ Allowance Charge Tax Category Code | G79: Code | I79: 0..1 | J79: A code identifying the tax category applicable to the allowance or charge. | K79: btx | L79: =_xlfn.LET( _xlpm.c,C79,_xlpm.e,E79,_xlpm.f,F79,_xlpm.h,H79, IF( ISNUMBER(MATCH(_xlpm.c,{"Abstract Class","Class"},0)), _xlfn.XLOOKUP(_xlpm.e,Class!E:E,Class!K:K,""), IF(ISNUMBER(MATCH(_xlpm.c,{"Composition","Reference Association","Specialization"},0)), _xlfn.XLOOKUP(_xlpm.h,Class!E:E,Class!K:K,""), _xlfn.XLOOKUP(_xlpm.f,Property!F:F,Property!K:K,"") ) ) ) -> btx
A80: 79 | B80: 2 | C80: Attribute | E80: Detail_ Allowance Charge | F80: Detail_ Allowance Charge Tax Ratio | G80: Pure | I80: 0..1 | J80: The tax ratio or rate applicable to the allowance or charge amount. | K80: btx | L80: =_xlfn.LET( _xlpm.c,C80,_xlpm.e,E80,_xlpm.f,F80,_xlpm.h,H80, IF( ISNUMBER(MATCH(_xlpm.c,{"Abstract Class","Class"},0)), _xlfn.XLOOKUP(_xlpm.e,Class!E:E,Class!K:K,""), IF(ISNUMBER(MATCH(_xlpm.c,{"Composition","Reference Association","Specialization"},0)), _xlfn.XLOOKUP(_xlpm.h,Class!E:E,Class!K:K,""), _xlfn.XLOOKUP(_xlpm.f,Property!F:F,Property!K:K,"") ) ) ) -> btx
A81: 80 | B81: 1 | C81: Class | E81: Header_ Party | I81: 0..1 | J81: Holder for entity information - information about the reporting organization. | K81: btx | L81: =_xlfn.LET( _xlpm.c,C81,_xlpm.e,E81,_xlpm.f,F81,_xlpm.h,H81, IF( ISNUMBER(MATCH(_xlpm.c,{"Abstract Class","Class"},0)), _xlfn.XLOOKUP(_xlpm.e,Class!E:E,Class!K:K,""), IF(ISNUMBER(MATCH(_xlpm.c,{"Composition","Reference Association","Specialization"},0)), _xlfn.XLOOKUP(_xlpm.h,Class!E:E,Class!K:K,""), _xlfn.XLOOKUP(_xlpm.f,Property!F:F,Property!K:K,"") ) ) ) -> btx
A82: 81 | B82: 2 | C82: Specialization | E82: Header_ Party | H82: Party | I82: 1 | K82: cor | L82: =_xlfn.LET( _xlpm.c,C82,_xlpm.e,E82,_xlpm.f,F82,_xlpm.h,H82, IF( ISNUMBER(MATCH(_xlpm.c,{"Abstract Class","Class"},0)), _xlfn.XLOOKUP(_xlpm.e,Class!E:E,Class!K:K,""), IF(ISNUMBER(MATCH(_xlpm.c,{"Composition","Reference Association","Specialization"},0)), _xlfn.XLOOKUP(_xlpm.h,Class!E:E,Class!K:K,""), _xlfn.XLOOKUP(_xlpm.f,Property!F:F,Property!K:K,"") ) ) ) -> cor
A83: 82 | B83: 2 | C83: Attribute | D83: PK | E83: Header_ Party | F83: Header_ Party ID | G83: String | I83: 0..1 | J83: ID Number of the party | K83: btx | L83: =_xlfn.LET( _xlpm.c,C83,_xlpm.e,E83,_xlpm.f,F83,_xlpm.h,H83, IF( ISNUMBER(MATCH(_xlpm.c,{"Abstract Class","Class"},0)), _xlfn.XLOOKUP(_xlpm.e,Class!E:E,Class!K:K,""), IF(ISNUMBER(MATCH(_xlpm.c,{"Composition","Reference Association","Specialization"},0)), _xlfn.XLOOKUP(_xlpm.h,Class!E:E,Class!K:K,""), _xlfn.XLOOKUP(_xlpm.f,Property!F:F,Property!K:K,"") ) ) ) -> btx
A84: 83 | B84: 2 | C84: Attribute | E84: Header_ Party | F84: Header_ Party Name | G84: String | I84: 0..1 | J84: Name of the party | K84: btx | L84: =_xlfn.LET( _xlpm.c,C84,_xlpm.e,E84,_xlpm.f,F84,_xlpm.h,H84, IF( ISNUMBER(MATCH(_xlpm.c,{"Abstract Class","Class"},0)), _xlfn.XLOOKUP(_xlpm.e,Class!E:E,Class!K:K,""), IF(ISNUMBER(MATCH(_xlpm.c,{"Composition","Reference Association","Specialization"},0)), _xlfn.XLOOKUP(_xlpm.h,Class!E:E,Class!K:K,""), _xlfn.XLOOKUP(_xlpm.f,Property!F:F,Property!K:K,"") ) ) ) -> btx
A85: 84 | B85: 2 | C85: Attribute | E85: Header_ Party | F85: Header_ Party Business Description | G85: String | I85: 0..1 | J85: Description of the nature of the business of the party. | K85: btx | L85: =_xlfn.LET( _xlpm.c,C85,_xlpm.e,E85,_xlpm.f,F85,_xlpm.h,H85, IF( ISNUMBER(MATCH(_xlpm.c,{"Abstract Class","Class"},0)), _xlfn.XLOOKUP(_xlpm.e,Class!E:E,Class!K:K,""), IF(ISNUMBER(MATCH(_xlpm.c,{"Composition","Reference Association","Specialization"},0)), _xlfn.XLOOKUP(_xlpm.h,Class!E:E,Class!K:K,""), _xlfn.XLOOKUP(_xlpm.f,Property!F:F,Property!K:K,"") ) ) ) -> btx
A86: 85 | B86: 2 | C86: Reference Association | E86: Header_ Party | F86: Header_ Party | H86: Authority Registered Identifier | I86: 0..* | J86: Class which contains various identifiers for theparty. | K86: cor | L86: =_xlfn.LET( _xlpm.c,C86,_xlpm.e,E86,_xlpm.f,F86,_xlpm.h,H86, IF( ISNUMBER(MATCH(_xlpm.c,{"Abstract Class","Class"},0)), _xlfn.XLOOKUP(_xlpm.e,Class!E:E,Class!K:K,""), IF(ISNUMBER(MATCH(_xlpm.c,{"Composition","Reference Association","Specialization"},0)), _xlfn.XLOOKUP(_xlpm.h,Class!E:E,Class!K:K,""), _xlfn.XLOOKUP(_xlpm.f,Property!F:F,Property!K:K,"") ) ) ) -> cor
A87: 86 | B87: 2 | C87: Composition | E87: Header_ Party | F87: Header_ Party | H87: Communication | I87: 0..* | J87: The exchange of messages or information between parties using a specified communication channel. | K87: bus | L87: =_xlfn.LET( _xlpm.c,C87,_xlpm.e,E87,_xlpm.f,F87,_xlpm.h,H87, IF( ISNUMBER(MATCH(_xlpm.c,{"Abstract Class","Class"},0)), _xlfn.XLOOKUP(_xlpm.e,Class!E:E,Class!K:K,""), IF(ISNUMBER(MATCH(_xlpm.c,{"Composition","Reference Association","Specialization"},0)), _xlfn.XLOOKUP(_xlpm.h,Class!E:E,Class!K:K,""), _xlfn.XLOOKUP(_xlpm.f,Property!F:F,Property!K:K,"") ) ) ) -> bus
A88: 87 | B88: 2 | C88: Composition | E88: Header_ Party | F88: Header_ Party | H88: Address | I88: 0..* | J88: Address class for the party | K88: bus | L88: =_xlfn.LET( _xlpm.c,C88,_xlpm.e,E88,_xlpm.f,F88,_xlpm.h,H88, IF( ISNUMBER(MATCH(_xlpm.c,{"Abstract Class","Class"},0)), _xlfn.XLOOKUP(_xlpm.e,Class!E:E,Class!K:K,""), IF(ISNUMBER(MATCH(_xlpm.c,{"Composition","Reference Association","Specialization"},0)), _xlfn.XLOOKUP(_xlpm.h,Class!E:E,Class!K:K,""), _xlfn.XLOOKUP(_xlpm.f,Property!F:F,Property!K:K,"") ) ) ) -> bus
A89: 88 | B89: 2 | C89: Composition | E89: Header_ Party | F89: Header_ Party | H89: Contact | I89: 0..* | J89: Information about contacts. | K89: bus | L89: =_xlfn.LET( _xlpm.c,C89,_xlpm.e,E89,_xlpm.f,F89,_xlpm.h,H89, IF( ISNUMBER(MATCH(_xlpm.c,{"Abstract Class","Class"},0)), _xlfn.XLOOKUP(_xlpm.e,Class!E:E,Class!K:K,""), IF(ISNUMBER(MATCH(_xlpm.c,{"Composition","Reference Association","Specialization"},0)), _xlfn.XLOOKUP(_xlpm.h,Class!E:E,Class!K:K,""), _xlfn.XLOOKUP(_xlpm.f,Property!F:F,Property!K:K,"") ) ) ) -> bus
A90: 89 | B90: 2 | C90: Attribute | E90: Header_ Party | F90: Header Party Business Description | G90: String | I90: 0..1 | J90: Description of the nature of the business of the entity. | K90: btx | L90: =_xlfn.LET( _xlpm.c,C90,_xlpm.e,E90,_xlpm.f,F90,_xlpm.h,H90, IF( ISNUMBER(MATCH(_xlpm.c,{"Abstract Class","Class"},0)), _xlfn.XLOOKUP(_xlpm.e,Class!E:E,Class!K:K,""), IF(ISNUMBER(MATCH(_xlpm.c,{"Composition","Reference Association","Specialization"},0)), _xlfn.XLOOKUP(_xlpm.h,Class!E:E,Class!K:K,""), _xlfn.XLOOKUP(_xlpm.f,Property!F:F,Property!K:K,"") ) ) ) -> btx
A91: 90 | B91: 1 | C91: Class | E91: Detail_ Party | I91: 0..1 | J91: Holder for entity information - information about the reporting organization. | K91: btx | L91: =_xlfn.LET( _xlpm.c,C91,_xlpm.e,E91,_xlpm.f,F91,_xlpm.h,H91, IF( ISNUMBER(MATCH(_xlpm.c,{"Abstract Class","Class"},0)), _xlfn.XLOOKUP(_xlpm.e,Class!E:E,Class!K:K,""), IF(ISNUMBER(MATCH(_xlpm.c,{"Composition","Reference Association","Specialization"},0)), _xlfn.XLOOKUP(_xlpm.h,Class!E:E,Class!K:K,""), _xlfn.XLOOKUP(_xlpm.f,Property!F:F,Property!K:K,"") ) ) ) -> btx
A92: 91 | B92: 2 | C92: Specialization | E92: Detail_ Party | H92: Party | I92: 1 | K92: cor | L92: =_xlfn.LET( _xlpm.c,C92,_xlpm.e,E92,_xlpm.f,F92,_xlpm.h,H92, IF( ISNUMBER(MATCH(_xlpm.c,{"Abstract Class","Class"},0)), _xlfn.XLOOKUP(_xlpm.e,Class!E:E,Class!K:K,""), IF(ISNUMBER(MATCH(_xlpm.c,{"Composition","Reference Association","Specialization"},0)), _xlfn.XLOOKUP(_xlpm.h,Class!E:E,Class!K:K,""), _xlfn.XLOOKUP(_xlpm.f,Property!F:F,Property!K:K,"") ) ) ) -> cor
A93: 92 | B93: 2 | C93: Attribute | D93: PK | E93: Detail_ Party | F93: Detail_ Party ID | G93: String | I93: 0..1 | J93: ID Number of the party | K93: btx | L93: =_xlfn.LET( _xlpm.c,C93,_xlpm.e,E93,_xlpm.f,F93,_xlpm.h,H93, IF( ISNUMBER(MATCH(_xlpm.c,{"Abstract Class","Class"},0)), _xlfn.XLOOKUP(_xlpm.e,Class!E:E,Class!K:K,""), IF(ISNUMBER(MATCH(_xlpm.c,{"Composition","Reference Association","Specialization"},0)), _xlfn.XLOOKUP(_xlpm.h,Class!E:E,Class!K:K,""), _xlfn.XLOOKUP(_xlpm.f,Property!F:F,Property!K:K,"") ) ) ) -> btx
A94: 93 | B94: 2 | C94: Attribute | E94: Detail_ Party | F94: Detail_ Party Name | G94: String | I94: 0..1 | J94: Name of the party | K94: btx | L94: =_xlfn.LET( _xlpm.c,C94,_xlpm.e,E94,_xlpm.f,F94,_xlpm.h,H94, IF( ISNUMBER(MATCH(_xlpm.c,{"Abstract Class","Class"},0)), _xlfn.XLOOKUP(_xlpm.e,Class!E:E,Class!K:K,""), IF(ISNUMBER(MATCH(_xlpm.c,{"Composition","Reference Association","Specialization"},0)), _xlfn.XLOOKUP(_xlpm.h,Class!E:E,Class!K:K,""), _xlfn.XLOOKUP(_xlpm.f,Property!F:F,Property!K:K,"") ) ) ) -> btx
A95: 94 | B95: 2 | C95: Attribute | E95: Detail_ Party | F95: Detail_ Party Business Description | G95: String | I95: 0..1 | J95: Description of the nature of the business of the party. | K95: btx | L95: =_xlfn.LET( _xlpm.c,C95,_xlpm.e,E95,_xlpm.f,F95,_xlpm.h,H95, IF( ISNUMBER(MATCH(_xlpm.c,{"Abstract Class","Class"},0)), _xlfn.XLOOKUP(_xlpm.e,Class!E:E,Class!K:K,""), IF(ISNUMBER(MATCH(_xlpm.c,{"Composition","Reference Association","Specialization"},0)), _xlfn.XLOOKUP(_xlpm.h,Class!E:E,Class!K:K,""), _xlfn.XLOOKUP(_xlpm.f,Property!F:F,Property!K:K,"") ) ) ) -> btx
A96: 95 | B96: 2 | C96: Reference Association | E96: Detail_ Party | F96: Detail_ Party | H96: Authority Registered Identifier | I96: 0..* | J96: Class which contains various identifiers for theparty. | K96: cor | L96: =_xlfn.LET( _xlpm.c,C96,_xlpm.e,E96,_xlpm.f,F96,_xlpm.h,H96, IF( ISNUMBER(MATCH(_xlpm.c,{"Abstract Class","Class"},0)), _xlfn.XLOOKUP(_xlpm.e,Class!E:E,Class!K:K,""), IF(ISNUMBER(MATCH(_xlpm.c,{"Composition","Reference Association","Specialization"},0)), _xlfn.XLOOKUP(_xlpm.h,Class!E:E,Class!K:K,""), _xlfn.XLOOKUP(_xlpm.f,Property!F:F,Property!K:K,"") ) ) ) -> cor
A97: 96 | B97: 2 | C97: Composition | E97: Detail_ Party | F97: Detail_ Party | H97: Communication | I97: 0..* | J97: The exchange of messages or information between parties using a specified communication channel. | K97: bus | L97: =_xlfn.LET( _xlpm.c,C97,_xlpm.e,E97,_xlpm.f,F97,_xlpm.h,H97, IF( ISNUMBER(MATCH(_xlpm.c,{"Abstract Class","Class"},0)), _xlfn.XLOOKUP(_xlpm.e,Class!E:E,Class!K:K,""), IF(ISNUMBER(MATCH(_xlpm.c,{"Composition","Reference Association","Specialization"},0)), _xlfn.XLOOKUP(_xlpm.h,Class!E:E,Class!K:K,""), _xlfn.XLOOKUP(_xlpm.f,Property!F:F,Property!K:K,"") ) ) ) -> bus
A98: 97 | B98: 2 | C98: Composition | E98: Detail_ Party | F98: Detail_ Party | H98: Address | I98: 0..* | J98: Address class for the party | K98: bus | L98: =_xlfn.LET( _xlpm.c,C98,_xlpm.e,E98,_xlpm.f,F98,_xlpm.h,H98, IF( ISNUMBER(MATCH(_xlpm.c,{"Abstract Class","Class"},0)), _xlfn.XLOOKUP(_xlpm.e,Class!E:E,Class!K:K,""), IF(ISNUMBER(MATCH(_xlpm.c,{"Composition","Reference Association","Specialization"},0)), _xlfn.XLOOKUP(_xlpm.h,Class!E:E,Class!K:K,""), _xlfn.XLOOKUP(_xlpm.f,Property!F:F,Property!K:K,"") ) ) ) -> bus
A99: 98 | B99: 2 | C99: Composition | E99: Detail_ Party | F99: Detail_ Party | H99: Contact | I99: 0..* | J99: Information about contacts. | K99: bus | L99: =_xlfn.LET( _xlpm.c,C99,_xlpm.e,E99,_xlpm.f,F99,_xlpm.h,H99, IF( ISNUMBER(MATCH(_xlpm.c,{"Abstract Class","Class"},0)), _xlfn.XLOOKUP(_xlpm.e,Class!E:E,Class!K:K,""), IF(ISNUMBER(MATCH(_xlpm.c,{"Composition","Reference Association","Specialization"},0)), _xlfn.XLOOKUP(_xlpm.h,Class!E:E,Class!K:K,""), _xlfn.XLOOKUP(_xlpm.f,Property!F:F,Property!K:K,"") ) ) ) -> bus
A100: 99 | B100: 2 | C100: Attribute | E100: Detail_ Party | F100: Detail Party Business Description | G100: String | I100: 0..1 | J100: Description of the nature of the business of the entity. | K100: btx | L100: =_xlfn.LET( _xlpm.c,C100,_xlpm.e,E100,_xlpm.f,F100,_xlpm.h,H100, IF( ISNUMBER(MATCH(_xlpm.c,{"Abstract Class","Class"},0)), _xlfn.XLOOKUP(_xlpm.e,Class!E:E,Class!K:K,""), IF(ISNUMBER(MATCH(_xlpm.c,{"Composition","Reference Association","Specialization"},0)), _xlfn.XLOOKUP(_xlpm.h,Class!E:E,Class!K:K,""), _xlfn.XLOOKUP(_xlpm.f,Property!F:F,Property!K:K,"") ) ) ) -> btx
...

Sheet Sheet5
A1: seq | B1: level | C1: Property type | D1: Identifier | E1: Class | F1: Property Term | G1: BaseType | H1: Associated Class | I1: Multiplicity | J1: Detail_ | K1: module | L1: LocalLabel | M1: LocalDocumentation
A2: seq | B2: level | C2: Property type | D2: Identifier | E2: Class | F2: Property Term | G2: BaseType | H2: Associated Class | I2: Multiplicity | J2: Definition | K2: module | L2: LocalLabel | M2: LocalDocumentation
A3: 1 | B3: 1 | C3: Class | E3: Reference Document | I3: 0..* | J3: Document reference used for business transactions. A written, printed, or electronic document that is referenced in a business transaction, such as an order, invoice, delivery note, or contract. | K3: fsm | L3: 参照文書 | M3: 業務取引において参照される文書（注文書、請求書、納品書、契約書等）
A4: 2 | B4: 2 | C4: Attribute(PK) | D4: PK | E4: Reference Document | F4: Reference Document ID | G4: String | I4: 0..1 | J4: An identifier assigned by the issuer to uniquely identify the referenced document. | K4: fsm | L4: 参照文書識別子 | M4: 発行者により付与された参照文書の識別子
A5: 3 | B5: 2 | C5: Attribute | E5: Reference Document | F5: Reference Document Type Code | G5: Code | I5: 0..1 | J5: A code specifying the type of the referenced document, such as order, invoice, or shipment document. | K5: fsm | L5: 参照文書種別コード | M5: 参照文書の種別を示すコード（例：注文書、請求書、出荷指示等）
A6: 4 | B6: 2 | C6: Attribute | E6: Reference Document | F6: Reference Document Issue Date Time | G6: Date Time | I6: 0..1 | J6: The date and time at which the referenced document was issued. | K6: fsm | L6: 参照文書発行日時 | M6: 参照文書が発行された日付および時刻
A7: 5 | B7: 2 | C7: Reference Association | E7: Reference Document | F7: Reference Document Issuer Party | H7: Party | I7: 0..1 | J7: A reference to the party that issued the referenced document. | K7: fsm | L7: 参照文書発行者 | M7: 参照文書を発行した取引主体への参照
A8: 6 | B8: 2 | C8: Composition | E8: Reference Document | F8: Reference Document Line | H8: Reference Document Line | I8: 0..* | J8: A composition association to the lines contained within the referenced document. | K8: fsm | L8: 参照文書行 | M8: 参照文書に含まれる明細行
A9: 7 | B9: 1 | C9: Class | E9: Reference Document Line | I9: 0..* | J9: A referenced line within a referenced document. A line item within a referenced document, used for line-level traceability in business transactions. | K9: fsm | L9: 参照文書行 | M9: 参照文書内の個々の明細行
A10: 8 | B10: 2 | C10: Attribute(PK) | D10: PK | E10: Reference Document Line | F10: Reference Document Line ID | G10: String | I10: 0..1 | J10: An identifier that uniquely identifies a line within the referenced document. | K10: fsm | L10: 参照文書行識別子 | M10: 参照文書内の行を識別するための識別子（行番号等）
A11: 9 | B11: 2 | C11: Attribute | E11: Reference Document Line | F11: Reference Document Line Issue Date Time | G11: Date Time | I11: 0..1 | J11: The date and time at which the referenced document line was issued or became effective. | K11: fsm | L11: 参照文書行発行日時 | M11: 参照文書行が発行または確定した日付および時刻
A12: 10 | B12: 2 | C12: Attribute | E12: Reference Document Line | F12: Reference Document Line Status Code | G12: Code | I12: 0..1 | J12: A code specifying the status of the referenced document line, such as active, changed, or cancelled. | K12: fsm | L12: 参照文書行状態コード | M12: 参照文書行の状態を示すコード（有効、取消、変更等）
A13: 11 | B13: 2 | C13: Attribute | E13: Reference Document Line | F13: Reference Document Parent Line ID | G13: String | I13: 0..1 | J13: An identifier of the parent line to which this referenced document line is hierarchically related. | K13: fsm | L13: 親行識別子 | M13: 当該参照文書行の親となる行の識別子
